Workbook
Name Slicer_Date: #N/A
Name Slicer_Date1: #N/A
Name Slicer_Party: #N/A
Name Slicer_Party_Name: #N/A
Name Slicer_Party_Name1: #N/A
Name Slicer_Party_Name2: #N/A
Name Slicer_Person: #N/A
Name Slicer_Shipment_Number: #N/A

Sheet Billing
B1: Party Name | C1: Tiyaar | D1: Rate | E1: Total | G1: Billing
B2: =B49 -> BSC | C2: =SUMIFS(ledger!G:G, ledger!B:B, B2, ledger!E:E, "<>*RD*") / 1.0936 -> 200789.03 | D2: 10 | E2: =(SUMIFS(ledger!G:G, ledger!B:B, B2, ledger!E:E, "<>*RD*",ledger!D:D, "Silky") / 1.0936)*12 + (SUMIFS(ledger!G:G, ledger!B:B, B2, ledger!E:E, "<>*RD*",ledger!D:D, "Chamki") / 1.0936)*10 -> 1579608.6 | I2: BSC | Q2: Billing Total
B3: =B50 -> Ejaz Sahab | C3: =SUMIFS(ledger!G:G, ledger!B:B, B3, ledger!E:E, "<>*RD*") / 1.0936 -> 34084.674 | D3: 10 | E3: =(SUMIFS(ledger!G:G, ledger!B:B, B3, ledger!E:E, "<>*RD*",ledger!D:D, "Silky") / 1.0936)*12 + (SUMIFS(ledger!G:G, ledger!B:B, B3, ledger!E:E, "<>*RD*",ledger!D:D, "Chamki") / 1.0936)*10 -> 409016.09 | I3: Ejaz Sahab
B4: =B51 -> Arshad | C4: =SUMIFS(ledger!G:G, ledger!B:B, B4, ledger!E:E, "<>*RD*") / 1.0936 -> 66135.699 | D4: 10 | E4: =(SUMIFS(ledger!G:G, ledger!B:B, B4, ledger!E:E, "<>*RD*",ledger!D:D, "Silky") / 1.0936)*12 + (SUMIFS(ledger!G:G, ledger!B:B, B4, ledger!E:E, "<>*RD*",ledger!D:D, "Chamki") / 1.0936)*10 -> 687011.7 | I4: Arshad | R4: Gaz | S4: Total Metres | T4: Total Chamki | U4: Total Super Silky | V4: Billing (Chamki/Crinkle) | W4: Billing (Super Chamki) | X4: Billing (Slub) | Y4: Billing (Satin) | Z4: Billing (Black-chamki) | AA4: Billing (Kataan) | AB4: Billing (Munaar) | AC4: Adjusted Bill | AD4: Amount Paid | AE4: Balance | AF4: Rate (Chamki) | AG4: Rate (Super Silky)
B5: =B52 -> Shehzad Kamoki | C5: =SUMIFS(ledger!G:G, ledger!B:B, B5, ledger!E:E, "<>*RD*") / 1.0936 -> 8092.5384 | D5: 10.5 | E5: =(SUMIFS(ledger!G:G, ledger!B:B, B5, ledger!E:E, "<>*RD*",ledger!D:D, "Silky") / 1.0936)*12 + (SUMIFS(ledger!G:G, ledger!B:B, B5, ledger!E:E, "<>*RD*",ledger!D:D, "Chamki") / 1.0936)*10.5 -> 84971.653 | I5: Shehzad Kamoki | Q5: {=_xlfn.UNIQUE(Table1[Party Name])} -> BSC | R5: {=_xlfn.BYROW(B49,_xlfn.LAMBDA(_xlpm.party,SUMIFS(ledger!G:G,ledger!B:B,_xlpm.party,ledger!E:E,"<>*RD*")))+_xlfn.IFNA(C84,0)} -> 2754521.9 | S5: {=_xlfn.BYROW(B49, _xlfn.LAMBDA(_xlpm.party, SUMIFS(ledger!G:G, ledger!B:B, _xlpm.party, ledger!E:E, "<>*RD*") / 1.0936 ))+_xlfn.IFNA(D84,0)} -> 2518765.4 | T5: {=(_xlfn.BYROW(B49,_xlfn.LAMBDA(_xlpm.party,SUMIFS(ledger!G:G,ledger!B:B,_xlpm.party,ledger!E:E,"<>*RD*",ledger!D:D,"Chamki")+SUMIFS(ledger!G:G, ledger!B:B, _xlpm.party, ledger!E:E, "<>*RD*", ledger!D:D, "Crinkle")))/1.0936)+_xlfn.IFNA(E84,0)} -> 2236296.5 | U5: {=(_xlfn.BYROW(B49,_xlfn.LAMBDA(_xlpm.party,SUMIFS(ledger!G:G,ledger!B:B,_xlpm.party,ledger!E:E,"<>*RD*",ledger!D:D,"Silky")))/1.0936)+_xlfn.IFNA(F84,0)} -> 282468.91 | V5: {=(_xlfn.BYROW(B49,_xlfn.LAMBDA(_xlpm.party, (SUMIFS(ledger!J:J,ledger!B:B,_xlpm.party,ledger!E:E,"<>*RD*",ledger!D:D,"Chamki",ledger!C:C,"<>November Closing CF")+ SUMIFS(ledger!J:J,ledger!B:B,_xlpm.party,ledger!E:E,"<>*RD*",ledger!D:D,"Crinkle",ledger!C:C,"<>November Closing CF") )+_xlfn.IFNA(G84,0))))} -> 22362965 | W5: {=_xlfn.BYROW(B49, _xlfn.LAMBDA(_xlpm.party, SUMIFS(ledger!J:J, ledger!B:B, _xlpm.party, ledger!E:E, "<>*RD*", ledger!D:D, "Silky", ledger!C:C, "<>November Closing CF") )) + _xlfn.IFNA(H84, 0)} -> 3583739.9 | X5: {=_xlfn.BYROW(B49, _xlfn.LAMBDA(_xlpm.party, SUMIFS(ledger!J:J, ledger!B:B, _xlpm.party, ledger!E:E, "<>*RD*", ledger!D:D, "Slub", ledger!C:C, "<>November Closing CF") ))+ _xlfn.IFNA(I84, 0)} -> 0 | Y5: {=_xlfn.BYROW(B49, _xlfn.LAMBDA(_xlpm.party, SUMIFS(ledger!J:J, ledger!B:B, _xlpm.party, ledger!E:E, "<>*RD*", ledger!D:D, "Satin", ledger!C:C, "<>November Closing CF") ))+ _xlfn.IFNA(J84, 0)} -> 0 | Z5: {=_xlfn.BYROW(B49, _xlfn.LAMBDA(_xlpm.party, SUMIFS(ledger!J:J, ledger!B:B, _xlpm.party, ledger!E:E, "<>*RD*", ledger!D:D, "Black-Chamki", ledger!C:C, "<>November Closing CF") ))+ _xlfn.IFNA(K84, 0)} -> 0 | AA5: {=_xlfn.BYROW(B49, _xlfn.LAMBDA(_xlpm.party, SUMIFS(ledger!J:J, ledger!B:B, _xlpm.party, ledger!E:E, "<>*RD*", ledger!D:D, "Kataan", ledger!C:C, "<>November Closing CF") ))+ _xlfn.IFNA(L84, 0)} -> 0 | AB5: {=_xlfn.BYROW(B49, _xlfn.LAMBDA(_xlpm.party, SUMIFS(ledger!J:J, ledger!B:B, _xlpm.party, ledger!E:E, "<>*RD*", ledger!D:D, "Munaar", ledger!C:C, "<>November Closing CF") ))+ _xlfn.IFNA(M84, 0)} -> 0 | AC5: =V5+W5+X5+Y5+Z5+AA5+AB5 -> 25946705 | AD5: =(SUMIF(Table14[Party],Q5,Table14[Credit]))+_xlfn.IFNA(O84,0) -> 19750734 | AE5: =AC5-AD5 -> 6195971.2 | AF5: 10 | AG5: 13
B6: =B53 -> Sufi Nawaz Sahab | C6: =SUMIFS(ledger!G:G, ledger!B:B, B6, ledger!E:E, "<>*RD*") / 1.0936 -> 23995.977 | D6: 10 | E6: =((SUMIFS(ledger!G:G, ledger!B:B, B6, ledger!E:E, "<>*RD*",ledger!D:D, "Silky") / 1.0936) *12) + ((SUMIFS(ledger!G:G, ledger!B:B, B6, ledger!E:E, "<>*RD*",ledger!D:D, "Chamki") / 1.0936)* 9) -> 0 | I6: Sufi Nawaz Sahab | Q6: Ejaz Sahab | R6: {=_xlfn.BYROW(B50,_xlfn.LAMBDA(_xlpm.party,SUMIFS(ledger!G:G,ledger!B:B,_xlpm.party,ledger!E:E,"<>*RD*")))+_xlfn.IFNA(C85,0)} -> 430669 | S6: {=_xlfn.BYROW(B50, _xlfn.LAMBDA(_xlpm.party, SUMIFS(ledger!G:G, ledger!B:B, _xlpm.party, ledger!E:E, "<>*RD*") / 1.0936 ))+_xlfn.IFNA(D85,0)} -> 393808.52 | T6: {=(_xlfn.BYROW(B50,_xlfn.LAMBDA(_xlpm.party,SUMIFS(ledger!G:G,ledger!B:B,_xlpm.party,ledger!E:E,"<>*RD*",ledger!D:D,"Chamki")+SUMIFS(ledger!G:G, ledger!B:B, _xlpm.party, ledger!E:E, "<>*RD*", ledger!D:D, "Crinkle")))/1.0936)+_xlfn.IFNA(E85,0)} -> 148145.57 | U6: {=(_xlfn.BYROW(B50,_xlfn.LAMBDA(_xlpm.party,SUMIFS(ledger!G:G,ledger!B:B,_xlpm.party,ledger!E:E,"<>*RD*",ledger!D:D,"Silky")))/1.0936)+_xlfn.IFNA(F85,0)} -> 245662.95 | V6: {=(_xlfn.BYROW(B50,_xlfn.LAMBDA(_xlpm.party, (SUMIFS(ledger!J:J,ledger!B:B,_xlpm.party,ledger!E:E,"<>*RD*",ledger!D:D,"Chamki",ledger!C:C,"<>November Closing CF")+ SUMIFS(ledger!J:J,ledger!B:B,_xlpm.party,ledger!E:E,"<>*RD*",ledger!D:D,"Crinkle",ledger!C:C,"<>November Closing CF") )+_xlfn.IFNA(G85,0))))} -> 1481455.7 | W6: {=_xlfn.BYROW(B50, _xlfn.LAMBDA(_xlpm.party, SUMIFS(ledger!J:J, ledger!B:B, _xlpm.party, ledger!E:E, "<>*RD*", ledger!D:D, "Silky", ledger!C:C, "<>November Closing CF") )) + _xlfn.IFNA(H85, 0)} -> 3134474.2 | X6: {=_xlfn.BYROW(B50, _xlfn.LAMBDA(_xlpm.party, SUMIFS(ledger!J:J, ledger!B:B, _xlpm.party, ledger!E:E, "<>*RD*", ledger!D:D, "Slub", ledger!C:C, "<>November Closing CF") ))+ _xlfn.IFNA(I85, 0)} -> 0 | Y6: {=_xlfn.BYROW(B50, _xlfn.LAMBDA(_xlpm.party, SUMIFS(ledger!J:J, ledger!B:B, _xlpm.party, ledger!E:E, "<>*RD*", ledger!D:D, "Satin", ledger!C:C, "<>November Closing CF") ))+ _xlfn.IFNA(J85, 0)} -> 0 | Z6: {=_xlfn.BYROW(B50, _xlfn.LAMBDA(_xlpm.party, SUMIFS(ledger!J:J, ledger!B:B, _xlpm.party, ledger!E:E, "<>*RD*", ledger!D:D, "Black-Chamki", ledger!C:C, "<>November Closing CF") ))+ _xlfn.IFNA(K85, 0)} -> 0 | AA6: {=_xlfn.BYROW(B50, _xlfn.LAMBDA(_xlpm.party, SUMIFS(ledger!J:J, ledger!B:B, _xlpm.party, ledger!E:E, "<>*RD*", ledger!D:D, "Kataan", ledger!C:C, "<>November Closing CF") ))+ _xlfn.IFNA(L85, 0)} -> 0 | AB6: {=_xlfn.BYROW(B50, _xlfn.LAMBDA(_xlpm.party, SUMIFS(ledger!J:J, ledger!B:B, _xlpm.party, ledger!E:E, "<>*RD*", ledger!D:D, "Munaar", ledger!C:C, "<>November Closing CF") ))+ _xlfn.IFNA(M85, 0)} -> 0 | AC6: =V6+W6+X6+Y6+Z6+AA6+AB6 -> 4615930 | AD6: =(SUMIF(Table14[Party],Q6,Table14[Credit]))+_xlfn.IFNA(O85,0) -> 4371992 | AE6: =AC6-AD6 -> 243937.96 | AF6: 10 | AG6: 13
B7: =B54 -> Sajad Khan | C7: =SUMIFS(ledger!G:G, ledger!B:B, B7, ledger!E:E, "<>*RD*") / 1.0936 -> 0 | D7: 10 | E7: {=(SUMIFS(ledger!G:G, ledger!B:B, B7, ledger!E:E, "<>*RD*",ledger!D:D, "Silky") / 1.0936)*12 + (SUMIFS(ledger!G:G, ledger!B:B, B7, ledger!E:E, "<>*RD*",ledger!D:D, "Chamki") / 1.0936)*10 +(SUMIFS(ledger!G:G, ledger!B:B, party, ledger!E:E, "<>*RD*", ledger!D:D, "Crinkle")/ 1.0936)*10} -> 0 | I7: Sajad Khan | Q7: Arshad | R7: {=_xlfn.BYROW(B51,_xlfn.LAMBDA(_xlpm.party,SUMIFS(ledger!G:G,ledger!B:B,_xlpm.party,ledger!E:E,"<>*RD*")))+_xlfn.IFNA(C86,0)} -> 729474 | S7: {=_xlfn.BYROW(B51, _xlfn.LAMBDA(_xlpm.party, SUMIFS(ledger!G:G, ledger!B:B, _xlpm.party, ledger!E:E, "<>*RD*") / 1.0936 ))+_xlfn.IFNA(D86,0)} -> 667039.14 | T7: {=(_xlfn.BYROW(B51,_xlfn.LAMBDA(_xlpm.party,SUMIFS(ledger!G:G,ledger!B:B,_xlpm.party,ledger!E:E,"<>*RD*",ledger!D:D,"Chamki")+SUMIFS(ledger!G:G, ledger!B:B, _xlpm.party, ledger!E:E, "<>*RD*", ledger!D:D, "Crinkle")))/1.0936)+_xlfn.IFNA(E86,0)} -> 576099.12 | U7: {=(_xlfn.BYROW(B51,_xlfn.LAMBDA(_xlpm.party,SUMIFS(ledger!G:G,ledger!B:B,_xlpm.party,ledger!E:E,"<>*RD*",ledger!D:D,"Silky")))/1.0936)+_xlfn.IFNA(F86,0)} -> 90940.015 | V7: {=(_xlfn.BYROW(B51,_xlfn.LAMBDA(_xlpm.party, (SUMIFS(ledger!J:J,ledger!B:B,_xlpm.party,ledger!E:E,"<>*RD*",ledger!D:D,"Chamki",ledger!C:C,"<>November Closing CF")+ SUMIFS(ledger!J:J,ledger!B:B,_xlpm.party,ledger!E:E,"<>*RD*",ledger!D:D,"Crinkle",ledger!C:C,"<>November Closing CF") )+_xlfn.IFNA(G86,0))))} -> 5760991.2 | W7: {=_xlfn.BYROW(B51, _xlfn.LAMBDA(_xlpm.party, SUMIFS(ledger!J:J, ledger!B:B, _xlpm.party, ledger!E:E, "<>*RD*", ledger!D:D, "Silky", ledger!C:C, "<>November Closing CF") )) + _xlfn.IFNA(H86, 0)} -> 1167425.9 | X7: {=_xlfn.BYROW(B51, _xlfn.LAMBDA(_xlpm.party, SUMIFS(ledger!J:J, ledger!B:B, _xlpm.party, ledger!E:E, "<>*RD*", ledger!D:D, "Slub", ledger!C:C, "<>November Closing CF") ))+ _xlfn.IFNA(I86, 0)} -> 0 | Y7: {=_xlfn.BYROW(B51, _xlfn.LAMBDA(_xlpm.party, SUMIFS(ledger!J:J, ledger!B:B, _xlpm.party, ledger!E:E, "<>*RD*", ledger!D:D, "Satin", ledger!C:C, "<>November Closing CF") ))+ _xlfn.IFNA(J86, 0)} -> 0 | Z7: {=_xlfn.BYROW(B51, _xlfn.LAMBDA(_xlpm.party, SUMIFS(ledger!J:J, ledger!B:B, _xlpm.party, ledger!E:E, "<>*RD*", ledger!D:D, "Black-Chamki", ledger!C:C, "<>November Closing CF") ))+ _xlfn.IFNA(K86, 0)} -> 0 | AA7: {=_xlfn.BYROW(B51, _xlfn.LAMBDA(_xlpm.party, SUMIFS(ledger!J:J, ledger!B:B, _xlpm.party, ledger!E:E, "<>*RD*", ledger!D:D, "Kataan", ledger!C:C, "<>November Closing CF") ))+ _xlfn.IFNA(L86, 0)} -> 0 | AB7: {=_xlfn.BYROW(B51, _xlfn.LAMBDA(_xlpm.party, SUMIFS(ledger!J:J, ledger!B:B, _xlpm.party, ledger!E:E, "<>*RD*", ledger!D:D, "Munaar", ledger!C:C, "<>November Closing CF") ))+ _xlfn.IFNA(M86, 0)} -> 0 | AC7: =V7+W7+X7+Y7+Z7+AA7+AB7 -> 6928417.2 | AD7: =(SUMIF(Table14[Party],Q7,Table14[Credit]))+_xlfn.IFNA(O86,0) -> 6705301 | AE7: =AC7-AD7 -> 223116.15 | AF7: 10 | AG7: 13
B8: =B55 -> Raaz Fabrics | C8: =SUMIFS(ledger!G:G, ledger!B:B, B8, ledger!E:E, "<>*RD*") / 1.0936 -> 23250.732 | D8: 10 | E8: =(SUMIFS(ledger!G:G, ledger!B:B, B8, ledger!E:E, "<>*RD*",ledger!D:D, "Silky") / 1.0936)*12 + (SUMIFS(ledger!G:G, ledger!B:B, B8, ledger!E:E, "<>*RD*",ledger!D:D, "chamki") / 1.0936)*10 +(SUMIFS(ledger!G:G, ledger!B:B, B8, ledger!E:E, "<>*RD*",ledger!D:D, "Crinkle") / 1.0936)*10 -> 232507.32 | I8: Raaz Fabrics | Q8: Shehzad Kamoki | R8: {=_xlfn.BYROW(B52,_xlfn.LAMBDA(_xlpm.party,SUMIFS(ledger!G:G,ledger!B:B,_xlpm.party,ledger!E:E,"<>*RD*")))+_xlfn.IFNA(C87,0)} -> 143457 | S8: {=_xlfn.BYROW(B52, _xlfn.LAMBDA(_xlpm.party, SUMIFS(ledger!G:G, ledger!B:B, _xlpm.party, ledger!E:E, "<>*RD*") / 1.0936 ))+_xlfn.IFNA(D87,0)} -> 131178.68 | T8: {=(_xlfn.BYROW(B52,_xlfn.LAMBDA(_xlpm.party,SUMIFS(ledger!G:G,ledger!B:B,_xlpm.party,ledger!E:E,"<>*RD*",ledger!D:D,"Chamki")+SUMIFS(ledger!G:G, ledger!B:B, _xlpm.party, ledger!E:E, "<>*RD*", ledger!D:D, "Crinkle")))/1.0936)+_xlfn.IFNA(E87,0)} -> 131178.68 | U8: {=(_xlfn.BYROW(B52,_xlfn.LAMBDA(_xlpm.party,SUMIFS(ledger!G:G,ledger!B:B,_xlpm.party,ledger!E:E,"<>*RD*",ledger!D:D,"Silky")))/1.0936)+_xlfn.IFNA(F87,0)} -> 0 | V8: {=(_xlfn.BYROW(B52,_xlfn.LAMBDA(_xlpm.party, (SUMIFS(ledger!J:J,ledger!B:B,_xlpm.party,ledger!E:E,"<>*RD*",ledger!D:D,"Chamki",ledger!C:C,"<>November Closing CF")+ SUMIFS(ledger!J:J,ledger!B:B,_xlpm.party,ledger!E:E,"<>*RD*",ledger!D:D,"Crinkle",ledger!C:C,"<>November Closing CF") )+_xlfn.IFNA(G87,0))))} -> 1354242 | W8: {=_xlfn.BYROW(B52, _xlfn.LAMBDA(_xlpm.party, SUMIFS(ledger!J:J, ledger!B:B, _xlpm.party, ledger!E:E, "<>*RD*", ledger!D:D, "Silky", ledger!C:C, "<>November Closing CF") )) + _xlfn.IFNA(H87, 0)} -> 0 | X8: {=_xlfn.BYROW(B52, _xlfn.LAMBDA(_xlpm.party, SUMIFS(ledger!J:J, ledger!B:B, _xlpm.party, ledger!E:E, "<>*RD*", ledger!D:D, "Slub", ledger!C:C, "<>November Closing CF") ))+ _xlfn.IFNA(I87, 0)} -> 0 | Y8: {=_xlfn.BYROW(B52, _xlfn.LAMBDA(_xlpm.party, SUMIFS(ledger!J:J, ledger!B:B, _xlpm.party, ledger!E:E, "<>*RD*", ledger!D:D, "Satin", ledger!C:C, "<>November Closing CF") ))+ _xlfn.IFNA(J87, 0)} -> 0 | Z8: {=_xlfn.BYROW(B52, _xlfn.LAMBDA(_xlpm.party, SUMIFS(ledger!J:J, ledger!B:B, _xlpm.party, ledger!E:E, "<>*RD*", ledger!D:D, "Black-Chamki", ledger!C:C, "<>November Closing CF") ))+ _xlfn.IFNA(K87, 0)} -> 0 | AA8: {=_xlfn.BYROW(B52, _xlfn.LAMBDA(_xlpm.party, SUMIFS(ledger!J:J, ledger!B:B, _xlpm.party, ledger!E:E, "<>*RD*", ledger!D:D, "Kataan", ledger!C:C, "<>November Closing CF") ))+ _xlfn.IFNA(L87, 0)} -> 0 | AB8: {=_xlfn.BYROW(B52, _xlfn.LAMBDA(_xlpm.party, SUMIFS(ledger!J:J, ledger!B:B, _xlpm.party, ledger!E:E, "<>*RD*", ledger!D:D, "Munaar", ledger!C:C, "<>November Closing CF") ))+ _xlfn.IFNA(M87, 0)} -> 0 | AC8: =V8+W8+X8+Y8+Z8+AA8+AB8 -> 1354242 | AD8: =(SUMIF(Table14[Party],Q8,Table14[Credit]))+_xlfn.IFNA(O87,0) -> 1353710 | AE8: =AC8-AD8 -> 531.99729 | AF8: 10.5 | AG8: 13
B9: =B56 -> Azam | C9: =SUMIFS(ledger!G:G, ledger!B:B, B9, ledger!E:E, "<>*RD*") / 1.0936 -> 94839.978 | D9: 10 | E9: =(SUMIFS(ledger!G:G, ledger!B:B, B9, ledger!E:E, "<>*RD*",ledger!D:D, "Silky") / 1.0936)*12 + (SUMIFS(ledger!G:G, ledger!B:B, B9, ledger!E:E, "<>*RD*",ledger!D:D, "Chamki") / 1.0936)*10 -> 948399.78 | I9: Azam | Q9: Sufi Nawaz Sahab | R9: {=_xlfn.BYROW(B53,_xlfn.LAMBDA(_xlpm.party,SUMIFS(ledger!G:G,ledger!B:B,_xlpm.party,ledger!E:E,"<>*RD*")))+_xlfn.IFNA(C88,0)} -> 1212967 | S9: {=_xlfn.BYROW(B53, _xlfn.LAMBDA(_xlpm.party, SUMIFS(ledger!G:G, ledger!B:B, _xlpm.party, ledger!E:E, "<>*RD*") / 1.0936 ))+_xlfn.IFNA(D88,0)} -> 1109150.5 | T9: {=(_xlfn.BYROW(B53,_xlfn.LAMBDA(_xlpm.party,SUMIFS(ledger!G:G,ledger!B:B,_xlpm.party,ledger!E:E,"<>*RD*",ledger!D:D,"Chamki")+SUMIFS(ledger!G:G, ledger!B:B, _xlpm.party, ledger!E:E, "<>*RD*", ledger!D:D, "Crinkle")))/1.0936)+_xlfn.IFNA(E88,0)} -> 599330.65 | U9: {=(_xlfn.BYROW(B53,_xlfn.LAMBDA(_xlpm.party,SUMIFS(ledger!G:G,ledger!B:B,_xlpm.party,ledger!E:E,"<>*RD*",ledger!D:D,"Silky")))/1.0936)+_xlfn.IFNA(F88,0)} -> 485823.88 | V9: {=(_xlfn.BYROW(B53,_xlfn.LAMBDA(_xlpm.party, (SUMIFS(ledger!J:J,ledger!B:B,_xlpm.party,ledger!E:E,"<>*RD*",ledger!D:D,"Chamki",ledger!C:C,"<>November Closing CF")+ SUMIFS(ledger!J:J,ledger!B:B,_xlpm.party,ledger!E:E,"<>*RD*",ledger!D:D,"Crinkle",ledger!C:C,"<>November Closing CF") )+_xlfn.IFNA(G88,0))))} -> 5408917.9 | W9: {=_xlfn.BYROW(B53, _xlfn.LAMBDA(_xlpm.party, SUMIFS(ledger!J:J, ledger!B:B, _xlpm.party, ledger!E:E, "<>*RD*", ledger!D:D, "Silky", ledger!C:C, "<>November Closing CF") )) + _xlfn.IFNA(H88, 0)} -> 5829886.6 | X9: {=_xlfn.BYROW(B53, _xlfn.LAMBDA(_xlpm.party, SUMIFS(ledger!J:J, ledger!B:B, _xlpm.party, ledger!E:E, "<>*RD*", ledger!D:D, "Slub", ledger!C:C, "<>November Closing CF") ))+ _xlfn.IFNA(I88, 0)} -> 0 | Y9: {=_xlfn.BYROW(B53, _xlfn.LAMBDA(_xlpm.party, SUMIFS(ledger!J:J, ledger!B:B, _xlpm.party, ledger!E:E, "<>*RD*", ledger!D:D, "Satin", ledger!C:C, "<>November Closing CF") ))+ _xlfn.IFNA(J88, 0)} -> 239959.77 | Z9: {=_xlfn.BYROW(B53, _xlfn.LAMBDA(_xlpm.party, SUMIFS(ledger!J:J, ledger!B:B, _xlpm.party, ledger!E:E, "<>*RD*", ledger!D:D, "Black-Chamki", ledger!C:C, "<>November Closing CF") ))+ _xlfn.IFNA(K88, 0)} -> 0 | AA9: {=_xlfn.BYROW(B53, _xlfn.LAMBDA(_xlpm.party, SUMIFS(ledger!J:J, ledger!B:B, _xlpm.party, ledger!E:E, "<>*RD*", ledger!D:D, "Kataan", ledger!C:C, "<>November Closing CF") ))+ _xlfn.IFNA(L88, 0)} -> 0 | AB9: {=_xlfn.BYROW(B53, _xlfn.LAMBDA(_xlpm.party, SUMIFS(ledger!J:J, ledger!B:B, _xlpm.party, ledger!E:E, "<>*RD*", ledger!D:D, "Munaar", ledger!C:C, "<>November Closing CF") ))+ _xlfn.IFNA(M88, 0)} -> 0 | AC9: =V9+W9+X9+Y9+Z9+AA9+AB9 -> 11478764 | AD9: =(SUMIF(Table14[Party],Q9,Table14[Credit]))+_xlfn.IFNA(O88,0) -> 11478764 | AE9: =AC9-AD9 -> 0.23847842 | AF9: 10 | AG9: 13
B10: =B57 -> Ubaidullah | C10: =SUMIFS(ledger!G:G, ledger!B:B, B10, ledger!E:E, "<>*RD*") / 1.0936 -> 0 | D10: 10 | E10: =(SUMIFS(ledger!G:G, ledger!B:B, B10, ledger!E:E, "<>*RD*",ledger!D:D, "Silky") / 1.0936)*12 + (SUMIFS(ledger!G:G, ledger!B:B, B10, ledger!E:E, "<>*RD*",ledger!D:D, "Chamki") / 1.0936)*10 -> 0 | I10: Ubaidullah | Q10: Sajad Khan | R10: {=_xlfn.BYROW(B54,_xlfn.LAMBDA(_xlpm.party,SUMIFS(ledger!G:G,ledger!B:B,_xlpm.party,ledger!E:E,"<>*RD*")))+_xlfn.IFNA(C89,0)} -> 865551 | S10: {=_xlfn.BYROW(B54, _xlfn.LAMBDA(_xlpm.party, SUMIFS(ledger!G:G, ledger!B:B, _xlpm.party, ledger!E:E, "<>*RD*") / 1.0936 ))+_xlfn.IFNA(D89,0)} -> 791469.46 | T10: {=(_xlfn.BYROW(B54,_xlfn.LAMBDA(_xlpm.party,SUMIFS(ledger!G:G,ledger!B:B,_xlpm.party,ledger!E:E,"<>*RD*",ledger!D:D,"Chamki")+SUMIFS(ledger!G:G, ledger!B:B, _xlpm.party, ledger!E:E, "<>*RD*", ledger!D:D, "Crinkle")))/1.0936)+_xlfn.IFNA(E89,0)} -> 785980.25 | U10: {=(_xlfn.BYROW(B54,_xlfn.LAMBDA(_xlpm.party,SUMIFS(ledger!G:G,ledger!B:B,_xlpm.party,ledger!E:E,"<>*RD*",ledger!D:D,"Silky")))/1.0936)+_xlfn.IFNA(F89,0)} -> 0 | V10: {=(_xlfn.BYROW(B54,_xlfn.LAMBDA(_xlpm.party, (SUMIFS(ledger!J:J,ledger!B:B,_xlpm.party,ledger!E:E,"<>*RD*",ledger!D:D,"Chamki",ledger!C:C,"<>November Closing CF")+ SUMIFS(ledger!J:J,ledger!B:B,_xlpm.party,ledger!E:E,"<>*RD*",ledger!D:D,"Crinkle",ledger!C:C,"<>November Closing CF") )+_xlfn.IFNA(G89,0))))} -> 7859802.5 | W10: {=_xlfn.BYROW(B54, _xlfn.LAMBDA(_xlpm.party, SUMIFS(ledger!J:J, ledger!B:B, _xlpm.party, ledger!E:E, "<>*RD*", ledger!D:D, "Silky", ledger!C:C, "<>November Closing CF") )) + _xlfn.IFNA(H89, 0)} -> 0 | X10: {=_xlfn.BYROW(B54, _xlfn.LAMBDA(_xlpm.party, SUMIFS(ledger!J:J, ledger!B:B, _xlpm.party, ledger!E:E, "<>*RD*", ledger!D:D, "Slub", ledger!C:C, "<>November Closing CF") ))+ _xlfn.IFNA(I89, 0)} -> 71359.729 | Y10: {=_xlfn.BYROW(B54, _xlfn.LAMBDA(_xlpm.party, SUMIFS(ledger!J:J, ledger!B:B, _xlpm.party, ledger!E:E, "<>*RD*", ledger!D:D, "Satin", ledger!C:C, "<>November Closing CF") ))+ _xlfn.IFNA(J89, 0)} -> 0 | Z10: {=_xlfn.BYROW(B54, _xlfn.LAMBDA(_xlpm.party, SUMIFS(ledger!J:J, ledger!B:B, _xlpm.party, ledger!E:E, "<>*RD*", ledger!D:D, "Black-Chamki", ledger!C:C, "<>November Closing CF") ))+ _xlfn.IFNA(K89, 0)} -> 0 | AA10: {=_xlfn.BYROW(B54, _xlfn.LAMBDA(_xlpm.party, SUMIFS(ledger!J:J, ledger!B:B, _xlpm.party, ledger!E:E, "<>*RD*", ledger!D:D, "Kataan", ledger!C:C, "<>November Closing CF") ))+ _xlfn.IFNA(L89, 0)} -> 0 | AB10: {=_xlfn.BYROW(B54, _xlfn.LAMBDA(_xlpm.party, SUMIFS(ledger!J:J, ledger!B:B, _xlpm.party, ledger!E:E, "<>*RD*", ledger!D:D, "Munaar", ledger!C:C, "<>November Closing CF") ))+ _xlfn.IFNA(M89, 0)} -> 0 | AC10: =V10+W10+X10+Y10+Z10+AA10+AB10 -> 7931162.2 | AD10: =(SUMIF(Table14[Party],Q10,Table14[Credit]))+_xlfn.IFNA(O89,0) -> 7997871 | AE10: =AC10-AD10 -> -66708.783 | AF10: 10 | AG10: 13
B11: =B58 -> Ashraf Zia | C11: =SUMIFS(ledger!G:G, ledger!B:B, B11, ledger!E:E, "<>*RD*") / 1.0936 -> 0 | D11: 12 | E11: =(SUMIFS(ledger!G:G, ledger!B:B, B11, ledger!E:E, "<>*RD*",ledger!D:D, "Silky") / 1.0936)*12 + (SUMIFS(ledger!G:G, ledger!B:B, B11, ledger!E:E, "<>*RD*",ledger!D:D, "Chamki") / 1.0936)*10 -> 0 | I11: Ashraf Zia | Q11: Raaz Fabrics | R11: {=_xlfn.BYROW(B55,_xlfn.LAMBDA(_xlpm.party,SUMIFS(ledger!G:G,ledger!B:B,_xlpm.party,ledger!E:E,"<>*RD*")))+_xlfn.IFNA(C90,0)} -> 177861 | S11: {=_xlfn.BYROW(B55, _xlfn.LAMBDA(_xlpm.party, SUMIFS(ledger!G:G, ledger!B:B, _xlpm.party, ledger!E:E, "<>*RD*") / 1.0936 ))+_xlfn.IFNA(D90,0)} -> 162638.08 | T11: {=(_xlfn.BYROW(B55,_xlfn.LAMBDA(_xlpm.party,SUMIFS(ledger!G:G,ledger!B:B,_xlpm.party,ledger!E:E,"<>*RD*",ledger!D:D,"Chamki")+SUMIFS(ledger!G:G, ledger!B:B, _xlpm.party, ledger!E:E, "<>*RD*", ledger!D:D, "Crinkle")))/1.0936)+_xlfn.IFNA(E90,0)} -> 162638.08 | U11: {=(_xlfn.BYROW(B55,_xlfn.LAMBDA(_xlpm.party,SUMIFS(ledger!G:G,ledger!B:B,_xlpm.party,ledger!E:E,"<>*RD*",ledger!D:D,"Silky")))/1.0936)+_xlfn.IFNA(F90,0)} -> 0 | V11: {=(_xlfn.BYROW(B55,_xlfn.LAMBDA(_xlpm.party, (SUMIFS(ledger!J:J,ledger!B:B,_xlpm.party,ledger!E:E,"<>*RD*",ledger!D:D,"Chamki",ledger!C:C,"<>November Closing CF")+ SUMIFS(ledger!J:J,ledger!B:B,_xlpm.party,ledger!E:E,"<>*RD*",ledger!D:D,"Crinkle",ledger!C:C,"<>November Closing CF") )+_xlfn.IFNA(G90,0))))} -> 1626380.8 | W11: {=_xlfn.BYROW(B55, _xlfn.LAMBDA(_xlpm.party, SUMIFS(ledger!J:J, ledger!B:B, _xlpm.party, ledger!E:E, "<>*RD*", ledger!D:D, "Silky", ledger!C:C, "<>November Closing CF") )) + _xlfn.IFNA(H90, 0)} -> 0 | X11: {=_xlfn.BYROW(B55, _xlfn.LAMBDA(_xlpm.party, SUMIFS(ledger!J:J, ledger!B:B, _xlpm.party, ledger!E:E, "<>*RD*", ledger!D:D, "Slub", ledger!C:C, "<>November Closing CF") ))+ _xlfn.IFNA(I90, 0)} -> 0 | Y11: {=_xlfn.BYROW(B55, _xlfn.LAMBDA(_xlpm.party, SUMIFS(ledger!J:J, ledger!B:B, _xlpm.party, ledger!E:E, "<>*RD*", ledger!D:D, "Satin", ledger!C:C, "<>November Closing CF") ))+ _xlfn.IFNA(J90, 0)} -> 0 | Z11: {=_xlfn.BYROW(B55, _xlfn.LAMBDA(_xlpm.party, SUMIFS(ledger!J:J, ledger!B:B, _xlpm.party, ledger!E:E, "<>*RD*", ledger!D:D, "Black-Chamki", ledger!C:C, "<>November Closing CF") ))+ _xlfn.IFNA(K90, 0)} -> 0 | AA11: {=_xlfn.BYROW(B55, _xlfn.LAMBDA(_xlpm.party, SUMIFS(ledger!J:J, ledger!B:B, _xlpm.party, ledger!E:E, "<>*RD*", ledger!D:D, "Kataan", ledger!C:C, "<>November Closing CF") ))+ _xlfn.IFNA(L90, 0)} -> 0 | AB11: {=_xlfn.BYROW(B55, _xlfn.LAMBDA(_xlpm.party, SUMIFS(ledger!J:J, ledger!B:B, _xlpm.party, ledger!E:E, "<>*RD*", ledger!D:D, "Munaar", ledger!C:C, "<>November Closing CF") ))+ _xlfn.IFNA(M90, 0)} -> 0 | AC11: =V11+W11+X11+Y11+Z11+AA11+AB11 -> 1626380.8 | AD11: =(SUMIF(Table14[Party],Q11,Table14[Credit]))+_xlfn.IFNA(O90,0) -> 1300000 | AE11: =AC11-AD11 -> 326380.76 | AF11: 10 | AG11: 13
B12: =B59 -> Hafiz Qureshi | C12: =SUMIFS(ledger!G:G, ledger!B:B, B12, ledger!E:E, "<>*RD*") / 1.0936 -> 77208.303 | E12: =(SUMIFS(ledger!G:G, ledger!B:B, B12, ledger!E:E, "<>*RD*",ledger!D:D, "Silky") / 1.0936)*12 + (SUMIFS(ledger!G:G, ledger!B:B, B12, ledger!E:E, "<>*RD*",ledger!D:D, "Chamki") / 1.0936)*10 -> 772083.03 | I12: Hafiz Qureshi | Q12: Azam | R12: {=_xlfn.BYROW(B56,_xlfn.LAMBDA(_xlpm.party,SUMIFS(ledger!G:G,ledger!B:B,_xlpm.party,ledger!E:E,"<>*RD*")))+_xlfn.IFNA(C91,0)} -> 465324 | S12: {=_xlfn.BYROW(B56, _xlfn.LAMBDA(_xlpm.party, SUMIFS(ledger!G:G, ledger!B:B, _xlpm.party, ledger!E:E, "<>*RD*") / 1.0936 ))+_xlfn.IFNA(D91,0)} -> 425497.44 | T12: {=(_xlfn.BYROW(B56,_xlfn.LAMBDA(_xlpm.party,SUMIFS(ledger!G:G,ledger!B:B,_xlpm.party,ledger!E:E,"<>*RD*",ledger!D:D,"Chamki")+SUMIFS(ledger!G:G, ledger!B:B, _xlpm.party, ledger!E:E, "<>*RD*", ledger!D:D, "Crinkle")))/1.0936)+_xlfn.IFNA(E91,0)} -> 400309.07 | U12: {=(_xlfn.BYROW(B56,_xlfn.LAMBDA(_xlpm.party,SUMIFS(ledger!G:G,ledger!B:B,_xlpm.party,ledger!E:E,"<>*RD*",ledger!D:D,"Silky")))/1.0936)+_xlfn.IFNA(F91,0)} -> 25188.369 | V12: {=(_xlfn.BYROW(B56,_xlfn.LAMBDA(_xlpm.party, (SUMIFS(ledger!J:J,ledger!B:B,_xlpm.party,ledger!E:E,"<>*RD*",ledger!D:D,"Chamki",ledger!C:C,"<>November Closing CF")+ SUMIFS(ledger!J:J,ledger!B:B,_xlpm.party,ledger!E:E,"<>*RD*",ledger!D:D,"Crinkle",ledger!C:C,"<>November Closing CF") )+_xlfn.IFNA(G91,0))))} -> 4003090.7 | W12: {=_xlfn.BYROW(B56, _xlfn.LAMBDA(_xlpm.party, SUMIFS(ledger!J:J, ledger!B:B, _xlpm.party, ledger!E:E, "<>*RD*", ledger!D:D, "Silky", ledger!C:C, "<>November Closing CF") )) + _xlfn.IFNA(H91, 0)} -> 327448.79 | X12: {=_xlfn.BYROW(B56, _xlfn.LAMBDA(_xlpm.party, SUMIFS(ledger!J:J, ledger!B:B, _xlpm.party, ledger!E:E, "<>*RD*", ledger!D:D, "Slub", ledger!C:C, "<>November Closing CF") ))+ _xlfn.IFNA(I91, 0)} -> 0 | Y12: {=_xlfn.BYROW(B56, _xlfn.LAMBDA(_xlpm.party, SUMIFS(ledger!J:J, ledger!B:B, _xlpm.party, ledger!E:E, "<>*RD*", ledger!D:D, "Satin", ledger!C:C, "<>November Closing CF") ))+ _xlfn.IFNA(J91, 0)} -> 0 | Z12: {=_xlfn.BYROW(B56, _xlfn.LAMBDA(_xlpm.party, SUMIFS(ledger!J:J, ledger!B:B, _xlpm.party, ledger!E:E, "<>*RD*", ledger!D:D, "Black-Chamki", ledger!C:C, "<>November Closing CF") ))+ _xlfn.IFNA(K91, 0)} -> 0 | AA12: {=_xlfn.BYROW(B56, _xlfn.LAMBDA(_xlpm.party, SUMIFS(ledger!J:J, ledger!B:B, _xlpm.party, ledger!E:E, "<>*RD*", ledger!D:D, "Kataan", ledger!C:C, "<>November Closing CF") ))+ _xlfn.IFNA(L91, 0)} -> 0 | AB12: {=_xlfn.BYROW(B56, _xlfn.LAMBDA(_xlpm.party, SUMIFS(ledger!J:J, ledger!B:B, _xlpm.party, ledger!E:E, "<>*RD*", ledger!D:D, "Munaar", ledger!C:C, "<>November Closing CF") ))+ _xlfn.IFNA(M91, 0)} -> 0 | AC12: =V12+W12+X12+Y12+Z12+AA12+AB12 -> 4330539.5 | AD12: =(SUMIF(Table14[Party],Q12,Table14[Credit]))+_xlfn.IFNA(O91,0) -> 4330540 | AE12: =AC12-AD12 -> -0.49743965 | AF12: 10 | AG12: 13
B13: =B60 -> Badshah Fabrics | C13: =SUMIFS(ledger!G:G, ledger!B:B, B13, ledger!E:E, "<>*RD*") / 1.0936 -> 108264.45 | E13: =(SUMIFS(ledger!G:G, ledger!B:B, B13, ledger!E:E, "<>*RD*",ledger!D:D, "Silky") / 1.0936)*12 + (SUMIFS(ledger!G:G, ledger!B:B, B13, ledger!E:E, "<>*RD*",ledger!D:D, "Chamki") / 1.0936)*10 -> 618461.96 | I13: Badshah Fabrics | Q13: Ubaidullah | R13: {=_xlfn.BYROW(B57,_xlfn.LAMBDA(_xlpm.party,SUMIFS(ledger!G:G,ledger!B:B,_xlpm.party,ledger!E:E,"<>*RD*")))+_xlfn.IFNA(C92,0)} -> 66850 | S13: {=_xlfn.BYROW(B57, _xlfn.LAMBDA(_xlpm.party, SUMIFS(ledger!G:G, ledger!B:B, _xlpm.party, ledger!E:E, "<>*RD*") / 1.0936 ))+_xlfn.IFNA(D92,0)} -> 61128.383 | T13: {=(_xlfn.BYROW(B57,_xlfn.LAMBDA(_xlpm.party,SUMIFS(ledger!G:G,ledger!B:B,_xlpm.party,ledger!E:E,"<>*RD*",ledger!D:D,"Chamki")+SUMIFS(ledger!G:G, ledger!B:B, _xlpm.party, ledger!E:E, "<>*RD*", ledger!D:D, "Crinkle")))/1.0936)+_xlfn.IFNA(E92,0)} -> 46132.955 | U13: {=(_xlfn.BYROW(B57,_xlfn.LAMBDA(_xlpm.party,SUMIFS(ledger!G:G,ledger!B:B,_xlpm.party,ledger!E:E,"<>*RD*",ledger!D:D,"Silky")))/1.0936)+_xlfn.IFNA(F92,0)} -> 14995.428 | V13: {=(_xlfn.BYROW(B57,_xlfn.LAMBDA(_xlpm.party, (SUMIFS(ledger!J:J,ledger!B:B,_xlpm.party,ledger!E:E,"<>*RD*",ledger!D:D,"Chamki",ledger!C:C,"<>November Closing CF")+ SUMIFS(ledger!J:J,ledger!B:B,_xlpm.party,ledger!E:E,"<>*RD*",ledger!D:D,"Crinkle",ledger!C:C,"<>November Closing CF") )+_xlfn.IFNA(G92,0))))} -> 461329.55 | W13: {=_xlfn.BYROW(B57, _xlfn.LAMBDA(_xlpm.party, SUMIFS(ledger!J:J, ledger!B:B, _xlpm.party, ledger!E:E, "<>*RD*", ledger!D:D, "Silky", ledger!C:C, "<>November Closing CF") )) + _xlfn.IFNA(H92, 0)} -> 179945.14 | X13: {=_xlfn.BYROW(B57, _xlfn.LAMBDA(_xlpm.party, SUMIFS(ledger!J:J, ledger!B:B, _xlpm.party, ledger!E:E, "<>*RD*", ledger!D:D, "Slub", ledger!C:C, "<>November Closing CF") ))+ _xlfn.IFNA(I92, 0)} -> 0 | Y13: {=_xlfn.BYROW(B57, _xlfn.LAMBDA(_xlpm.party, SUMIFS(ledger!J:J, ledger!B:B, _xlpm.party, ledger!E:E, "<>*RD*", ledger!D:D, "Satin", ledger!C:C, "<>November Closing CF") ))+ _xlfn.IFNA(J92, 0)} -> 0 | Z13: {=_xlfn.BYROW(B57, _xlfn.LAMBDA(_xlpm.party, SUMIFS(ledger!J:J, ledger!B:B, _xlpm.party, ledger!E:E, "<>*RD*", ledger!D:D, "Black-Chamki", ledger!C:C, "<>November Closing CF") ))+ _xlfn.IFNA(K92, 0)} -> 0 | AA13: {=_xlfn.BYROW(B57, _xlfn.LAMBDA(_xlpm.party, SUMIFS(ledger!J:J, ledger!B:B, _xlpm.party, ledger!E:E, "<>*RD*", ledger!D:D, "Kataan", ledger!C:C, "<>November Closing CF") ))+ _xlfn.IFNA(L92, 0)} -> 0 | AB13: {=_xlfn.BYROW(B57, _xlfn.LAMBDA(_xlpm.party, SUMIFS(ledger!J:J, ledger!B:B, _xlpm.party, ledger!E:E, "<>*RD*", ledger!D:D, "Munaar", ledger!C:C, "<>November Closing CF") ))+ _xlfn.IFNA(M92, 0)} -> 0 | AC13: =V13+W13+X13+Y13+Z13+AA13+AB13 -> 641274.69 | AD13: =(SUMIF(Table14[Party],Q13,Table14[Credit]))+_xlfn.IFNA(O92,0) -> 640190 | AE13: =AC13-AD13 -> 1084.6891 | AF13: 10 | AG13: 13
B14: =B61 -> Reject | C14: =SUMIFS(ledger!G:G, ledger!B:B, B14, ledger!E:E, "<>*RD*") / 1.0936 -> 0 | E14: =(SUMIFS(ledger!G:G, ledger!B:B, B14, ledger!E:E, "<>*RD*",ledger!D:D, "Silky") / 1.0936)*12 + (SUMIFS(ledger!G:G, ledger!B:B, B14, ledger!E:E, "<>*RD*",ledger!D:D, "Chamki") / 1.0936)*10 -> 0 | I14: Reject | Q14: Ashraf Zia | R14: {=_xlfn.BYROW(B58,_xlfn.LAMBDA(_xlpm.party,SUMIFS(ledger!G:G,ledger!B:B,_xlpm.party,ledger!E:E,"<>*RD*")))+_xlfn.IFNA(C93,0)} -> 23305 | S14: {=_xlfn.BYROW(B58, _xlfn.LAMBDA(_xlpm.party, SUMIFS(ledger!G:G, ledger!B:B, _xlpm.party, ledger!E:E, "<>*RD*") / 1.0936 ))+_xlfn.IFNA(D93,0)} -> 21310.351 | T14: {=(_xlfn.BYROW(B58,_xlfn.LAMBDA(_xlpm.party,SUMIFS(ledger!G:G,ledger!B:B,_xlpm.party,ledger!E:E,"<>*RD*",ledger!D:D,"Chamki")+SUMIFS(ledger!G:G, ledger!B:B, _xlpm.party, ledger!E:E, "<>*RD*", ledger!D:D, "Crinkle")))/1.0936)+_xlfn.IFNA(E93,0)} -> 21310.351 | U14: {=(_xlfn.BYROW(B58,_xlfn.LAMBDA(_xlpm.party,SUMIFS(ledger!G:G,ledger!B:B,_xlpm.party,ledger!E:E,"<>*RD*",ledger!D:D,"Silky")))/1.0936)+_xlfn.IFNA(F93,0)} -> 0 | V14: {=(_xlfn.BYROW(B58,_xlfn.LAMBDA(_xlpm.party, (SUMIFS(ledger!J:J,ledger!B:B,_xlpm.party,ledger!E:E,"<>*RD*",ledger!D:D,"Chamki",ledger!C:C,"<>November Closing CF")+ SUMIFS(ledger!J:J,ledger!B:B,_xlpm.party,ledger!E:E,"<>*RD*",ledger!D:D,"Crinkle",ledger!C:C,"<>November Closing CF") )+_xlfn.IFNA(G93,0))))} -> 255724.21 | W14: {=_xlfn.BYROW(B58, _xlfn.LAMBDA(_xlpm.party, SUMIFS(ledger!J:J, ledger!B:B, _xlpm.party, ledger!E:E, "<>*RD*", ledger!D:D, "Silky", ledger!C:C, "<>November Closing CF") )) + _xlfn.IFNA(H93, 0)} -> 0 | X14: {=_xlfn.BYROW(B58, _xlfn.LAMBDA(_xlpm.party, SUMIFS(ledger!J:J, ledger!B:B, _xlpm.party, ledger!E:E, "<>*RD*", ledger!D:D, "Slub", ledger!C:C, "<>November Closing CF") ))+ _xlfn.IFNA(I93, 0)} -> 0 | Y14: {=_xlfn.BYROW(B58, _xlfn.LAMBDA(_xlpm.party, SUMIFS(ledger!J:J, ledger!B:B, _xlpm.party, ledger!E:E, "<>*RD*", ledger!D:D, "Satin", ledger!C:C, "<>November Closing CF") ))+ _xlfn.IFNA(J93, 0)} -> 0 | Z14: {=_xlfn.BYROW(B58, _xlfn.LAMBDA(_xlpm.party, SUMIFS(ledger!J:J, ledger!B:B, _xlpm.party, ledger!E:E, "<>*RD*", ledger!D:D, "Black-Chamki", ledger!C:C, "<>November Closing CF") ))+ _xlfn.IFNA(K93, 0)} -> 0 | AA14: {=_xlfn.BYROW(B58, _xlfn.LAMBDA(_xlpm.party, SUMIFS(ledger!J:J, ledger!B:B, _xlpm.party, ledger!E:E, "<>*RD*", ledger!D:D, "Kataan", ledger!C:C, "<>November Closing CF") ))+ _xlfn.IFNA(L93, 0)} -> 0 | AB14: {=_xlfn.BYROW(B58, _xlfn.LAMBDA(_xlpm.party, SUMIFS(ledger!J:J, ledger!B:B, _xlpm.party, ledger!E:E, "<>*RD*", ledger!D:D, "Munaar", ledger!C:C, "<>November Closing CF") ))+ _xlfn.IFNA(M93, 0)} -> 0 | AC14: =V14+W14+X14+Y14+Z14+AA14+AB14 -> 255724.21 | AD14: =(SUMIF(Table14[Party],Q14,Table14[Credit]))+_xlfn.IFNA(O93,0) -> 130000 | AE14: =AC14-AD14 -> 125724.21 | AF14: 12 | AG14: 13
B15: =B62 -> Amjad 7up | C15: =SUMIFS(ledger!G:G, ledger!B:B, B15, ledger!E:E, "<>*RD*") / 1.0936 -> 0 | E15: =(SUMIFS(ledger!G:G, ledger!B:B, B15, ledger!E:E, "<>*RD*",ledger!D:D, "Silky") / 1.0936)*12 + (SUMIFS(ledger!G:G, ledger!B:B, B15, ledger!E:E, "<>*RD*",ledger!D:D, "Chamki") / 1.0936)*10 -> 0 | I15: Amjad 7up | Q15: Hafiz Qureshi | R15: {=_xlfn.BYROW(B59,_xlfn.LAMBDA(_xlpm.party,SUMIFS(ledger!G:G,ledger!B:B,_xlpm.party,ledger!E:E,"<>*RD*")))+_xlfn.IFNA(C94,0)} -> 287250 | S15: {=_xlfn.BYROW(B59, _xlfn.LAMBDA(_xlpm.party, SUMIFS(ledger!G:G, ledger!B:B, _xlpm.party, ledger!E:E, "<>*RD*") / 1.0936 ))+_xlfn.IFNA(D94,0)} -> 262664.59 | T15: {=(_xlfn.BYROW(B59,_xlfn.LAMBDA(_xlpm.party,SUMIFS(ledger!G:G,ledger!B:B,_xlpm.party,ledger!E:E,"<>*RD*",ledger!D:D,"Chamki")+SUMIFS(ledger!G:G, ledger!B:B, _xlpm.party, ledger!E:E, "<>*RD*", ledger!D:D, "Crinkle")))/1.0936)+_xlfn.IFNA(E94,0)} -> 262664.59 | U15: {=(_xlfn.BYROW(B59,_xlfn.LAMBDA(_xlpm.party,SUMIFS(ledger!G:G,ledger!B:B,_xlpm.party,ledger!E:E,"<>*RD*",ledger!D:D,"Silky")))/1.0936)+_xlfn.IFNA(F94,0)} -> 0 | V15: {=(_xlfn.BYROW(B59,_xlfn.LAMBDA(_xlpm.party, (SUMIFS(ledger!J:J,ledger!B:B,_xlpm.party,ledger!E:E,"<>*RD*",ledger!D:D,"Chamki",ledger!C:C,"<>November Closing CF")+ SUMIFS(ledger!J:J,ledger!B:B,_xlpm.party,ledger!E:E,"<>*RD*",ledger!D:D,"Crinkle",ledger!C:C,"<>November Closing CF") )+_xlfn.IFNA(G94,0))))} -> 2626645.9 | W15: {=_xlfn.BYROW(B59, _xlfn.LAMBDA(_xlpm.party, SUMIFS(ledger!J:J, ledger!B:B, _xlpm.party, ledger!E:E, "<>*RD*", ledger!D:D, "Silky", ledger!C:C, "<>November Closing CF") )) + _xlfn.IFNA(H94, 0)} -> 0 | X15: {=_xlfn.BYROW(B59, _xlfn.LAMBDA(_xlpm.party, SUMIFS(ledger!J:J, ledger!B:B, _xlpm.party, ledger!E:E, "<>*RD*", ledger!D:D, "Slub", ledger!C:C, "<>November Closing CF") ))+ _xlfn.IFNA(I94, 0)} -> 0 | Y15: {=_xlfn.BYROW(B59, _xlfn.LAMBDA(_xlpm.party, SUMIFS(ledger!J:J, ledger!B:B, _xlpm.party, ledger!E:E, "<>*RD*", ledger!D:D, "Satin", ledger!C:C, "<>November Closing CF") ))+ _xlfn.IFNA(J94, 0)} -> 0 | Z15: {=_xlfn.BYROW(B59, _xlfn.LAMBDA(_xlpm.party, SUMIFS(ledger!J:J, ledger!B:B, _xlpm.party, ledger!E:E, "<>*RD*", ledger!D:D, "Black-Chamki", ledger!C:C, "<>November Closing CF") ))+ _xlfn.IFNA(K94, 0)} -> 0 | AA15: {=_xlfn.BYROW(B59, _xlfn.LAMBDA(_xlpm.party, SUMIFS(ledger!J:J, ledger!B:B, _xlpm.party, ledger!E:E, "<>*RD*", ledger!D:D, "Kataan", ledger!C:C, "<>November Closing CF") ))+ _xlfn.IFNA(L94, 0)} -> 0 | AB15: {=_xlfn.BYROW(B59, _xlfn.LAMBDA(_xlpm.party, SUMIFS(ledger!J:J, ledger!B:B, _xlpm.party, ledger!E:E, "<>*RD*", ledger!D:D, "Munaar", ledger!C:C, "<>November Closing CF") ))+ _xlfn.IFNA(M94, 0)} -> 0 | AC15: =V15+W15+X15+Y15+Z15+AA15+AB15 -> 2626645.9 | AD15: =(SUMIF(Table14[Party],Q15,Table14[Credit]))+_xlfn.IFNA(O94,0) -> 2261380 | AE15: =AC15-AD15 -> 365265.94 | AF15: 10 | AG15: 13
B16: =B63 -> Hazrat Khan | C16: =SUMIFS(ledger!G:G, ledger!B:B, B16, ledger!E:E, "<>*RD*") / 1.0936 -> 0 | E16: =(SUMIFS(ledger!G:G, ledger!B:B, B16, ledger!E:E, "<>*RD*",ledger!D:D, "Silky") / 1.0936)*12 + (SUMIFS(ledger!G:G, ledger!B:B, B16, ledger!E:E, "<>*RD*",ledger!D:D, "Chamki") / 1.0936)*10 -> 0 | I16: Hazrat Khan | Q16: Badshah Fabrics | R16: {=_xlfn.BYROW(B60,_xlfn.LAMBDA(_xlpm.party,SUMIFS(ledger!G:G,ledger!B:B,_xlpm.party,ledger!E:E,"<>*RD*")))+_xlfn.IFNA(C95,0)} -> 635806 | S16: {=_xlfn.BYROW(B60, _xlfn.LAMBDA(_xlpm.party, SUMIFS(ledger!G:G, ledger!B:B, _xlpm.party, ledger!E:E, "<>*RD*") / 1.0936 ))+_xlfn.IFNA(D95,0)} -> 581388.08 | T16: {=(_xlfn.BYROW(B60,_xlfn.LAMBDA(_xlpm.party,SUMIFS(ledger!G:G,ledger!B:B,_xlpm.party,ledger!E:E,"<>*RD*",ledger!D:D,"Chamki")+SUMIFS(ledger!G:G, ledger!B:B, _xlpm.party, ledger!E:E, "<>*RD*", ledger!D:D, "Crinkle")))/1.0936)+_xlfn.IFNA(E95,0)} -> 464174.29 | U16: {=(_xlfn.BYROW(B60,_xlfn.LAMBDA(_xlpm.party,SUMIFS(ledger!G:G,ledger!B:B,_xlpm.party,ledger!E:E,"<>*RD*",ledger!D:D,"Silky")))/1.0936)+_xlfn.IFNA(F95,0)} -> 117213.79 | V16: {=(_xlfn.BYROW(B60,_xlfn.LAMBDA(_xlpm.party, (SUMIFS(ledger!J:J,ledger!B:B,_xlpm.party,ledger!E:E,"<>*RD*",ledger!D:D,"Chamki",ledger!C:C,"<>November Closing CF")+ SUMIFS(ledger!J:J,ledger!B:B,_xlpm.party,ledger!E:E,"<>*RD*",ledger!D:D,"Crinkle",ledger!C:C,"<>November Closing CF") )+_xlfn.IFNA(G95,0))))} -> 4641742.9 | W16: {=_xlfn.BYROW(B60, _xlfn.LAMBDA(_xlpm.party, SUMIFS(ledger!J:J, ledger!B:B, _xlpm.party, ledger!E:E, "<>*RD*", ledger!D:D, "Silky", ledger!C:C, "<>November Closing CF") )) + _xlfn.IFNA(H95, 0)} -> 1460624.5 | X16: {=_xlfn.BYROW(B60, _xlfn.LAMBDA(_xlpm.party, SUMIFS(ledger!J:J, ledger!B:B, _xlpm.party, ledger!E:E, "<>*RD*", ledger!D:D, "Slub", ledger!C:C, "<>November Closing CF") ))+ _xlfn.IFNA(I95, 0)} -> 0 | Y16: {=_xlfn.BYROW(B60, _xlfn.LAMBDA(_xlpm.party, SUMIFS(ledger!J:J, ledger!B:B, _xlpm.party, ledger!E:E, "<>*RD*", ledger!D:D, "Satin", ledger!C:C, "<>November Closing CF") ))+ _xlfn.IFNA(J95, 0)} -> 0 | Z16: {=_xlfn.BYROW(B60, _xlfn.LAMBDA(_xlpm.party, SUMIFS(ledger!J:J, ledger!B:B, _xlpm.party, ledger!E:E, "<>*RD*", ledger!D:D, "Black-Chamki", ledger!C:C, "<>November Closing CF") ))+ _xlfn.IFNA(K95, 0)} -> 0 | AA16: {=_xlfn.BYROW(B60, _xlfn.LAMBDA(_xlpm.party, SUMIFS(ledger!J:J, ledger!B:B, _xlpm.party, ledger!E:E, "<>*RD*", ledger!D:D, "Kataan", ledger!C:C, "<>November Closing CF") ))+ _xlfn.IFNA(L95, 0)} -> 0 | AB16: {=_xlfn.BYROW(B60, _xlfn.LAMBDA(_xlpm.party, SUMIFS(ledger!J:J, ledger!B:B, _xlpm.party, ledger!E:E, "<>*RD*", ledger!D:D, "Munaar", ledger!C:C, "<>November Closing CF") ))+ _xlfn.IFNA(M95, 0)} -> 0 | AC16: =V16+W16+X16+Y16+Z16+AA16+AB16 -> 6102367.4 | AD16: =(SUMIF(Table14[Party],Q16,Table14[Credit]))+_xlfn.IFNA(O95,0) -> 6015761 | AE16: =AC16-AD16 -> 86606.41 | AF16: 10 | AG16: 13
B17: =B64 -> Haseeb Shamsi | C17: =SUMIFS(ledger!G:G, ledger!B:B, B17, ledger!E:E, "<>*RD*") / 1.0936 -> 0 | E17: =(SUMIFS(ledger!G:G, ledger!B:B, B17, ledger!E:E, "<>*RD*",ledger!D:D, "Silky") / 1.0936)*12 + (SUMIFS(ledger!G:G, ledger!B:B, B17, ledger!E:E, "<>*RD*",ledger!D:D, "Chamki") / 1.0936)*10 -> 0 | I17: Haseeb Shamsi | Q17: Reject | R17: {=_xlfn.BYROW(B61,_xlfn.LAMBDA(_xlpm.party,SUMIFS(ledger!G:G,ledger!B:B,_xlpm.party,ledger!E:E,"<>*RD*")))+_xlfn.IFNA(C96,0)} -> 0 | S17: {=_xlfn.BYROW(B61, _xlfn.LAMBDA(_xlpm.party, SUMIFS(ledger!G:G, ledger!B:B, _xlpm.party, ledger!E:E, "<>*RD*") / 1.0936 ))+_xlfn.IFNA(D96,0)} -> 0 | T17: {=(_xlfn.BYROW(B61,_xlfn.LAMBDA(_xlpm.party,SUMIFS(ledger!G:G,ledger!B:B,_xlpm.party,ledger!E:E,"<>*RD*",ledger!D:D,"Chamki")+SUMIFS(ledger!G:G, ledger!B:B, _xlpm.party, ledger!E:E, "<>*RD*", ledger!D:D, "Crinkle")))/1.0936)+_xlfn.IFNA(E96,0)} -> 0 | U17: {=(_xlfn.BYROW(B61,_xlfn.LAMBDA(_xlpm.party,SUMIFS(ledger!G:G,ledger!B:B,_xlpm.party,ledger!E:E,"<>*RD*",ledger!D:D,"Silky")))/1.0936)+_xlfn.IFNA(F96,0)} -> 0 | V17: {=(_xlfn.BYROW(B61,_xlfn.LAMBDA(_xlpm.party, (SUMIFS(ledger!J:J,ledger!B:B,_xlpm.party,ledger!E:E,"<>*RD*",ledger!D:D,"Chamki",ledger!C:C,"<>November Closing CF")+ SUMIFS(ledger!J:J,ledger!B:B,_xlpm.party,ledger!E:E,"<>*RD*",ledger!D:D,"Crinkle",ledger!C:C,"<>November Closing CF") )+_xlfn.IFNA(G96,0))))} -> 0 | W17: {=_xlfn.BYROW(B61, _xlfn.LAMBDA(_xlpm.party, SUMIFS(ledger!J:J, ledger!B:B, _xlpm.party, ledger!E:E, "<>*RD*", ledger!D:D, "Silky", ledger!C:C, "<>November Closing CF") )) + _xlfn.IFNA(H96, 0)} -> 0 | X17: {=_xlfn.BYROW(B61, _xlfn.LAMBDA(_xlpm.party, SUMIFS(ledger!J:J, ledger!B:B, _xlpm.party, ledger!E:E, "<>*RD*", ledger!D:D, "Slub", ledger!C:C, "<>November Closing CF") ))+ _xlfn.IFNA(I96, 0)} -> 0 | Y17: {=_xlfn.BYROW(B61, _xlfn.LAMBDA(_xlpm.party, SUMIFS(ledger!J:J, ledger!B:B, _xlpm.party, ledger!E:E, "<>*RD*", ledger!D:D, "Satin", ledger!C:C, "<>November Closing CF") ))+ _xlfn.IFNA(J96, 0)} -> 0 | Z17: {=_xlfn.BYROW(B61, _xlfn.LAMBDA(_xlpm.party, SUMIFS(ledger!J:J, ledger!B:B, _xlpm.party, ledger!E:E, "<>*RD*", ledger!D:D, "Black-Chamki", ledger!C:C, "<>November Closing CF") ))+ _xlfn.IFNA(K96, 0)} -> 0 | AA17: {=_xlfn.BYROW(B61, _xlfn.LAMBDA(_xlpm.party, SUMIFS(ledger!J:J, ledger!B:B, _xlpm.party, ledger!E:E, "<>*RD*", ledger!D:D, "Kataan", ledger!C:C, "<>November Closing CF") ))+ _xlfn.IFNA(L96, 0)} -> 0 | AB17: {=_xlfn.BYROW(B61, _xlfn.LAMBDA(_xlpm.party, SUMIFS(ledger!J:J, ledger!B:B, _xlpm.party, ledger!E:E, "<>*RD*", ledger!D:D, "Munaar", ledger!C:C, "<>November Closing CF") ))+ _xlfn.IFNA(M96, 0)} -> 0 | AC17: =V17+W17+X17+Y17+Z17+AA17+AB17 -> 0 | AD17: =(SUMIF(Table14[Party],Q17,Table14[Credit]))+_xlfn.IFNA(O96,0) -> 0 | AE17: =AC17-AD17 -> 0 | AF17: 10 | AG17: 13
B18: =B65 -> Faizan | C18: =SUMIFS(ledger!G:G, ledger!B:B, B18, ledger!E:E, "<>*RD*") / 1.0936 -> 0 | E18: =(SUMIFS(ledger!G:G, ledger!B:B, B18, ledger!E:E, "<>*RD*",ledger!D:D, "Silky") / 1.0936)*12 + (SUMIFS(ledger!G:G, ledger!B:B, B18, ledger!E:E, "<>*RD*",ledger!D:D, "Chamki") / 1.0936)*10 -> 0 | I18: Faizan | Q18: Amjad 7up | R18: {=_xlfn.BYROW(B62,_xlfn.LAMBDA(_xlpm.party,SUMIFS(ledger!G:G,ledger!B:B,_xlpm.party,ledger!E:E,"<>*RD*")))+_xlfn.IFNA(C97,0)} -> 52914 | S18: {=_xlfn.BYROW(B62, _xlfn.LAMBDA(_xlpm.party, SUMIFS(ledger!G:G, ledger!B:B, _xlpm.party, ledger!E:E, "<>*RD*") / 1.0936 ))+_xlfn.IFNA(D97,0)} -> 48385.15 | T18: {=(_xlfn.BYROW(B62,_xlfn.LAMBDA(_xlpm.party,SUMIFS(ledger!G:G,ledger!B:B,_xlpm.party,ledger!E:E,"<>*RD*",ledger!D:D,"Chamki")+SUMIFS(ledger!G:G, ledger!B:B, _xlpm.party, ledger!E:E, "<>*RD*", ledger!D:D, "Crinkle")))/1.0936)+_xlfn.IFNA(E97,0)} -> 48385.15 | U18: {=(_xlfn.BYROW(B62,_xlfn.LAMBDA(_xlpm.party,SUMIFS(ledger!G:G,ledger!B:B,_xlpm.party,ledger!E:E,"<>*RD*",ledger!D:D,"Silky")))/1.0936)+_xlfn.IFNA(F97,0)} -> 0 | V18: {=(_xlfn.BYROW(B62,_xlfn.LAMBDA(_xlpm.party, (SUMIFS(ledger!J:J,ledger!B:B,_xlpm.party,ledger!E:E,"<>*RD*",ledger!D:D,"Chamki",ledger!C:C,"<>November Closing CF")+ SUMIFS(ledger!J:J,ledger!B:B,_xlpm.party,ledger!E:E,"<>*RD*",ledger!D:D,"Crinkle",ledger!C:C,"<>November Closing CF") )+_xlfn.IFNA(G97,0))))} -> 483851.5 | W18: {=_xlfn.BYROW(B62, _xlfn.LAMBDA(_xlpm.party, SUMIFS(ledger!J:J, ledger!B:B, _xlpm.party, ledger!E:E, "<>*RD*", ledger!D:D, "Silky", ledger!C:C, "<>November Closing CF") )) + _xlfn.IFNA(H97, 0)} -> 0 | X18: {=_xlfn.BYROW(B62, _xlfn.LAMBDA(_xlpm.party, SUMIFS(ledger!J:J, ledger!B:B, _xlpm.party, ledger!E:E, "<>*RD*", ledger!D:D, "Slub", ledger!C:C, "<>November Closing CF") ))+ _xlfn.IFNA(I97, 0)} -> 0 | Y18: {=_xlfn.BYROW(B62, _xlfn.LAMBDA(_xlpm.party, SUMIFS(ledger!J:J, ledger!B:B, _xlpm.party, ledger!E:E, "<>*RD*", ledger!D:D, "Satin", ledger!C:C, "<>November Closing CF") ))+ _xlfn.IFNA(J97, 0)} -> 0 | Z18: {=_xlfn.BYROW(B62, _xlfn.LAMBDA(_xlpm.party, SUMIFS(ledger!J:J, ledger!B:B, _xlpm.party, ledger!E:E, "<>*RD*", ledger!D:D, "Black-Chamki", ledger!C:C, "<>November Closing CF") ))+ _xlfn.IFNA(K97, 0)} -> 0 | AA18: {=_xlfn.BYROW(B62, _xlfn.LAMBDA(_xlpm.party, SUMIFS(ledger!J:J, ledger!B:B, _xlpm.party, ledger!E:E, "<>*RD*", ledger!D:D, "Kataan", ledger!C:C, "<>November Closing CF") ))+ _xlfn.IFNA(L97, 0)} -> 0 | AB18: {=_xlfn.BYROW(B62, _xlfn.LAMBDA(_xlpm.party, SUMIFS(ledger!J:J, ledger!B:B, _xlpm.party, ledger!E:E, "<>*RD*", ledger!D:D, "Munaar", ledger!C:C, "<>November Closing CF") ))+ _xlfn.IFNA(M97, 0)} -> 0 | AC18: =V18+W18+X18+Y18+Z18+AA18+AB18 -> 483851.5 | AD18: =(SUMIF(Table14[Party],Q18,Table14[Credit]))+_xlfn.IFNA(O97,0) -> 480000 | AE18: =AC18-AD18 -> 3851.4996 | AF18: 10 | AG18: 13
I19: Shafique Ansari | Q19: Hazrat Khan | R19: {=_xlfn.BYROW(B63,_xlfn.LAMBDA(_xlpm.party,SUMIFS(ledger!G:G,ledger!B:B,_xlpm.party,ledger!E:E,"<>*RD*")))+_xlfn.IFNA(C98,0)} -> 9750 | S19: {=_xlfn.BYROW(B63, _xlfn.LAMBDA(_xlpm.party, SUMIFS(ledger!G:G, ledger!B:B, _xlpm.party, ledger!E:E, "<>*RD*") / 1.0936 ))+_xlfn.IFNA(D98,0)} -> 8915.5084 | T19: {=(_xlfn.BYROW(B63,_xlfn.LAMBDA(_xlpm.party,SUMIFS(ledger!G:G,ledger!B:B,_xlpm.party,ledger!E:E,"<>*RD*",ledger!D:D,"Chamki")+SUMIFS(ledger!G:G, ledger!B:B, _xlpm.party, ledger!E:E, "<>*RD*", ledger!D:D, "Crinkle")))/1.0936)+_xlfn.IFNA(E98,0)} -> 8915.5084 | U19: {=(_xlfn.BYROW(B63,_xlfn.LAMBDA(_xlpm.party,SUMIFS(ledger!G:G,ledger!B:B,_xlpm.party,ledger!E:E,"<>*RD*",ledger!D:D,"Silky")))/1.0936)+_xlfn.IFNA(F98,0)} -> 0 | V19: {=(_xlfn.BYROW(B63,_xlfn.LAMBDA(_xlpm.party, (SUMIFS(ledger!J:J,ledger!B:B,_xlpm.party,ledger!E:E,"<>*RD*",ledger!D:D,"Chamki",ledger!C:C,"<>November Closing CF")+ SUMIFS(ledger!J:J,ledger!B:B,_xlpm.party,ledger!E:E,"<>*RD*",ledger!D:D,"Crinkle",ledger!C:C,"<>November Closing CF") )+_xlfn.IFNA(G98,0))))} -> 89155.084 | W19: {=_xlfn.BYROW(B63, _xlfn.LAMBDA(_xlpm.party, SUMIFS(ledger!J:J, ledger!B:B, _xlpm.party, ledger!E:E, "<>*RD*", ledger!D:D, "Silky", ledger!C:C, "<>November Closing CF") )) + _xlfn.IFNA(H98, 0)} -> 0 | X19: {=_xlfn.BYROW(B63, _xlfn.LAMBDA(_xlpm.party, SUMIFS(ledger!J:J, ledger!B:B, _xlpm.party, ledger!E:E, "<>*RD*", ledger!D:D, "Slub", ledger!C:C, "<>November Closing CF") ))+ _xlfn.IFNA(I98, 0)} -> 0 | Y19: {=_xlfn.BYROW(B63, _xlfn.LAMBDA(_xlpm.party, SUMIFS(ledger!J:J, ledger!B:B, _xlpm.party, ledger!E:E, "<>*RD*", ledger!D:D, "Satin", ledger!C:C, "<>November Closing CF") ))+ _xlfn.IFNA(J98, 0)} -> 0 | Z19: {=_xlfn.BYROW(B63, _xlfn.LAMBDA(_xlpm.party, SUMIFS(ledger!J:J, ledger!B:B, _xlpm.party, ledger!E:E, "<>*RD*", ledger!D:D, "Black-Chamki", ledger!C:C, "<>November Closing CF") ))+ _xlfn.IFNA(K98, 0)} -> 0 | AA19: {=_xlfn.BYROW(B63, _xlfn.LAMBDA(_xlpm.party, SUMIFS(ledger!J:J, ledger!B:B, _xlpm.party, ledger!E:E, "<>*RD*", ledger!D:D, "Kataan", ledger!C:C, "<>November Closing CF") ))+ _xlfn.IFNA(L98, 0)} -> 0 | AB19: {=_xlfn.BYROW(B63, _xlfn.LAMBDA(_xlpm.party, SUMIFS(ledger!J:J, ledger!B:B, _xlpm.party, ledger!E:E, "<>*RD*", ledger!D:D, "Munaar", ledger!C:C, "<>November Closing CF") ))+ _xlfn.IFNA(M98, 0)} -> 0 | AC19: =V19+W19+X19+Y19+Z19+AA19+AB19 -> 89155.084 | AD19: =(SUMIF(Table14[Party],Q19,Table14[Credit]))+_xlfn.IFNA(O98,0) -> 95000 | AE19: =AC19-AD19 -> -5844.9159 | AF19: 10 | AG19: 13
I20: Amjad sohail | Q20: Haseeb Shamsi | R20: {=_xlfn.BYROW(B64,_xlfn.LAMBDA(_xlpm.party,SUMIFS(ledger!G:G,ledger!B:B,_xlpm.party,ledger!E:E,"<>*RD*")))+_xlfn.IFNA(C99,0)} -> 61975 | S20: {=_xlfn.BYROW(B64, _xlfn.LAMBDA(_xlpm.party, SUMIFS(ledger!G:G, ledger!B:B, _xlpm.party, ledger!E:E, "<>*RD*") / 1.0936 ))+_xlfn.IFNA(D99,0)} -> 56670.629 | T20: {=(_xlfn.BYROW(B64,_xlfn.LAMBDA(_xlpm.party,SUMIFS(ledger!G:G,ledger!B:B,_xlpm.party,ledger!E:E,"<>*RD*",ledger!D:D,"Chamki")+SUMIFS(ledger!G:G, ledger!B:B, _xlpm.party, ledger!E:E, "<>*RD*", ledger!D:D, "Crinkle")))/1.0936)+_xlfn.IFNA(E99,0)} -> 47437.82 | U20: {=(_xlfn.BYROW(B64,_xlfn.LAMBDA(_xlpm.party,SUMIFS(ledger!G:G,ledger!B:B,_xlpm.party,ledger!E:E,"<>*RD*",ledger!D:D,"Silky")))/1.0936)+_xlfn.IFNA(F99,0)} -> 9232.8091 | V20: {=(_xlfn.BYROW(B64,_xlfn.LAMBDA(_xlpm.party, (SUMIFS(ledger!J:J,ledger!B:B,_xlpm.party,ledger!E:E,"<>*RD*",ledger!D:D,"Chamki",ledger!C:C,"<>November Closing CF")+ SUMIFS(ledger!J:J,ledger!B:B,_xlpm.party,ledger!E:E,"<>*RD*",ledger!D:D,"Crinkle",ledger!C:C,"<>November Closing CF") )+_xlfn.IFNA(G99,0))))} -> 474378.2 | W20: {=_xlfn.BYROW(B64, _xlfn.LAMBDA(_xlpm.party, SUMIFS(ledger!J:J, ledger!B:B, _xlpm.party, ledger!E:E, "<>*RD*", ledger!D:D, "Silky", ledger!C:C, "<>November Closing CF") )) + _xlfn.IFNA(H99, 0)} -> 120026.52 | X20: {=_xlfn.BYROW(B64, _xlfn.LAMBDA(_xlpm.party, SUMIFS(ledger!J:J, ledger!B:B, _xlpm.party, ledger!E:E, "<>*RD*", ledger!D:D, "Slub", ledger!C:C, "<>November Closing CF") ))+ _xlfn.IFNA(I99, 0)} -> 0 | Y20: {=_xlfn.BYROW(B64, _xlfn.LAMBDA(_xlpm.party, SUMIFS(ledger!J:J, ledger!B:B, _xlpm.party, ledger!E:E, "<>*RD*", ledger!D:D, "Satin", ledger!C:C, "<>November Closing CF") ))+ _xlfn.IFNA(J99, 0)} -> 0 | Z20: {=_xlfn.BYROW(B64, _xlfn.LAMBDA(_xlpm.party, SUMIFS(ledger!J:J, ledger!B:B, _xlpm.party, ledger!E:E, "<>*RD*", ledger!D:D, "Black-Chamki", ledger!C:C, "<>November Closing CF") ))+ _xlfn.IFNA(K99, 0)} -> 0 | AA20: {=_xlfn.BYROW(B64, _xlfn.LAMBDA(_xlpm.party, SUMIFS(ledger!J:J, ledger!B:B, _xlpm.party, ledger!E:E, "<>*RD*", ledger!D:D, "Kataan", ledger!C:C, "<>November Closing CF") ))+ _xlfn.IFNA(L99, 0)} -> 0 | AB20: {=_xlfn.BYROW(B64, _xlfn.LAMBDA(_xlpm.party, SUMIFS(ledger!J:J, ledger!B:B, _xlpm.party, ledger!E:E, "<>*RD*", ledger!D:D, "Munaar", ledger!C:C, "<>November Closing CF") ))+ _xlfn.IFNA(M99, 0)} -> 0 | AC20: =V20+W20+X20+Y20+Z20+AA20+AB20 -> 594404.72 | AD20: =(SUMIF(Table14[Party],Q20,Table14[Credit]))+_xlfn.IFNA(O99,0) -> 594405 | AE20: =AC20-AD20 -> -0.28163862 | AF20: 10 | AG20: 13
B21: Total: | C21: =SUM(N49:N78) -> 7678658.4 | D21: (Real Figure) | I21: Salman Zaffar | Q21: Faizan | R21: {=_xlfn.BYROW(B65,_xlfn.LAMBDA(_xlpm.party,SUMIFS(ledger!G:G,ledger!B:B,_xlpm.party,ledger!E:E,"<>*RD*")))+_xlfn.IFNA(C100,0)} -> 438975 | S21: {=_xlfn.BYROW(B65, _xlfn.LAMBDA(_xlpm.party, SUMIFS(ledger!G:G, ledger!B:B, _xlpm.party, ledger!E:E, "<>*RD*") / 1.0936 ))+_xlfn.IFNA(D100,0)} -> 401403.62 | T21: {=(_xlfn.BYROW(B65,_xlfn.LAMBDA(_xlpm.party,SUMIFS(ledger!G:G,ledger!B:B,_xlpm.party,ledger!E:E,"<>*RD*",ledger!D:D,"Chamki")+SUMIFS(ledger!G:G, ledger!B:B, _xlpm.party, ledger!E:E, "<>*RD*", ledger!D:D, "Crinkle")))/1.0936)+_xlfn.IFNA(E100,0)} -> 0 | U21: {=(_xlfn.BYROW(B65,_xlfn.LAMBDA(_xlpm.party,SUMIFS(ledger!G:G,ledger!B:B,_xlpm.party,ledger!E:E,"<>*RD*",ledger!D:D,"Silky")))/1.0936)+_xlfn.IFNA(F100,0)} -> 398433.61 | V21: {=(_xlfn.BYROW(B65,_xlfn.LAMBDA(_xlpm.party, (SUMIFS(ledger!J:J,ledger!B:B,_xlpm.party,ledger!E:E,"<>*RD*",ledger!D:D,"Chamki",ledger!C:C,"<>November Closing CF")+ SUMIFS(ledger!J:J,ledger!B:B,_xlpm.party,ledger!E:E,"<>*RD*",ledger!D:D,"Crinkle",ledger!C:C,"<>November Closing CF") )+_xlfn.IFNA(G100,0))))} -> 0 | W21: {=_xlfn.BYROW(B65, _xlfn.LAMBDA(_xlpm.party, SUMIFS(ledger!J:J, ledger!B:B, _xlpm.party, ledger!E:E, "<>*RD*", ledger!D:D, "Silky", ledger!C:C, "<>November Closing CF") )) + _xlfn.IFNA(H100, 0)} -> 5179637 | X21: {=_xlfn.BYROW(B65, _xlfn.LAMBDA(_xlpm.party, SUMIFS(ledger!J:J, ledger!B:B, _xlpm.party, ledger!E:E, "<>*RD*", ledger!D:D, "Slub", ledger!C:C, "<>November Closing CF") ))+ _xlfn.IFNA(I100, 0)} -> 44550.11 | Y21: {=_xlfn.BYROW(B65, _xlfn.LAMBDA(_xlpm.party, SUMIFS(ledger!J:J, ledger!B:B, _xlpm.party, ledger!E:E, "<>*RD*", ledger!D:D, "Satin", ledger!C:C, "<>November Closing CF") ))+ _xlfn.IFNA(J100, 0)} -> 0 | Z21: {=_xlfn.BYROW(B65, _xlfn.LAMBDA(_xlpm.party, SUMIFS(ledger!J:J, ledger!B:B, _xlpm.party, ledger!E:E, "<>*RD*", ledger!D:D, "Black-Chamki", ledger!C:C, "<>November Closing CF") ))+ _xlfn.IFNA(K100, 0)} -> 0 | AA21: {=_xlfn.BYROW(B65, _xlfn.LAMBDA(_xlpm.party, SUMIFS(ledger!J:J, ledger!B:B, _xlpm.party, ledger!E:E, "<>*RD*", ledger!D:D, "Kataan", ledger!C:C, "<>November Closing CF") ))+ _xlfn.IFNA(L100, 0)} -> 0 | AB21: {=_xlfn.BYROW(B65, _xlfn.LAMBDA(_xlpm.party, SUMIFS(ledger!J:J, ledger!B:B, _xlpm.party, ledger!E:E, "<>*RD*", ledger!D:D, "Munaar", ledger!C:C, "<>November Closing CF") ))+ _xlfn.IFNA(M100, 0)} -> 0 | AC21: =V21+W21+X21+Y21+Z21+AA21+AB21 -> 5224187.1 | AD21: =(SUMIF(Table14[Party],Q21,Table14[Credit]))+_xlfn.IFNA(O100,0) -> 4915571 | AE21: =AC21-AD21 -> 308616.09 | AF21: 10 | AG21: 13
I22: Shahid Qasayi | Q22: Shafique Ansari | R22: {=_xlfn.BYROW(B66,_xlfn.LAMBDA(_xlpm.party,SUMIFS(ledger!G:G,ledger!B:B,_xlpm.party,ledger!E:E,"<>*RD*")))+_xlfn.IFNA(C101,0)} -> 82290 | S22: {=_xlfn.BYROW(B66, _xlfn.LAMBDA(_xlpm.party, SUMIFS(ledger!G:G, ledger!B:B, _xlpm.party, ledger!E:E, "<>*RD*") / 1.0936 ))+_xlfn.IFNA(D101,0)} -> 75246.891 | T22: {=(_xlfn.BYROW(B66,_xlfn.LAMBDA(_xlpm.party,SUMIFS(ledger!G:G,ledger!B:B,_xlpm.party,ledger!E:E,"<>*RD*",ledger!D:D,"Chamki")+SUMIFS(ledger!G:G, ledger!B:B, _xlpm.party, ledger!E:E, "<>*RD*", ledger!D:D, "Crinkle")))/1.0936)+_xlfn.IFNA(E101,0)} -> 64300.475 | U22: {=(_xlfn.BYROW(B66,_xlfn.LAMBDA(_xlpm.party,SUMIFS(ledger!G:G,ledger!B:B,_xlpm.party,ledger!E:E,"<>*RD*",ledger!D:D,"Silky")))/1.0936)+_xlfn.IFNA(F101,0)} -> 7565.8376 | V22: {=(_xlfn.BYROW(B66,_xlfn.LAMBDA(_xlpm.party, (SUMIFS(ledger!J:J,ledger!B:B,_xlpm.party,ledger!E:E,"<>*RD*",ledger!D:D,"Chamki",ledger!C:C,"<>November Closing CF")+ SUMIFS(ledger!J:J,ledger!B:B,_xlpm.party,ledger!E:E,"<>*RD*",ledger!D:D,"Crinkle",ledger!C:C,"<>November Closing CF") )+_xlfn.IFNA(G101,0))))} -> 643004.75 | W22: {=_xlfn.BYROW(B66, _xlfn.LAMBDA(_xlpm.party, SUMIFS(ledger!J:J, ledger!B:B, _xlpm.party, ledger!E:E, "<>*RD*", ledger!D:D, "Silky", ledger!C:C, "<>November Closing CF") )) + _xlfn.IFNA(H101, 0)} -> 98355.889 | X22: {=_xlfn.BYROW(B66, _xlfn.LAMBDA(_xlpm.party, SUMIFS(ledger!J:J, ledger!B:B, _xlpm.party, ledger!E:E, "<>*RD*", ledger!D:D, "Slub", ledger!C:C, "<>November Closing CF") ))+ _xlfn.IFNA(I101, 0)} -> 0 | Y22: {=_xlfn.BYROW(B66, _xlfn.LAMBDA(_xlpm.party, SUMIFS(ledger!J:J, ledger!B:B, _xlpm.party, ledger!E:E, "<>*RD*", ledger!D:D, "Satin", ledger!C:C, "<>November Closing CF") ))+ _xlfn.IFNA(J101, 0)} -> 94656.181 | Z22: {=_xlfn.BYROW(B66, _xlfn.LAMBDA(_xlpm.party, SUMIFS(ledger!J:J, ledger!B:B, _xlpm.party, ledger!E:E, "<>*RD*", ledger!D:D, "Black-Chamki", ledger!C:C, "<>November Closing CF") ))+ _xlfn.IFNA(K101, 0)} -> 0 | AA22: {=_xlfn.BYROW(B66, _xlfn.LAMBDA(_xlpm.party, SUMIFS(ledger!J:J, ledger!B:B, _xlpm.party, ledger!E:E, "<>*RD*", ledger!D:D, "Kataan", ledger!C:C, "<>November Closing CF") ))+ _xlfn.IFNA(L101, 0)} -> 0 | AB22: {=_xlfn.BYROW(B66, _xlfn.LAMBDA(_xlpm.party, SUMIFS(ledger!J:J, ledger!B:B, _xlpm.party, ledger!E:E, "<>*RD*", ledger!D:D, "Munaar", ledger!C:C, "<>November Closing CF") ))+ _xlfn.IFNA(M101, 0)} -> 0 | AC22: =V22+W22+X22+Y22+Z22+AA22+AB22 -> 836016.83 | AD22: =(SUMIF(Table14[Party],Q22,Table14[Credit]))+_xlfn.IFNA(O101,0) -> 835660 | AE22: =AC22-AD22 -> 356.82516 | AF22: 10 | AG22: 13
B23: Total influx | C23: =SUM(N49:N81) -> 7678658.4 | D23: (considering 10.5) | I23: Hameed corporation | Q23: Amjad sohail | R23: {=_xlfn.BYROW(B67,_xlfn.LAMBDA(_xlpm.party,SUMIFS(ledger!G:G,ledger!B:B,_xlpm.party,ledger!E:E,"<>*RD*")))+_xlfn.IFNA(C102,0)} -> 281909 | S23: {=_xlfn.BYROW(B67, _xlfn.LAMBDA(_xlpm.party, SUMIFS(ledger!G:G, ledger!B:B, _xlpm.party, ledger!E:E, "<>*RD*") / 1.0936 ))+_xlfn.IFNA(D102,0)} -> 257780.72 | T23: {=(_xlfn.BYROW(B67,_xlfn.LAMBDA(_xlpm.party,SUMIFS(ledger!G:G,ledger!B:B,_xlpm.party,ledger!E:E,"<>*RD*",ledger!D:D,"Chamki")+SUMIFS(ledger!G:G, ledger!B:B, _xlpm.party, ledger!E:E, "<>*RD*", ledger!D:D, "Crinkle")))/1.0936)+_xlfn.IFNA(E102,0)} -> 213946.6 | U23: {=(_xlfn.BYROW(B67,_xlfn.LAMBDA(_xlpm.party,SUMIFS(ledger!G:G,ledger!B:B,_xlpm.party,ledger!E:E,"<>*RD*",ledger!D:D,"Silky")))/1.0936)+_xlfn.IFNA(F102,0)} -> 43834.126 | V23: {=(_xlfn.BYROW(B67,_xlfn.LAMBDA(_xlpm.party, (SUMIFS(ledger!J:J,ledger!B:B,_xlpm.party,ledger!E:E,"<>*RD*",ledger!D:D,"Chamki",ledger!C:C,"<>November Closing CF")+ SUMIFS(ledger!J:J,ledger!B:B,_xlpm.party,ledger!E:E,"<>*RD*",ledger!D:D,"Crinkle",ledger!C:C,"<>November Closing CF") )+_xlfn.IFNA(G102,0))))} -> 2139466 | W23: {=_xlfn.BYROW(B67, _xlfn.LAMBDA(_xlpm.party, SUMIFS(ledger!J:J, ledger!B:B, _xlpm.party, ledger!E:E, "<>*RD*", ledger!D:D, "Silky", ledger!C:C, "<>November Closing CF") )) + _xlfn.IFNA(H102, 0)} -> 569843.64 | X23: {=_xlfn.BYROW(B67, _xlfn.LAMBDA(_xlpm.party, SUMIFS(ledger!J:J, ledger!B:B, _xlpm.party, ledger!E:E, "<>*RD*", ledger!D:D, "Slub", ledger!C:C, "<>November Closing CF") ))+ _xlfn.IFNA(I102, 0)} -> 0 | Y23: {=_xlfn.BYROW(B67, _xlfn.LAMBDA(_xlpm.party, SUMIFS(ledger!J:J, ledger!B:B, _xlpm.party, ledger!E:E, "<>*RD*", ledger!D:D, "Satin", ledger!C:C, "<>November Closing CF") ))+ _xlfn.IFNA(J102, 0)} -> 0 | Z23: {=_xlfn.BYROW(B67, _xlfn.LAMBDA(_xlpm.party, SUMIFS(ledger!J:J, ledger!B:B, _xlpm.party, ledger!E:E, "<>*RD*", ledger!D:D, "Black-Chamki", ledger!C:C, "<>November Closing CF") ))+ _xlfn.IFNA(K102, 0)} -> 0 | AA23: {=_xlfn.BYROW(B67, _xlfn.LAMBDA(_xlpm.party, SUMIFS(ledger!J:J, ledger!B:B, _xlpm.party, ledger!E:E, "<>*RD*", ledger!D:D, "Kataan", ledger!C:C, "<>November Closing CF") ))+ _xlfn.IFNA(L102, 0)} -> 0 | AB23: {=_xlfn.BYROW(B67, _xlfn.LAMBDA(_xlpm.party, SUMIFS(ledger!J:J, ledger!B:B, _xlpm.party, ledger!E:E, "<>*RD*", ledger!D:D, "Munaar", ledger!C:C, "<>November Closing CF") ))+ _xlfn.IFNA(M102, 0)} -> 0 | AC23: =V23+W23+X23+Y23+Z23+AA23+AB23 -> 2709309.6 | AD23: =(SUMIF(Table14[Party],Q23,Table14[Credit]))+_xlfn.IFNA(O102,0) -> 2709310 | AE23: =AC23-AD23 -> -0.38039503 | AF23: 10 | AG23: 13
I24: ibraheem behraam | Q24: Salman Zaffar | R24: {=_xlfn.BYROW(B68,_xlfn.LAMBDA(_xlpm.party,SUMIFS(ledger!G:G,ledger!B:B,_xlpm.party,ledger!E:E,"<>*RD*")))+_xlfn.IFNA(C103,0)} -> 93232 | S24: {=_xlfn.BYROW(B68, _xlfn.LAMBDA(_xlpm.party, SUMIFS(ledger!G:G, ledger!B:B, _xlpm.party, ledger!E:E, "<>*RD*") / 1.0936 ))+_xlfn.IFNA(D103,0)} -> 85252.377 | T24: {=(_xlfn.BYROW(B68,_xlfn.LAMBDA(_xlpm.party,SUMIFS(ledger!G:G,ledger!B:B,_xlpm.party,ledger!E:E,"<>*RD*",ledger!D:D,"Chamki")+SUMIFS(ledger!G:G, ledger!B:B, _xlpm.party, ledger!E:E, "<>*RD*", ledger!D:D, "Crinkle")))/1.0936)+_xlfn.IFNA(E103,0)} -> 40372.165 | U24: {=(_xlfn.BYROW(B68,_xlfn.LAMBDA(_xlpm.party,SUMIFS(ledger!G:G,ledger!B:B,_xlpm.party,ledger!E:E,"<>*RD*",ledger!D:D,"Silky")))/1.0936)+_xlfn.IFNA(F103,0)} -> 31409.108 | V24: {=(_xlfn.BYROW(B68,_xlfn.LAMBDA(_xlpm.party, (SUMIFS(ledger!J:J,ledger!B:B,_xlpm.party,ledger!E:E,"<>*RD*",ledger!D:D,"Chamki",ledger!C:C,"<>November Closing CF")+ SUMIFS(ledger!J:J,ledger!B:B,_xlpm.party,ledger!E:E,"<>*RD*",ledger!D:D,"Crinkle",ledger!C:C,"<>November Closing CF") )+_xlfn.IFNA(G103,0))))} -> 403721.65 | W24: {=_xlfn.BYROW(B68, _xlfn.LAMBDA(_xlpm.party, SUMIFS(ledger!J:J, ledger!B:B, _xlpm.party, ledger!E:E, "<>*RD*", ledger!D:D, "Silky", ledger!C:C, "<>November Closing CF") )) + _xlfn.IFNA(H103, 0)} -> 408318.4 | X24: {=_xlfn.BYROW(B68, _xlfn.LAMBDA(_xlpm.party, SUMIFS(ledger!J:J, ledger!B:B, _xlpm.party, ledger!E:E, "<>*RD*", ledger!D:D, "Slub", ledger!C:C, "<>November Closing CF") ))+ _xlfn.IFNA(I103, 0)} -> 0 | Y24: {=_xlfn.BYROW(B68, _xlfn.LAMBDA(_xlpm.party, SUMIFS(ledger!J:J, ledger!B:B, _xlpm.party, ledger!E:E, "<>*RD*", ledger!D:D, "Satin", ledger!C:C, "<>November Closing CF") ))+ _xlfn.IFNA(J103, 0)} -> 0 | Z24: {=_xlfn.BYROW(B68, _xlfn.LAMBDA(_xlpm.party, SUMIFS(ledger!J:J, ledger!B:B, _xlpm.party, ledger!E:E, "<>*RD*", ledger!D:D, "Black-Chamki", ledger!C:C, "<>November Closing CF") ))+ _xlfn.IFNA(K103, 0)} -> 161653.26 | AA24: {=_xlfn.BYROW(B68, _xlfn.LAMBDA(_xlpm.party, SUMIFS(ledger!J:J, ledger!B:B, _xlpm.party, ledger!E:E, "<>*RD*", ledger!D:D, "Kataan", ledger!C:C, "<>November Closing CF") ))+ _xlfn.IFNA(L103, 0)} -> 0 | AB24: {=_xlfn.BYROW(B68, _xlfn.LAMBDA(_xlpm.party, SUMIFS(ledger!J:J, ledger!B:B, _xlpm.party, ledger!E:E, "<>*RD*", ledger!D:D, "Munaar", ledger!C:C, "<>November Closing CF") ))+ _xlfn.IFNA(M103, 0)} -> 0 | AC24: =V24+W24+X24+Y24+Z24+AA24+AB24 -> 973693.31 | AD24: =(SUMIF(Table14[Party],Q24,Table14[Credit]))+_xlfn.IFNA(O103,0) -> 973525 | AE24: =AC24-AD24 -> 168.30651 | AF24: 10 | AG24: 13
I25: Zia-ullah karachi | Q25: Shahid Qasayi | R25: {=_xlfn.BYROW(B69,_xlfn.LAMBDA(_xlpm.party,SUMIFS(ledger!G:G,ledger!B:B,_xlpm.party,ledger!E:E,"<>*RD*")))+_xlfn.IFNA(C104,0)} -> 263818 | S25: {=_xlfn.BYROW(B69, _xlfn.LAMBDA(_xlpm.party, SUMIFS(ledger!G:G, ledger!B:B, _xlpm.party, ledger!E:E, "<>*RD*") / 1.0936 ))+_xlfn.IFNA(D104,0)} -> 241238.11 | T25: {=(_xlfn.BYROW(B69,_xlfn.LAMBDA(_xlpm.party,SUMIFS(ledger!G:G,ledger!B:B,_xlpm.party,ledger!E:E,"<>*RD*",ledger!D:D,"Chamki")+SUMIFS(ledger!G:G, ledger!B:B, _xlpm.party, ledger!E:E, "<>*RD*", ledger!D:D, "Crinkle")))/1.0936)+_xlfn.IFNA(E104,0)} -> 189718.36 | U25: {=(_xlfn.BYROW(B69,_xlfn.LAMBDA(_xlpm.party,SUMIFS(ledger!G:G,ledger!B:B,_xlpm.party,ledger!E:E,"<>*RD*",ledger!D:D,"Silky")))/1.0936)+_xlfn.IFNA(F104,0)} -> 0 | V25: {=(_xlfn.BYROW(B69,_xlfn.LAMBDA(_xlpm.party, (SUMIFS(ledger!J:J,ledger!B:B,_xlpm.party,ledger!E:E,"<>*RD*",ledger!D:D,"Chamki",ledger!C:C,"<>November Closing CF")+ SUMIFS(ledger!J:J,ledger!B:B,_xlpm.party,ledger!E:E,"<>*RD*",ledger!D:D,"Crinkle",ledger!C:C,"<>November Closing CF") )+_xlfn.IFNA(G104,0))))} -> 1897183.6 | W25: {=_xlfn.BYROW(B69, _xlfn.LAMBDA(_xlpm.party, SUMIFS(ledger!J:J, ledger!B:B, _xlpm.party, ledger!E:E, "<>*RD*", ledger!D:D, "Silky", ledger!C:C, "<>November Closing CF") )) + _xlfn.IFNA(H104, 0)} -> 0 | X25: {=_xlfn.BYROW(B69, _xlfn.LAMBDA(_xlpm.party, SUMIFS(ledger!J:J, ledger!B:B, _xlpm.party, ledger!E:E, "<>*RD*", ledger!D:D, "Slub", ledger!C:C, "<>November Closing CF") ))+ _xlfn.IFNA(I104, 0)} -> 0 | Y25: {=_xlfn.BYROW(B69, _xlfn.LAMBDA(_xlpm.party, SUMIFS(ledger!J:J, ledger!B:B, _xlpm.party, ledger!E:E, "<>*RD*", ledger!D:D, "Satin", ledger!C:C, "<>November Closing CF") ))+ _xlfn.IFNA(J104, 0)} -> 0 | Z25: {=_xlfn.BYROW(B69, _xlfn.LAMBDA(_xlpm.party, SUMIFS(ledger!J:J, ledger!B:B, _xlpm.party, ledger!E:E, "<>*RD*", ledger!D:D, "Black-Chamki", ledger!C:C, "<>November Closing CF") ))+ _xlfn.IFNA(K104, 0)} -> 47534.748 | AA25: {=_xlfn.BYROW(B69, _xlfn.LAMBDA(_xlpm.party, SUMIFS(ledger!J:J, ledger!B:B, _xlpm.party, ledger!E:E, "<>*RD*", ledger!D:D, "Kataan", ledger!C:C, "<>November Closing CF") ))+ _xlfn.IFNA(L104, 0)} -> 523143.75 | AB25: {=_xlfn.BYROW(B69, _xlfn.LAMBDA(_xlpm.party, SUMIFS(ledger!J:J, ledger!B:B, _xlpm.party, ledger!E:E, "<>*RD*", ledger!D:D, "Munaar", ledger!C:C, "<>November Closing CF") ))+ _xlfn.IFNA(M104, 0)} -> 0 | AC25: =V25+W25+X25+Y25+Z25+AA25+AB25 -> 2467862.1 | AD25: =(SUMIF(Table14[Party],Q25,Table14[Credit]))+_xlfn.IFNA(O104,0) -> 2333095 | AE25: =AC25-AD25 -> 134767.11 | AF25: 10 | AG25: 13
I26: ZA | Q26: Hameed corporation | R26: {=_xlfn.BYROW(B70,_xlfn.LAMBDA(_xlpm.party,SUMIFS(ledger!G:G,ledger!B:B,_xlpm.party,ledger!E:E,"<>*RD*")))+_xlfn.IFNA(C105,0)} -> 46404 | S26: {=_xlfn.BYROW(B70, _xlfn.LAMBDA(_xlpm.party, SUMIFS(ledger!G:G, ledger!B:B, _xlpm.party, ledger!E:E, "<>*RD*") / 1.0936 ))+_xlfn.IFNA(D105,0)} -> 42432.334 | T26: {=(_xlfn.BYROW(B70,_xlfn.LAMBDA(_xlpm.party,SUMIFS(ledger!G:G,ledger!B:B,_xlpm.party,ledger!E:E,"<>*RD*",ledger!D:D,"Chamki")+SUMIFS(ledger!G:G, ledger!B:B, _xlpm.party, ledger!E:E, "<>*RD*", ledger!D:D, "Crinkle")))/1.0936)+_xlfn.IFNA(E105,0)} -> 42432.334 | U26: {=(_xlfn.BYROW(B70,_xlfn.LAMBDA(_xlpm.party,SUMIFS(ledger!G:G,ledger!B:B,_xlpm.party,ledger!E:E,"<>*RD*",ledger!D:D,"Silky")))/1.0936)+_xlfn.IFNA(F105,0)} -> 0 | V26: {=(_xlfn.BYROW(B70,_xlfn.LAMBDA(_xlpm.party, (SUMIFS(ledger!J:J,ledger!B:B,_xlpm.party,ledger!E:E,"<>*RD*",ledger!D:D,"Chamki",ledger!C:C,"<>November Closing CF")+ SUMIFS(ledger!J:J,ledger!B:B,_xlpm.party,ledger!E:E,"<>*RD*",ledger!D:D,"Crinkle",ledger!C:C,"<>November Closing CF") )+_xlfn.IFNA(G105,0))))} -> 424323.34 | W26: {=_xlfn.BYROW(B70, _xlfn.LAMBDA(_xlpm.party, SUMIFS(ledger!J:J, ledger!B:B, _xlpm.party, ledger!E:E, "<>*RD*", ledger!D:D, "Silky", ledger!C:C, "<>November Closing CF") )) + _xlfn.IFNA(H105, 0)} -> 0 | X26: {=_xlfn.BYROW(B70, _xlfn.LAMBDA(_xlpm.party, SUMIFS(ledger!J:J, ledger!B:B, _xlpm.party, ledger!E:E, "<>*RD*", ledger!D:D, "Slub", ledger!C:C, "<>November Closing CF") ))+ _xlfn.IFNA(I105, 0)} -> 0 | Y26: {=_xlfn.BYROW(B70, _xlfn.LAMBDA(_xlpm.party, SUMIFS(ledger!J:J, ledger!B:B, _xlpm.party, ledger!E:E, "<>*RD*", ledger!D:D, "Satin", ledger!C:C, "<>November Closing CF") ))+ _xlfn.IFNA(J105, 0)} -> 0 | Z26: {=_xlfn.BYROW(B70, _xlfn.LAMBDA(_xlpm.party, SUMIFS(ledger!J:J, ledger!B:B, _xlpm.party, ledger!E:E, "<>*RD*", ledger!D:D, "Black-Chamki", ledger!C:C, "<>November Closing CF") ))+ _xlfn.IFNA(K105, 0)} -> 0 | AA26: {=_xlfn.BYROW(B70, _xlfn.LAMBDA(_xlpm.party, SUMIFS(ledger!J:J, ledger!B:B, _xlpm.party, ledger!E:E, "<>*RD*", ledger!D:D, "Kataan", ledger!C:C, "<>November Closing CF") ))+ _xlfn.IFNA(L105, 0)} -> 0 | AB26: {=_xlfn.BYROW(B70, _xlfn.LAMBDA(_xlpm.party, SUMIFS(ledger!J:J, ledger!B:B, _xlpm.party, ledger!E:E, "<>*RD*", ledger!D:D, "Munaar", ledger!C:C, "<>November Closing CF") ))+ _xlfn.IFNA(M105, 0)} -> 0 | AC26: =V26+W26+X26+Y26+Z26+AA26+AB26 -> 424323.34 | AD26: =(SUMIF(Table14[Party],Q26,Table14[Credit]))+_xlfn.IFNA(O105,0) -> 424323 | AE26: =AC26-AD26 -> 0.33577176 | AF26: 10 | AG26: 13
I27: Ahmad Javaid | Q27: ibraheem behraam | R27: {=_xlfn.BYROW(B71,_xlfn.LAMBDA(_xlpm.party,SUMIFS(ledger!G:G,ledger!B:B,_xlpm.party,ledger!E:E,"<>*RD*")))+_xlfn.IFNA(C106,0)} -> 66705 | S27: {=_xlfn.BYROW(B71, _xlfn.LAMBDA(_xlpm.party, SUMIFS(ledger!G:G, ledger!B:B, _xlpm.party, ledger!E:E, "<>*RD*") / 1.0936 ))+_xlfn.IFNA(D106,0)} -> 60995.794 | T27: {=(_xlfn.BYROW(B71,_xlfn.LAMBDA(_xlpm.party,SUMIFS(ledger!G:G,ledger!B:B,_xlpm.party,ledger!E:E,"<>*RD*",ledger!D:D,"Chamki")+SUMIFS(ledger!G:G, ledger!B:B, _xlpm.party, ledger!E:E, "<>*RD*", ledger!D:D, "Crinkle")))/1.0936)+_xlfn.IFNA(E106,0)} -> 0 | U27: {=(_xlfn.BYROW(B71,_xlfn.LAMBDA(_xlpm.party,SUMIFS(ledger!G:G,ledger!B:B,_xlpm.party,ledger!E:E,"<>*RD*",ledger!D:D,"Silky")))/1.0936)+_xlfn.IFNA(F106,0)} -> 60995.794 | V27: {=(_xlfn.BYROW(B71,_xlfn.LAMBDA(_xlpm.party, (SUMIFS(ledger!J:J,ledger!B:B,_xlpm.party,ledger!E:E,"<>*RD*",ledger!D:D,"Chamki",ledger!C:C,"<>November Closing CF")+ SUMIFS(ledger!J:J,ledger!B:B,_xlpm.party,ledger!E:E,"<>*RD*",ledger!D:D,"Crinkle",ledger!C:C,"<>November Closing CF") )+_xlfn.IFNA(G106,0))))} -> 0 | W27: {=_xlfn.BYROW(B71, _xlfn.LAMBDA(_xlpm.party, SUMIFS(ledger!J:J, ledger!B:B, _xlpm.party, ledger!E:E, "<>*RD*", ledger!D:D, "Silky", ledger!C:C, "<>November Closing CF") )) + _xlfn.IFNA(H106, 0)} -> 792945.32 | X27: {=_xlfn.BYROW(B71, _xlfn.LAMBDA(_xlpm.party, SUMIFS(ledger!J:J, ledger!B:B, _xlpm.party, ledger!E:E, "<>*RD*", ledger!D:D, "Slub", ledger!C:C, "<>November Closing CF") ))+ _xlfn.IFNA(I106, 0)} -> 0 | Y27: {=_xlfn.BYROW(B71, _xlfn.LAMBDA(_xlpm.party, SUMIFS(ledger!J:J, ledger!B:B, _xlpm.party, ledger!E:E, "<>*RD*", ledger!D:D, "Satin", ledger!C:C, "<>November Closing CF") ))+ _xlfn.IFNA(J106, 0)} -> 0 | Z27: {=_xlfn.BYROW(B71, _xlfn.LAMBDA(_xlpm.party, SUMIFS(ledger!J:J, ledger!B:B, _xlpm.party, ledger!E:E, "<>*RD*", ledger!D:D, "Black-Chamki", ledger!C:C, "<>November Closing CF") ))+ _xlfn.IFNA(K106, 0)} -> 0 | AA27: {=_xlfn.BYROW(B71, _xlfn.LAMBDA(_xlpm.party, SUMIFS(ledger!J:J, ledger!B:B, _xlpm.party, ledger!E:E, "<>*RD*", ledger!D:D, "Kataan", ledger!C:C, "<>November Closing CF") ))+ _xlfn.IFNA(L106, 0)} -> 0 | AB27: {=_xlfn.BYROW(B71, _xlfn.LAMBDA(_xlpm.party, SUMIFS(ledger!J:J, ledger!B:B, _xlpm.party, ledger!E:E, "<>*RD*", ledger!D:D, "Munaar", ledger!C:C, "<>November Closing CF") ))+ _xlfn.IFNA(M106, 0)} -> 0 | AC27: =V27+W27+X27+Y27+Z27+AA27+AB27 -> 792945.32 | AD27: =(SUMIF(Table14[Party],Q27,Table14[Credit]))+_xlfn.IFNA(O106,0) -> 790500 | AE27: =AC27-AD27 -> 2445.3182 | AF27: 10 | AG27: 13
Q28: Zia-ullah karachi | R28: {=_xlfn.BYROW(B72,_xlfn.LAMBDA(_xlpm.party,SUMIFS(ledger!G:G,ledger!B:B,_xlpm.party,ledger!E:E,"<>*RD*")))+_xlfn.IFNA(C107,0)} -> 13622 | S28: {=_xlfn.BYROW(B72, _xlfn.LAMBDA(_xlpm.party, SUMIFS(ledger!G:G, ledger!B:B, _xlpm.party, ledger!E:E, "<>*RD*") / 1.0936 ))+_xlfn.IFNA(D107,0)} -> 12456.108 | T28: {=(_xlfn.BYROW(B72,_xlfn.LAMBDA(_xlpm.party,SUMIFS(ledger!G:G,ledger!B:B,_xlpm.party,ledger!E:E,"<>*RD*",ledger!D:D,"Chamki")+SUMIFS(ledger!G:G, ledger!B:B, _xlpm.party, ledger!E:E, "<>*RD*", ledger!D:D, "Crinkle")))/1.0936)+_xlfn.IFNA(E107,0)} -> 12456.108 | U28: {=(_xlfn.BYROW(B72,_xlfn.LAMBDA(_xlpm.party,SUMIFS(ledger!G:G,ledger!B:B,_xlpm.party,ledger!E:E,"<>*RD*",ledger!D:D,"Silky")))/1.0936)+_xlfn.IFNA(F107,0)} -> 0 | V28: {=(_xlfn.BYROW(B72,_xlfn.LAMBDA(_xlpm.party, (SUMIFS(ledger!J:J,ledger!B:B,_xlpm.party,ledger!E:E,"<>*RD*",ledger!D:D,"Chamki",ledger!C:C,"<>November Closing CF")+ SUMIFS(ledger!J:J,ledger!B:B,_xlpm.party,ledger!E:E,"<>*RD*",ledger!D:D,"Crinkle",ledger!C:C,"<>November Closing CF") )+_xlfn.IFNA(G107,0))))} -> 124561.08 | W28: {=_xlfn.BYROW(B72, _xlfn.LAMBDA(_xlpm.party, SUMIFS(ledger!J:J, ledger!B:B, _xlpm.party, ledger!E:E, "<>*RD*", ledger!D:D, "Silky", ledger!C:C, "<>November Closing CF") )) + _xlfn.IFNA(H107, 0)} -> 0 | X28: {=_xlfn.BYROW(B72, _xlfn.LAMBDA(_xlpm.party, SUMIFS(ledger!J:J, ledger!B:B, _xlpm.party, ledger!E:E, "<>*RD*", ledger!D:D, "Slub", ledger!C:C, "<>November Closing CF") ))+ _xlfn.IFNA(I107, 0)} -> 0 | Y28: {=_xlfn.BYROW(B72, _xlfn.LAMBDA(_xlpm.party, SUMIFS(ledger!J:J, ledger!B:B, _xlpm.party, ledger!E:E, "<>*RD*", ledger!D:D, "Satin", ledger!C:C, "<>November Closing CF") ))+ _xlfn.IFNA(J107, 0)} -> 0 | Z28: {=_xlfn.BYROW(B72, _xlfn.LAMBDA(_xlpm.party, SUMIFS(ledger!J:J, ledger!B:B, _xlpm.party, ledger!E:E, "<>*RD*", ledger!D:D, "Black-Chamki", ledger!C:C, "<>November Closing CF") ))+ _xlfn.IFNA(K107, 0)} -> 0 | AA28: {=_xlfn.BYROW(B72, _xlfn.LAMBDA(_xlpm.party, SUMIFS(ledger!J:J, ledger!B:B, _xlpm.party, ledger!E:E, "<>*RD*", ledger!D:D, "Kataan", ledger!C:C, "<>November Closing CF") ))+ _xlfn.IFNA(L107, 0)} -> 0 | AB28: {=_xlfn.BYROW(B72, _xlfn.LAMBDA(_xlpm.party, SUMIFS(ledger!J:J, ledger!B:B, _xlpm.party, ledger!E:E, "<>*RD*", ledger!D:D, "Munaar", ledger!C:C, "<>November Closing CF") ))+ _xlfn.IFNA(M107, 0)} -> 0 | AC28: =V28+W28+X28+Y28+Z28+AA28+AB28 -> 124561.08 | AD28: =(SUMIF(Table14[Party],Q28,Table14[Credit]))+_xlfn.IFNA(O107,0) -> 124560 | AE28: =AC28-AD28 -> 1.0826628 | AF28: 10 | AG28: 13
Q29: ZA | R29: {=_xlfn.BYROW(B73,_xlfn.LAMBDA(_xlpm.party,SUMIFS(ledger!G:G,ledger!B:B,_xlpm.party,ledger!E:E,"<>*RD*")))+_xlfn.IFNA(C108,0)} -> 32399 | S29: {=_xlfn.BYROW(B73, _xlfn.LAMBDA(_xlpm.party, SUMIFS(ledger!G:G, ledger!B:B, _xlpm.party, ledger!E:E, "<>*RD*") / 1.0936 ))+_xlfn.IFNA(D108,0)} -> 29626.006 | T29: {=(_xlfn.BYROW(B73,_xlfn.LAMBDA(_xlpm.party,SUMIFS(ledger!G:G,ledger!B:B,_xlpm.party,ledger!E:E,"<>*RD*",ledger!D:D,"Chamki")+SUMIFS(ledger!G:G, ledger!B:B, _xlpm.party, ledger!E:E, "<>*RD*", ledger!D:D, "Crinkle")))/1.0936)+_xlfn.IFNA(E108,0)} -> 0 | U29: {=(_xlfn.BYROW(B73,_xlfn.LAMBDA(_xlpm.party,SUMIFS(ledger!G:G,ledger!B:B,_xlpm.party,ledger!E:E,"<>*RD*",ledger!D:D,"Silky")))/1.0936)+_xlfn.IFNA(F108,0)} -> 29626.006 | V29: {=(_xlfn.BYROW(B73,_xlfn.LAMBDA(_xlpm.party, (SUMIFS(ledger!J:J,ledger!B:B,_xlpm.party,ledger!E:E,"<>*RD*",ledger!D:D,"Chamki",ledger!C:C,"<>November Closing CF")+ SUMIFS(ledger!J:J,ledger!B:B,_xlpm.party,ledger!E:E,"<>*RD*",ledger!D:D,"Crinkle",ledger!C:C,"<>November Closing CF") )+_xlfn.IFNA(G108,0))))} -> 0 | W29: {=_xlfn.BYROW(B73, _xlfn.LAMBDA(_xlpm.party, SUMIFS(ledger!J:J, ledger!B:B, _xlpm.party, ledger!E:E, "<>*RD*", ledger!D:D, "Silky", ledger!C:C, "<>November Closing CF") )) + _xlfn.IFNA(H108, 0)} -> 385138.08 | X29: {=_xlfn.BYROW(B73, _xlfn.LAMBDA(_xlpm.party, SUMIFS(ledger!J:J, ledger!B:B, _xlpm.party, ledger!E:E, "<>*RD*", ledger!D:D, "Slub", ledger!C:C, "<>November Closing CF") ))+ _xlfn.IFNA(I108, 0)} -> 0 | Y29: {=_xlfn.BYROW(B73, _xlfn.LAMBDA(_xlpm.party, SUMIFS(ledger!J:J, ledger!B:B, _xlpm.party, ledger!E:E, "<>*RD*", ledger!D:D, "Satin", ledger!C:C, "<>November Closing CF") ))+ _xlfn.IFNA(J108, 0)} -> 0 | Z29: {=_xlfn.BYROW(B73, _xlfn.LAMBDA(_xlpm.party, SUMIFS(ledger!J:J, ledger!B:B, _xlpm.party, ledger!E:E, "<>*RD*", ledger!D:D, "Black-Chamki", ledger!C:C, "<>November Closing CF") ))+ _xlfn.IFNA(K108, 0)} -> 0 | AA29: {=_xlfn.BYROW(B73, _xlfn.LAMBDA(_xlpm.party, SUMIFS(ledger!J:J, ledger!B:B, _xlpm.party, ledger!E:E, "<>*RD*", ledger!D:D, "Kataan", ledger!C:C, "<>November Closing CF") ))+ _xlfn.IFNA(L108, 0)} -> 0 | AB29: {=_xlfn.BYROW(B73, _xlfn.LAMBDA(_xlpm.party, SUMIFS(ledger!J:J, ledger!B:B, _xlpm.party, ledger!E:E, "<>*RD*", ledger!D:D, "Munaar", ledger!C:C, "<>November Closing CF") ))+ _xlfn.IFNA(M108, 0)} -> 0 | AC29: =V29+W29+X29+Y29+Z29+AA29+AB29 -> 385138.08 | AD29: =(SUMIF(Table14[Party],Q29,Table14[Credit]))+_xlfn.IFNA(O108,0) -> 250000 | AE29: =AC29-AD29 -> 135138.08 | AF29: 10 | AG29: 13
Q30: Ahmad Javaid | R30: {=_xlfn.BYROW(B74,_xlfn.LAMBDA(_xlpm.party,SUMIFS(ledger!G:G,ledger!B:B,_xlpm.party,ledger!E:E,"<>*RD*")))+_xlfn.IFNA(C109,0)} -> 12745 | S30: {=_xlfn.BYROW(B74, _xlfn.LAMBDA(_xlpm.party, SUMIFS(ledger!G:G, ledger!B:B, _xlpm.party, ledger!E:E, "<>*RD*") / 1.0936 ))+_xlfn.IFNA(D109,0)} -> 11654.17 | T30: {=(_xlfn.BYROW(B74,_xlfn.LAMBDA(_xlpm.party,SUMIFS(ledger!G:G,ledger!B:B,_xlpm.party,ledger!E:E,"<>*RD*",ledger!D:D,"Chamki")+SUMIFS(ledger!G:G, ledger!B:B, _xlpm.party, ledger!E:E, "<>*RD*", ledger!D:D, "Crinkle")))/1.0936)+_xlfn.IFNA(E109,0)} -> 0 | U30: {=(_xlfn.BYROW(B74,_xlfn.LAMBDA(_xlpm.party,SUMIFS(ledger!G:G,ledger!B:B,_xlpm.party,ledger!E:E,"<>*RD*",ledger!D:D,"Silky")))/1.0936)+_xlfn.IFNA(F109,0)} -> 0 | V30: {=(_xlfn.BYROW(B74,_xlfn.LAMBDA(_xlpm.party, (SUMIFS(ledger!J:J,ledger!B:B,_xlpm.party,ledger!E:E,"<>*RD*",ledger!D:D,"Chamki",ledger!C:C,"<>November Closing CF")+ SUMIFS(ledger!J:J,ledger!B:B,_xlpm.party,ledger!E:E,"<>*RD*",ledger!D:D,"Crinkle",ledger!C:C,"<>November Closing CF") )+_xlfn.IFNA(G109,0))))} -> 0 | W30: {=_xlfn.BYROW(B74, _xlfn.LAMBDA(_xlpm.party, SUMIFS(ledger!J:J, ledger!B:B, _xlpm.party, ledger!E:E, "<>*RD*", ledger!D:D, "Silky", ledger!C:C, "<>November Closing CF") )) + _xlfn.IFNA(H109, 0)} -> 0 | X30: {=_xlfn.BYROW(B74, _xlfn.LAMBDA(_xlpm.party, SUMIFS(ledger!J:J, ledger!B:B, _xlpm.party, ledger!E:E, "<>*RD*", ledger!D:D, "Slub", ledger!C:C, "<>November Closing CF") ))+ _xlfn.IFNA(I109, 0)} -> 0 | Y30: {=_xlfn.BYROW(B74, _xlfn.LAMBDA(_xlpm.party, SUMIFS(ledger!J:J, ledger!B:B, _xlpm.party, ledger!E:E, "<>*RD*", ledger!D:D, "Satin", ledger!C:C, "<>November Closing CF") ))+ _xlfn.IFNA(J109, 0)} -> 0 | Z30: {=_xlfn.BYROW(B74, _xlfn.LAMBDA(_xlpm.party, SUMIFS(ledger!J:J, ledger!B:B, _xlpm.party, ledger!E:E, "<>*RD*", ledger!D:D, "Black-Chamki", ledger!C:C, "<>November Closing CF") ))+ _xlfn.IFNA(K109, 0)} -> 0 | AA30: {=_xlfn.BYROW(B74, _xlfn.LAMBDA(_xlpm.party, SUMIFS(ledger!J:J, ledger!B:B, _xlpm.party, ledger!E:E, "<>*RD*", ledger!D:D, "Kataan", ledger!C:C, "<>November Closing CF") ))+ _xlfn.IFNA(L109, 0)} -> 0 | AB30: {=_xlfn.BYROW(B74, _xlfn.LAMBDA(_xlpm.party, SUMIFS(ledger!J:J, ledger!B:B, _xlpm.party, ledger!E:E, "<>*RD*", ledger!D:D, "Munaar", ledger!C:C, "<>November Closing CF") ))+ _xlfn.IFNA(M109, 0)} -> 151504.21 | AC30: =V30+W30+X30+Y30+Z30+AA30+AB30 -> 151504.21 | AD30: =(SUMIF(Table14[Party],Q30,Table14[Credit]))+_xlfn.IFNA(O109,0) -> 0 | AE30: =AC30-AD30 -> 151504.21 | AF30: 10 | AG30: 13
R31: {=_xlfn.BYROW(B75,_xlfn.LAMBDA(_xlpm.party,SUMIFS(ledger!G:G,ledger!B:B,_xlpm.party,ledger!E:E,"<>*RD*")))+_xlfn.IFNA(C110,0)} -> 0 | S31: {=_xlfn.BYROW(B75, _xlfn.LAMBDA(_xlpm.party, SUMIFS(ledger!G:G, ledger!B:B, _xlpm.party, ledger!E:E, "<>*RD*") / 1.0936 ))+_xlfn.IFNA(D110,0)} -> 0 | T31: {=(_xlfn.BYROW(B75,_xlfn.LAMBDA(_xlpm.party,SUMIFS(ledger!G:G,ledger!B:B,_xlpm.party,ledger!E:E,"<>*RD*",ledger!D:D,"Chamki")+SUMIFS(ledger!G:G, ledger!B:B, _xlpm.party, ledger!E:E, "<>*RD*", ledger!D:D, "Crinkle")))/1.0936)+_xlfn.IFNA(E110,0)} -> 0 | U31: {=(_xlfn.BYROW(B75,_xlfn.LAMBDA(_xlpm.party,SUMIFS(ledger!G:G,ledger!B:B,_xlpm.party,ledger!E:E,"<>*RD*",ledger!D:D,"Silky")))/1.0936)+_xlfn.IFNA(F110,0)} -> 0 | V31: {=(_xlfn.BYROW(B75,_xlfn.LAMBDA(_xlpm.party, (SUMIFS(ledger!J:J,ledger!B:B,_xlpm.party,ledger!E:E,"<>*RD*",ledger!D:D,"Chamki",ledger!C:C,"<>November Closing CF")+ SUMIFS(ledger!J:J,ledger!B:B,_xlpm.party,ledger!E:E,"<>*RD*",ledger!D:D,"Crinkle",ledger!C:C,"<>November Closing CF") )+_xlfn.IFNA(G110,0))))} -> 0 | W31: {=_xlfn.BYROW(B75, _xlfn.LAMBDA(_xlpm.party, SUMIFS(ledger!J:J, ledger!B:B, _xlpm.party, ledger!E:E, "<>*RD*", ledger!D:D, "Silky", ledger!C:C, "<>November Closing CF") )) + _xlfn.IFNA(H110, 0)} -> 0 | X31: {=_xlfn.BYROW(B75, _xlfn.LAMBDA(_xlpm.party, SUMIFS(ledger!J:J, ledger!B:B, _xlpm.party, ledger!E:E, "<>*RD*", ledger!D:D, "Slub", ledger!C:C, "<>November Closing CF") ))+ _xlfn.IFNA(I110, 0)} -> 0 | Y31: {=_xlfn.BYROW(B75, _xlfn.LAMBDA(_xlpm.party, SUMIFS(ledger!J:J, ledger!B:B, _xlpm.party, ledger!E:E, "<>*RD*", ledger!D:D, "Satin", ledger!C:C, "<>November Closing CF") ))+ _xlfn.IFNA(J110, 0)} -> 0 | Z31: {=_xlfn.BYROW(B75, _xlfn.LAMBDA(_xlpm.party, SUMIFS(ledger!J:J, ledger!B:B, _xlpm.party, ledger!E:E, "<>*RD*", ledger!D:D, "Black-Chamki", ledger!C:C, "<>November Closing CF") ))+ _xlfn.IFNA(K110, 0)} -> 0 | AA31: {=_xlfn.BYROW(B75, _xlfn.LAMBDA(_xlpm.party, SUMIFS(ledger!J:J, ledger!B:B, _xlpm.party, ledger!E:E, "<>*RD*", ledger!D:D, "Kataan", ledger!C:C, "<>November Closing CF") ))+ _xlfn.IFNA(L110, 0)} -> 0 | AB31: {=_xlfn.BYROW(B75, _xlfn.LAMBDA(_xlpm.party, SUMIFS(ledger!J:J, ledger!B:B, _xlpm.party, ledger!E:E, "<>*RD*", ledger!D:D, "Munaar", ledger!C:C, "<>November Closing CF") ))+ _xlfn.IFNA(M110, 0)} -> 0 | AC31: =V31+W31+X31+Y31+Z31+AA31+AB31 -> 0 | AD31: =(SUMIF(Table14[Party],Q31,Table14[Credit]))+_xlfn.IFNA(O110,0) -> 0 | AE31: =AC31-AD31 -> 0 | AF31: 10 | AG31: 13
R32: {=_xlfn.BYROW(B76,_xlfn.LAMBDA(_xlpm.party,SUMIFS(ledger!G:G,ledger!B:B,_xlpm.party,ledger!E:E,"<>*RD*")))+_xlfn.IFNA(C111,0)} -> 0 | S32: {=_xlfn.BYROW(B76, _xlfn.LAMBDA(_xlpm.party, SUMIFS(ledger!G:G, ledger!B:B, _xlpm.party, ledger!E:E, "<>*RD*") / 1.0936 ))+_xlfn.IFNA(D111,0)} -> 0 | T32: {=(_xlfn.BYROW(B76,_xlfn.LAMBDA(_xlpm.party,SUMIFS(ledger!G:G,ledger!B:B,_xlpm.party,ledger!E:E,"<>*RD*",ledger!D:D,"Chamki")+SUMIFS(ledger!G:G, ledger!B:B, _xlpm.party, ledger!E:E, "<>*RD*", ledger!D:D, "Crinkle")))/1.0936)+_xlfn.IFNA(E111,0)} -> 0 | U32: {=(_xlfn.BYROW(B76,_xlfn.LAMBDA(_xlpm.party,SUMIFS(ledger!G:G,ledger!B:B,_xlpm.party,ledger!E:E,"<>*RD*",ledger!D:D,"Silky")))/1.0936)+_xlfn.IFNA(F111,0)} -> 0 | V32: {=(_xlfn.BYROW(B76,_xlfn.LAMBDA(_xlpm.party, (SUMIFS(ledger!J:J,ledger!B:B,_xlpm.party,ledger!E:E,"<>*RD*",ledger!D:D,"Chamki",ledger!C:C,"<>November Closing CF")+ SUMIFS(ledger!J:J,ledger!B:B,_xlpm.party,ledger!E:E,"<>*RD*",ledger!D:D,"Crinkle",ledger!C:C,"<>November Closing CF") )+_xlfn.IFNA(G111,0))))} -> 0 | W32: {=_xlfn.BYROW(B76, _xlfn.LAMBDA(_xlpm.party, SUMIFS(ledger!J:J, ledger!B:B, _xlpm.party, ledger!E:E, "<>*RD*", ledger!D:D, "Silky", ledger!C:C, "<>November Closing CF") )) + _xlfn.IFNA(H111, 0)} -> 0 | X32: {=_xlfn.BYROW(B76, _xlfn.LAMBDA(_xlpm.party, SUMIFS(ledger!J:J, ledger!B:B, _xlpm.party, ledger!E:E, "<>*RD*", ledger!D:D, "Slub", ledger!C:C, "<>November Closing CF") ))+ _xlfn.IFNA(I111, 0)} -> 0 | Y32: {=_xlfn.BYROW(B76, _xlfn.LAMBDA(_xlpm.party, SUMIFS(ledger!J:J, ledger!B:B, _xlpm.party, ledger!E:E, "<>*RD*", ledger!D:D, "Satin", ledger!C:C, "<>November Closing CF") ))+ _xlfn.IFNA(J111, 0)} -> 0 | Z32: {=_xlfn.BYROW(B76, _xlfn.LAMBDA(_xlpm.party, SUMIFS(ledger!J:J, ledger!B:B, _xlpm.party, ledger!E:E, "<>*RD*", ledger!D:D, "Black-Chamki", ledger!C:C, "<>November Closing CF") ))+ _xlfn.IFNA(K111, 0)} -> 0 | AA32: {=_xlfn.BYROW(B76, _xlfn.LAMBDA(_xlpm.party, SUMIFS(ledger!J:J, ledger!B:B, _xlpm.party, ledger!E:E, "<>*RD*", ledger!D:D, "Kataan", ledger!C:C, "<>November Closing CF") ))+ _xlfn.IFNA(L111, 0)} -> 0 | AB32: {=_xlfn.BYROW(B76, _xlfn.LAMBDA(_xlpm.party, SUMIFS(ledger!J:J, ledger!B:B, _xlpm.party, ledger!E:E, "<>*RD*", ledger!D:D, "Munaar", ledger!C:C, "<>November Closing CF") ))+ _xlfn.IFNA(M111, 0)} -> 0 | AC32: =V32+W32+X32+Y32+Z32+AA32+AB32 -> 0 | AD32: =(SUMIF(Table14[Party],Q32,Table14[Credit]))+_xlfn.IFNA(O111,0) -> 0 | AE32: =AC32-AD32 -> 0 | AF32: 10 | AG32: 13
R33: {=_xlfn.BYROW(B77,_xlfn.LAMBDA(_xlpm.party,SUMIFS(ledger!G:G,ledger!B:B,_xlpm.party,ledger!E:E,"<>*RD*")))+_xlfn.IFNA(C112,0)} -> 0 | S33: {=_xlfn.BYROW(B77, _xlfn.LAMBDA(_xlpm.party, SUMIFS(ledger!G:G, ledger!B:B, _xlpm.party, ledger!E:E, "<>*RD*") / 1.0936 ))+_xlfn.IFNA(D112,0)} -> 0 | T33: {=(_xlfn.BYROW(B77,_xlfn.LAMBDA(_xlpm.party,SUMIFS(ledger!G:G,ledger!B:B,_xlpm.party,ledger!E:E,"<>*RD*",ledger!D:D,"Chamki")+SUMIFS(ledger!G:G, ledger!B:B, _xlpm.party, ledger!E:E, "<>*RD*", ledger!D:D, "Crinkle")))/1.0936)+_xlfn.IFNA(E112,0)} -> 0 | U33: {=(_xlfn.BYROW(B77,_xlfn.LAMBDA(_xlpm.party,SUMIFS(ledger!G:G,ledger!B:B,_xlpm.party,ledger!E:E,"<>*RD*",ledger!D:D,"Silky")))/1.0936)+_xlfn.IFNA(F112,0)} -> 0 | V33: {=(_xlfn.BYROW(B77,_xlfn.LAMBDA(_xlpm.party, (SUMIFS(ledger!J:J,ledger!B:B,_xlpm.party,ledger!E:E,"<>*RD*",ledger!D:D,"Chamki",ledger!C:C,"<>November Closing CF")+ SUMIFS(ledger!J:J,ledger!B:B,_xlpm.party,ledger!E:E,"<>*RD*",ledger!D:D,"Crinkle",ledger!C:C,"<>November Closing CF") )+_xlfn.IFNA(G112,0))))} -> 0 | W33: {=_xlfn.BYROW(B77, _xlfn.LAMBDA(_xlpm.party, SUMIFS(ledger!J:J, ledger!B:B, _xlpm.party, ledger!E:E, "<>*RD*", ledger!D:D, "Silky", ledger!C:C, "<>November Closing CF") )) + _xlfn.IFNA(H112, 0)} -> 0 | X33: {=_xlfn.BYROW(B77, _xlfn.LAMBDA(_xlpm.party, SUMIFS(ledger!J:J, ledger!B:B, _xlpm.party, ledger!E:E, "<>*RD*", ledger!D:D, "Slub", ledger!C:C, "<>November Closing CF") ))+ _xlfn.IFNA(I112, 0)} -> 0 | Y33: {=_xlfn.BYROW(B77, _xlfn.LAMBDA(_xlpm.party, SUMIFS(ledger!J:J, ledger!B:B, _xlpm.party, ledger!E:E, "<>*RD*", ledger!D:D, "Satin", ledger!C:C, "<>November Closing CF") ))+ _xlfn.IFNA(J112, 0)} -> 0 | Z33: {=_xlfn.BYROW(B77, _xlfn.LAMBDA(_xlpm.party, SUMIFS(ledger!J:J, ledger!B:B, _xlpm.party, ledger!E:E, "<>*RD*", ledger!D:D, "Black-Chamki", ledger!C:C, "<>November Closing CF") ))+ _xlfn.IFNA(K112, 0)} -> 0 | AA33: {=_xlfn.BYROW(B77, _xlfn.LAMBDA(_xlpm.party, SUMIFS(ledger!J:J, ledger!B:B, _xlpm.party, ledger!E:E, "<>*RD*", ledger!D:D, "Kataan", ledger!C:C, "<>November Closing CF") ))+ _xlfn.IFNA(L112, 0)} -> 0 | AB33: {=_xlfn.BYROW(B77, _xlfn.LAMBDA(_xlpm.party, SUMIFS(ledger!J:J, ledger!B:B, _xlpm.party, ledger!E:E, "<>*RD*", ledger!D:D, "Munaar", ledger!C:C, "<>November Closing CF") ))+ _xlfn.IFNA(M112, 0)} -> 0 | AC33: =V33+W33+X33+Y33+Z33+AA33+AB33 -> 0 | AD33: =(SUMIF(Table14[Party],Q33,Table14[Credit]))+_xlfn.IFNA(O112,0) -> 0 | AE33: =AC33-AD33 -> 0 | AF33: 10 | AG33: 13
R34: {=_xlfn.BYROW(B78,_xlfn.LAMBDA(_xlpm.party,SUMIFS(ledger!G:G,ledger!B:B,_xlpm.party,ledger!E:E,"<>*RD*")))+_xlfn.IFNA(C113,0)} -> 0 | S34: {=_xlfn.BYROW(B78, _xlfn.LAMBDA(_xlpm.party, SUMIFS(ledger!G:G, ledger!B:B, _xlpm.party, ledger!E:E, "<>*RD*") / 1.0936 ))+_xlfn.IFNA(D113,0)} -> 0 | T34: {=(_xlfn.BYROW(B78,_xlfn.LAMBDA(_xlpm.party,SUMIFS(ledger!G:G,ledger!B:B,_xlpm.party,ledger!E:E,"<>*RD*",ledger!D:D,"Chamki")+SUMIFS(ledger!G:G, ledger!B:B, _xlpm.party, ledger!E:E, "<>*RD*", ledger!D:D, "Crinkle")))/1.0936)+_xlfn.IFNA(E113,0)} -> 0 | U34: {=(_xlfn.BYROW(B78,_xlfn.LAMBDA(_xlpm.party,SUMIFS(ledger!G:G,ledger!B:B,_xlpm.party,ledger!E:E,"<>*RD*",ledger!D:D,"Silky")))/1.0936)+_xlfn.IFNA(F113,0)} -> 0 | V34: {=(_xlfn.BYROW(B78,_xlfn.LAMBDA(_xlpm.party, (SUMIFS(ledger!J:J,ledger!B:B,_xlpm.party,ledger!E:E,"<>*RD*",ledger!D:D,"Chamki",ledger!C:C,"<>November Closing CF")+ SUMIFS(ledger!J:J,ledger!B:B,_xlpm.party,ledger!E:E,"<>*RD*",ledger!D:D,"Crinkle",ledger!C:C,"<>November Closing CF") )+_xlfn.IFNA(G113,0))))} -> 0 | W34: {=_xlfn.BYROW(B78, _xlfn.LAMBDA(_xlpm.party, SUMIFS(ledger!J:J, ledger!B:B, _xlpm.party, ledger!E:E, "<>*RD*", ledger!D:D, "Silky", ledger!C:C, "<>November Closing CF") )) + _xlfn.IFNA(H113, 0)} -> 0 | X34: {=_xlfn.BYROW(B78, _xlfn.LAMBDA(_xlpm.party, SUMIFS(ledger!J:J, ledger!B:B, _xlpm.party, ledger!E:E, "<>*RD*", ledger!D:D, "Slub", ledger!C:C, "<>November Closing CF") ))+ _xlfn.IFNA(I113, 0)} -> 0 | Y34: {=_xlfn.BYROW(B78, _xlfn.LAMBDA(_xlpm.party, SUMIFS(ledger!J:J, ledger!B:B, _xlpm.party, ledger!E:E, "<>*RD*", ledger!D:D, "Satin", ledger!C:C, "<>November Closing CF") ))+ _xlfn.IFNA(J113, 0)} -> 0 | Z34: {=_xlfn.BYROW(B78, _xlfn.LAMBDA(_xlpm.party, SUMIFS(ledger!J:J, ledger!B:B, _xlpm.party, ledger!E:E, "<>*RD*", ledger!D:D, "Black-Chamki", ledger!C:C, "<>November Closing CF") ))+ _xlfn.IFNA(K113, 0)} -> 0 | AA34: {=_xlfn.BYROW(B78, _xlfn.LAMBDA(_xlpm.party, SUMIFS(ledger!J:J, ledger!B:B, _xlpm.party, ledger!E:E, "<>*RD*", ledger!D:D, "Kataan", ledger!C:C, "<>November Closing CF") ))+ _xlfn.IFNA(L113, 0)} -> 0 | AB34: {=_xlfn.BYROW(B78, _xlfn.LAMBDA(_xlpm.party, SUMIFS(ledger!J:J, ledger!B:B, _xlpm.party, ledger!E:E, "<>*RD*", ledger!D:D, "Munaar", ledger!C:C, "<>November Closing CF") ))+ _xlfn.IFNA(M113, 0)} -> 0 | AC34: =V34+W34+X34+Y34+Z34+AA34+AB34 -> 0 | AD34: =(SUMIF(Table14[Party],Q34,Table14[Credit]))+_xlfn.IFNA(O113,0) -> 0 | AE34: =AC34-AD34 -> 0 | AF34: 10 | AG34: 13
R35: {=_xlfn.BYROW(B79,_xlfn.LAMBDA(_xlpm.party,SUMIFS(ledger!G:G,ledger!B:B,_xlpm.party,ledger!E:E,"<>*RD*")))+_xlfn.IFNA(C114,0)} -> 0 | S35: {=_xlfn.BYROW(B79, _xlfn.LAMBDA(_xlpm.party, SUMIFS(ledger!G:G, ledger!B:B, _xlpm.party, ledger!E:E, "<>*RD*") / 1.0936 ))+_xlfn.IFNA(D114,0)} -> 0 | T35: {=(_xlfn.BYROW(B79,_xlfn.LAMBDA(_xlpm.party,SUMIFS(ledger!G:G,ledger!B:B,_xlpm.party,ledger!E:E,"<>*RD*",ledger!D:D,"Chamki")+SUMIFS(ledger!G:G, ledger!B:B, _xlpm.party, ledger!E:E, "<>*RD*", ledger!D:D, "Crinkle")))/1.0936)+_xlfn.IFNA(E114,0)} -> 0 | U35: {=(_xlfn.BYROW(B79,_xlfn.LAMBDA(_xlpm.party,SUMIFS(ledger!G:G,ledger!B:B,_xlpm.party,ledger!E:E,"<>*RD*",ledger!D:D,"Silky")))/1.0936)+_xlfn.IFNA(F114,0)} -> 0 | V35: {=(_xlfn.BYROW(B79,_xlfn.LAMBDA(_xlpm.party, (SUMIFS(ledger!J:J,ledger!B:B,_xlpm.party,ledger!E:E,"<>*RD*",ledger!D:D,"Chamki",ledger!C:C,"<>November Closing CF")+ SUMIFS(ledger!J:J,ledger!B:B,_xlpm.party,ledger!E:E,"<>*RD*",ledger!D:D,"Crinkle",ledger!C:C,"<>November Closing CF") )+_xlfn.IFNA(G114,0))))} -> 0 | W35: {=_xlfn.BYROW(B79, _xlfn.LAMBDA(_xlpm.party, SUMIFS(ledger!J:J, ledger!B:B, _xlpm.party, ledger!E:E, "<>*RD*", ledger!D:D, "Silky", ledger!C:C, "<>November Closing CF") )) + _xlfn.IFNA(H114, 0)} -> 0 | X35: {=_xlfn.BYROW(B79, _xlfn.LAMBDA(_xlpm.party, SUMIFS(ledger!J:J, ledger!B:B, _xlpm.party, ledger!E:E, "<>*RD*", ledger!D:D, "Slub", ledger!C:C, "<>November Closing CF") ))+ _xlfn.IFNA(I114, 0)} -> 0 | Y35: {=_xlfn.BYROW(B79, _xlfn.LAMBDA(_xlpm.party, SUMIFS(ledger!J:J, ledger!B:B, _xlpm.party, ledger!E:E, "<>*RD*", ledger!D:D, "Satin", ledger!C:C, "<>November Closing CF") ))+ _xlfn.IFNA(J114, 0)} -> 0 | Z35: {=_xlfn.BYROW(B79, _xlfn.LAMBDA(_xlpm.party, SUMIFS(ledger!J:J, ledger!B:B, _xlpm.party, ledger!E:E, "<>*RD*", ledger!D:D, "Black-Chamki", ledger!C:C, "<>November Closing CF") ))+ _xlfn.IFNA(K114, 0)} -> 0 | AA35: {=_xlfn.BYROW(B79, _xlfn.LAMBDA(_xlpm.party, SUMIFS(ledger!J:J, ledger!B:B, _xlpm.party, ledger!E:E, "<>*RD*", ledger!D:D, "Kataan", ledger!C:C, "<>November Closing CF") ))+ _xlfn.IFNA(L114, 0)} -> 0 | AB35: {=_xlfn.BYROW(B79, _xlfn.LAMBDA(_xlpm.party, SUMIFS(ledger!J:J, ledger!B:B, _xlpm.party, ledger!E:E, "<>*RD*", ledger!D:D, "Munaar", ledger!C:C, "<>November Closing CF") ))+ _xlfn.IFNA(M114, 0)} -> 0 | AC35: =V35+W35+X35+Y35+Z35+AA35+AB35 -> 0 | AD35: =(SUMIF(Table14[Party],Q35,Table14[Credit]))+_xlfn.IFNA(O114,0) -> 0 | AE35: =AC35-AD35 -> 0 | AF35: 10 | AG35: 13
V36: {=(_xlfn.BYROW(B80,_xlfn.LAMBDA(_xlpm.party, (SUMIFS(ledger!J:J,ledger!B:B,_xlpm.party,ledger!E:E,"<>*RD*",ledger!D:D,"Chamki",ledger!C:C,"<>November Closing CF")+ SUMIFS(ledger!J:J,ledger!B:B,_xlpm.party,ledger!E:E,"<>*RD*",ledger!D:D,"Crinkle",ledger!C:C,"<>November Closing CF") )+_xlfn.IFNA(G115,0))))} -> 0 | W36: {=_xlfn.BYROW(B80, _xlfn.LAMBDA(_xlpm.party, SUMIFS(ledger!J:J, ledger!B:B, _xlpm.party, ledger!E:E, "<>*RD*", ledger!D:D, "Silky", ledger!C:C, "<>November Closing CF") )) + _xlfn.IFNA(H115, 0)} -> 0 | X36: {=_xlfn.BYROW(B80, _xlfn.LAMBDA(_xlpm.party, SUMIFS(ledger!J:J, ledger!B:B, _xlpm.party, ledger!E:E, "<>*RD*", ledger!D:D, "Slub", ledger!C:C, "<>November Closing CF") ))+ _xlfn.IFNA(I115, 0)} -> 0 | Y36: {=_xlfn.BYROW(B80, _xlfn.LAMBDA(_xlpm.party, SUMIFS(ledger!J:J, ledger!B:B, _xlpm.party, ledger!E:E, "<>*RD*", ledger!D:D, "Satin", ledger!C:C, "<>November Closing CF") ))+ _xlfn.IFNA(J115, 0)} -> 0 | Z36: {=_xlfn.BYROW(B80, _xlfn.LAMBDA(_xlpm.party, SUMIFS(ledger!J:J, ledger!B:B, _xlpm.party, ledger!E:E, "<>*RD*", ledger!D:D, "Black-Chamki", ledger!C:C, "<>November Closing CF") ))+ _xlfn.IFNA(K115, 0)} -> 0 | AA36: {=_xlfn.BYROW(B80, _xlfn.LAMBDA(_xlpm.party, SUMIFS(ledger!J:J, ledger!B:B, _xlpm.party, ledger!E:E, "<>*RD*", ledger!D:D, "Kataan", ledger!C:C, "<>November Closing CF") ))+ _xlfn.IFNA(L115, 0)} -> 0 | AB36: {=_xlfn.BYROW(B80, _xlfn.LAMBDA(_xlpm.party, SUMIFS(ledger!J:J, ledger!B:B, _xlpm.party, ledger!E:E, "<>*RD*", ledger!D:D, "Munaar", ledger!C:C, "<>November Closing CF") ))+ _xlfn.IFNA(M115, 0)} -> 0 | AC36: =V36+W36+X36+Y36+Z36+AA36+AB36 -> 0 | AD36: =(SUMIF(Table14[Party],Q36,Table14[Credit]))+_xlfn.IFNA(O115,0) -> 0
B47: Billing September
C48: Gaz | D48: Total Metres | E48: Total Chamki | F48: Total Super Silky | G48: Billing (Chamki/Crinkle) | H48: Billing (Super Chamki) | I48: Billing (Slub) | J48: Billing (Satin) | K48: Billing (Black-chamki) | L48: Billing (Kataan) | M48: Billing (Munaar) | N48: Adjusted Bill | O48: Amount Paid | P48: Balance | Q48: Rate (Chamki) | R48: Rate (Super Silky)
A49: Parties: | B49: {=_xlfn.UNIQUE(Table1[Party Name])} -> BSC | C49: {=_xlfn.BYROW(_xlfn.ANCHORARRAY(B49),_xlfn.LAMBDA(_xlpm.party,SUMIFS(ledger!G:G,ledger!B:B,_xlpm.party,ledger!E:E,"<>*RD*")))} -> 219582.88 | D49: {=_xlfn.BYROW(_xlfn.ANCHORARRAY(B49), _xlfn.LAMBDA(_xlpm.party, SUMIFS(ledger!G:G, ledger!B:B, _xlpm.party, ledger!E:E, "<>*RD*") / 1.0936 ))} -> 200789.03 | E49: {=(_xlfn.BYROW(_xlfn.ANCHORARRAY(B49),_xlfn.LAMBDA(_xlpm.party,SUMIFS(ledger!G:G,ledger!B:B,_xlpm.party,ledger!E:E,"<>*RD*",ledger!D:D,"Chamki")+SUMIFS(ledger!G:G, ledger!B:B, _xlpm.party, ledger!E:E, "<>*RD*", ledger!D:D, "Crinkle")))/1.0936)} -> 200789.03 | F49: {=(_xlfn.BYROW(_xlfn.ANCHORARRAY(B49),_xlfn.LAMBDA(_xlpm.party,SUMIFS(ledger!G:G,ledger!B:B,_xlpm.party,ledger!E:E,"<>*RD*",ledger!D:D,"Silky")))/1.0936)} -> 0 | G49: {=(_xlfn.BYROW(B49,_xlfn.LAMBDA(_xlpm.party, (SUMIFS(ledger!J:J,ledger!B:B,_xlpm.party,ledger!E:E,"<>*RD*",ledger!D:D,"Chamki",ledger!C:C,"<>November Closing CF")+ SUMIFS(ledger!J:J,ledger!B:B,_xlpm.party,ledger!E:E,"<>*RD*",ledger!D:D,"Crinkle",ledger!C:C,"<>November Closing CF") ))))} -> 2007890.3 | H49: {=_xlfn.BYROW(B49, _xlfn.LAMBDA(_xlpm.party, SUMIFS(ledger!J:J, ledger!B:B, _xlpm.party, ledger!E:E, "<>*RD*", ledger!D:D, "Silky", ledger!C:C, "<>November Closing CF") ))} -> 0 | I49: {=_xlfn.BYROW(B49, _xlfn.LAMBDA(_xlpm.party, SUMIFS(ledger!J:J, ledger!B:B, _xlpm.party, ledger!E:E, "<>*RD*", ledger!D:D, "Slub", ledger!C:C, "<>November Closing CF") ))} -> 0 | J49: {=_xlfn.BYROW(B49, _xlfn.LAMBDA(_xlpm.party, SUMIFS(ledger!J:J, ledger!B:B, _xlpm.party, ledger!E:E, "<>*RD*", ledger!D:D, "Satin", ledger!C:C, "<>November Closing CF") ))} -> 0 | K49: {=_xlfn.BYROW(B49, _xlfn.LAMBDA(_xlpm.party, SUMIFS(ledger!J:J, ledger!B:B, _xlpm.party, ledger!E:E, "<>*RD*", ledger!D:D, "Black-chamki", ledger!C:C, "<>November Closing CF") ))} -> 0 | L49: {=_xlfn.BYROW(B49, _xlfn.LAMBDA(_xlpm.party, SUMIFS(ledger!J:J, ledger!B:B, _xlpm.party, ledger!E:E, "<>*RD*", ledger!D:D, "Kataan", ledger!C:C, "<>November Closing CF") ))} -> 0 | M49: {=_xlfn.BYROW(B49, _xlfn.LAMBDA(_xlpm.party, SUMIFS(ledger!J:J, ledger!B:B, _xlpm.party, ledger!E:E, "<>*RD*", ledger!D:D, "Munaar", ledger!C:C, "<>November Closing CF") ))} -> 0 | N49: =SUM(G49:M49) -> 2007890.3 | O49: =(SUMIF(Table14[Party],B49,Table14[Credit])) -> 0 | P49: =N49-O49 -> 2007890.3 | Q49: 10 | R49: 12
B50: Ejaz Sahab | C50: 37275 | D50: 34084.674 | E50: 0 | F50: 34084.674 | G50: {=(_xlfn.BYROW(B50,_xlfn.LAMBDA(_xlpm.party, (SUMIFS(ledger!J:J,ledger!B:B,_xlpm.party,ledger!E:E,"<>*RD*",ledger!D:D,"Chamki",ledger!C:C,"<>November Closing CF")+ SUMIFS(ledger!J:J,ledger!B:B,_xlpm.party,ledger!E:E,"<>*RD*",ledger!D:D,"Crinkle",ledger!C:C,"<>November Closing CF") ))))} -> 0 | H50: {=_xlfn.BYROW(B50, _xlfn.LAMBDA(_xlpm.party, SUMIFS(ledger!J:J, ledger!B:B, _xlpm.party, ledger!E:E, "<>*RD*", ledger!D:D, "Silky", ledger!C:C, "<>November Closing CF") ))} -> 443100.77 | I50: {=_xlfn.BYROW(B50, _xlfn.LAMBDA(_xlpm.party, SUMIFS(ledger!J:J, ledger!B:B, _xlpm.party, ledger!E:E, "<>*RD*", ledger!D:D, "Slub", ledger!C:C, "<>November Closing CF") ))} -> 0 | J50: {=_xlfn.BYROW(B50, _xlfn.LAMBDA(_xlpm.party, SUMIFS(ledger!J:J, ledger!B:B, _xlpm.party, ledger!E:E, "<>*RD*", ledger!D:D, "Satin", ledger!C:C, "<>November Closing CF") ))} -> 0 | K50: {=_xlfn.BYROW(B50, _xlfn.LAMBDA(_xlpm.party, SUMIFS(ledger!J:J, ledger!B:B, _xlpm.party, ledger!E:E, "<>*RD*", ledger!D:D, "Black-chamki", ledger!C:C, "<>November Closing CF") ))} -> 0 | L50: {=_xlfn.BYROW(B50, _xlfn.LAMBDA(_xlpm.party, SUMIFS(ledger!J:J, ledger!B:B, _xlpm.party, ledger!E:E, "<>*RD*", ledger!D:D, "Kataan", ledger!C:C, "<>November Closing CF") ))} -> 0 | M50: {=_xlfn.BYROW(B50, _xlfn.LAMBDA(_xlpm.party, SUMIFS(ledger!J:J, ledger!B:B, _xlpm.party, ledger!E:E, "<>*RD*", ledger!D:D, "Munaar", ledger!C:C, "<>November Closing CF") ))} -> 0 | N50: =SUM(G50:M50) -> 443100.77 | O50: =(SUMIF(Table14[Party],B50,Table14[Credit])) -> 408088 | P50: =N50-O50 -> 35012.768 | Q50: 10 | R50: 12
B51: Arshad | C51: 72326 | D51: 66135.699 | E51: 53308.339 | F51: 12827.359 | G51: {=(_xlfn.BYROW(B51,_xlfn.LAMBDA(_xlpm.party, (SUMIFS(ledger!J:J,ledger!B:B,_xlpm.party,ledger!E:E,"<>*RD*",ledger!D:D,"Chamki",ledger!C:C,"<>November Closing CF")+ SUMIFS(ledger!J:J,ledger!B:B,_xlpm.party,ledger!E:E,"<>*RD*",ledger!D:D,"Crinkle",ledger!C:C,"<>November Closing CF") ))))} -> 533083.39 | H51: {=_xlfn.BYROW(B51, _xlfn.LAMBDA(_xlpm.party, SUMIFS(ledger!J:J, ledger!B:B, _xlpm.party, ledger!E:E, "<>*RD*", ledger!D:D, "Silky", ledger!C:C, "<>November Closing CF") ))} -> 166755.67 | I51: {=_xlfn.BYROW(B51, _xlfn.LAMBDA(_xlpm.party, SUMIFS(ledger!J:J, ledger!B:B, _xlpm.party, ledger!E:E, "<>*RD*", ledger!D:D, "Slub", ledger!C:C, "<>November Closing CF") ))} -> 0 | J51: {=_xlfn.BYROW(B51, _xlfn.LAMBDA(_xlpm.party, SUMIFS(ledger!J:J, ledger!B:B, _xlpm.party, ledger!E:E, "<>*RD*", ledger!D:D, "Satin", ledger!C:C, "<>November Closing CF") ))} -> 0 | K51: {=_xlfn.BYROW(B51, _xlfn.LAMBDA(_xlpm.party, SUMIFS(ledger!J:J, ledger!B:B, _xlpm.party, ledger!E:E, "<>*RD*", ledger!D:D, "Black-chamki", ledger!C:C, "<>November Closing CF") ))} -> 0 | L51: {=_xlfn.BYROW(B51, _xlfn.LAMBDA(_xlpm.party, SUMIFS(ledger!J:J, ledger!B:B, _xlpm.party, ledger!E:E, "<>*RD*", ledger!D:D, "Kataan", ledger!C:C, "<>November Closing CF") ))} -> 0 | M51: {=_xlfn.BYROW(B51, _xlfn.LAMBDA(_xlpm.party, SUMIFS(ledger!J:J, ledger!B:B, _xlpm.party, ledger!E:E, "<>*RD*", ledger!D:D, "Munaar", ledger!C:C, "<>November Closing CF") ))} -> 0 | N51: =SUM(G51:M51) -> 699839.06 | O51: =(SUMIF(Table14[Party],B51,Table14[Credit])) -> 702366 | P51: =N51-O51 -> -2526.9364 | Q51: 10 | R51: 12
B52: Shehzad Kamoki | C52: 8850 | D52: 8092.5384 | E52: 8092.5384 | F52: 0 | G52: {=(_xlfn.BYROW(B52,_xlfn.LAMBDA(_xlpm.party, (SUMIFS(ledger!J:J,ledger!B:B,_xlpm.party,ledger!E:E,"<>*RD*",ledger!D:D,"Chamki",ledger!C:C,"<>November Closing CF")+ SUMIFS(ledger!J:J,ledger!B:B,_xlpm.party,ledger!E:E,"<>*RD*",ledger!D:D,"Crinkle",ledger!C:C,"<>November Closing CF") ))))} -> 84971.653 | H52: {=_xlfn.BYROW(B52, _xlfn.LAMBDA(_xlpm.party, SUMIFS(ledger!J:J, ledger!B:B, _xlpm.party, ledger!E:E, "<>*RD*", ledger!D:D, "Silky", ledger!C:C, "<>November Closing CF") ))} -> 0 | I52: {=_xlfn.BYROW(B52, _xlfn.LAMBDA(_xlpm.party, SUMIFS(ledger!J:J, ledger!B:B, _xlpm.party, ledger!E:E, "<>*RD*", ledger!D:D, "Slub", ledger!C:C, "<>November Closing CF") ))} -> 0 | J52: {=_xlfn.BYROW(B52, _xlfn.LAMBDA(_xlpm.party, SUMIFS(ledger!J:J, ledger!B:B, _xlpm.party, ledger!E:E, "<>*RD*", ledger!D:D, "Satin", ledger!C:C, "<>November Closing CF") ))} -> 0 | K52: {=_xlfn.BYROW(B52, _xlfn.LAMBDA(_xlpm.party, SUMIFS(ledger!J:J, ledger!B:B, _xlpm.party, ledger!E:E, "<>*RD*", ledger!D:D, "Black-chamki", ledger!C:C, "<>November Closing CF") ))} -> 0 | L52: {=_xlfn.BYROW(B52, _xlfn.LAMBDA(_xlpm.party, SUMIFS(ledger!J:J, ledger!B:B, _xlpm.party, ledger!E:E, "<>*RD*", ledger!D:D, "Kataan", ledger!C:C, "<>November Closing CF") ))} -> 0 | M52: {=_xlfn.BYROW(B52, _xlfn.LAMBDA(_xlpm.party, SUMIFS(ledger!J:J, ledger!B:B, _xlpm.party, ledger!E:E, "<>*RD*", ledger!D:D, "Munaar", ledger!C:C, "<>November Closing CF") ))} -> 0 | N52: =SUM(G52:M52) -> 84971.653 | O52: =(SUMIF(Table14[Party],B52,Table14[Credit])) -> 84970 | P52: =N52-O52 -> 1.6532553 | Q52: 10.5 | R52: 13
B53: Sufi Nawaz Sahab | C53: 26242 | D53: 23995.977 | E53: 0 | F53: 0 | G53: {=(_xlfn.BYROW(B53,_xlfn.LAMBDA(_xlpm.party, (SUMIFS(ledger!J:J,ledger!B:B,_xlpm.party,ledger!E:E,"<>*RD*",ledger!D:D,"Chamki",ledger!C:C,"<>November Closing CF")+ SUMIFS(ledger!J:J,ledger!B:B,_xlpm.party,ledger!E:E,"<>*RD*",ledger!D:D,"Crinkle",ledger!C:C,"<>November Closing CF") ))))} -> 0 | H53: {=_xlfn.BYROW(B53, _xlfn.LAMBDA(_xlpm.party, SUMIFS(ledger!J:J, ledger!B:B, _xlpm.party, ledger!E:E, "<>*RD*", ledger!D:D, "Silky", ledger!C:C, "<>November Closing CF") ))} -> 0 | I53: {=_xlfn.BYROW(B53, _xlfn.LAMBDA(_xlpm.party, SUMIFS(ledger!J:J, ledger!B:B, _xlpm.party, ledger!E:E, "<>*RD*", ledger!D:D, "Slub", ledger!C:C, "<>November Closing CF") ))} -> 0 | J53: {=_xlfn.BYROW(B53, _xlfn.LAMBDA(_xlpm.party, SUMIFS(ledger!J:J, ledger!B:B, _xlpm.party, ledger!E:E, "<>*RD*", ledger!D:D, "Satin", ledger!C:C, "<>November Closing CF") ))} -> 239959.77 | K53: {=_xlfn.BYROW(B53, _xlfn.LAMBDA(_xlpm.party, SUMIFS(ledger!J:J, ledger!B:B, _xlpm.party, ledger!E:E, "<>*RD*", ledger!D:D, "Black-chamki", ledger!C:C, "<>November Closing CF") ))} -> 0 | L53: {=_xlfn.BYROW(B53, _xlfn.LAMBDA(_xlpm.party, SUMIFS(ledger!J:J, ledger!B:B, _xlpm.party, ledger!E:E, "<>*RD*", ledger!D:D, "Kataan", ledger!C:C, "<>November Closing CF") ))} -> 0 | M53: {=_xlfn.BYROW(B53, _xlfn.LAMBDA(_xlpm.party, SUMIFS(ledger!J:J, ledger!B:B, _xlpm.party, ledger!E:E, "<>*RD*", ledger!D:D, "Munaar", ledger!C:C, "<>November Closing CF") ))} -> 0 | N53: =SUM(G53:M53) -> 239959.77 | O53: =(SUMIF(Table14[Party],B53,Table14[Credit])) -> 849664 | P53: =N53-O53 -> -609704.23 | Q53: 10 | R53: 12
B54: Sajad Khan | C54: 0 | D54: 0 | E54: 0 | F54: 0 | G54: {=(_xlfn.BYROW(B54,_xlfn.LAMBDA(_xlpm.party, (SUMIFS(ledger!J:J,ledger!B:B,_xlpm.party,ledger!E:E,"<>*RD*",ledger!D:D,"Chamki",ledger!C:C,"<>November Closing CF")+ SUMIFS(ledger!J:J,ledger!B:B,_xlpm.party,ledger!E:E,"<>*RD*",ledger!D:D,"Crinkle",ledger!C:C,"<>November Closing CF") ))))} -> 0 | H54: {=_xlfn.BYROW(B54, _xlfn.LAMBDA(_xlpm.party, SUMIFS(ledger!J:J, ledger!B:B, _xlpm.party, ledger!E:E, "<>*RD*", ledger!D:D, "Silky", ledger!C:C, "<>November Closing CF") ))} -> 0 | I54: {=_xlfn.BYROW(B54, _xlfn.LAMBDA(_xlpm.party, SUMIFS(ledger!J:J, ledger!B:B, _xlpm.party, ledger!E:E, "<>*RD*", ledger!D:D, "Slub", ledger!C:C, "<>November Closing CF") ))} -> 0 | J54: {=_xlfn.BYROW(B54, _xlfn.LAMBDA(_xlpm.party, SUMIFS(ledger!J:J, ledger!B:B, _xlpm.party, ledger!E:E, "<>*RD*", ledger!D:D, "Satin", ledger!C:C, "<>November Closing CF") ))} -> 0 | K54: {=_xlfn.BYROW(B54, _xlfn.LAMBDA(_xlpm.party, SUMIFS(ledger!J:J, ledger!B:B, _xlpm.party, ledger!E:E, "<>*RD*", ledger!D:D, "Black-chamki", ledger!C:C, "<>November Closing CF") ))} -> 0 | L54: {=_xlfn.BYROW(B54, _xlfn.LAMBDA(_xlpm.party, SUMIFS(ledger!J:J, ledger!B:B, _xlpm.party, ledger!E:E, "<>*RD*", ledger!D:D, "Kataan", ledger!C:C, "<>November Closing CF") ))} -> 0 | M54: {=_xlfn.BYROW(B54, _xlfn.LAMBDA(_xlpm.party, SUMIFS(ledger!J:J, ledger!B:B, _xlpm.party, ledger!E:E, "<>*RD*", ledger!D:D, "Munaar", ledger!C:C, "<>November Closing CF") ))} -> 0 | N54: =SUM(G54:M54) -> 0 | O54: =(SUMIF(Table14[Party],B54,Table14[Credit])) -> 600000 | P54: =N54-O54 -> -600000 | Q54: 10 | R54: 12
B55: Raaz Fabrics | C55: 25427 | D55: 23250.732 | E55: 23250.732 | F55: 0 | G55: {=(_xlfn.BYROW(B55,_xlfn.LAMBDA(_xlpm.party, (SUMIFS(ledger!J:J,ledger!B:B,_xlpm.party,ledger!E:E,"<>*RD*",ledger!D:D,"Chamki",ledger!C:C,"<>November Closing CF")+ SUMIFS(ledger!J:J,ledger!B:B,_xlpm.party,ledger!E:E,"<>*RD*",ledger!D:D,"Crinkle",ledger!C:C,"<>November Closing CF") ))))} -> 232507.32 | H55: {=_xlfn.BYROW(B55, _xlfn.LAMBDA(_xlpm.party, SUMIFS(ledger!J:J, ledger!B:B, _xlpm.party, ledger!E:E, "<>*RD*", ledger!D:D, "Silky", ledger!C:C, "<>November Closing CF") ))} -> 0 | I55: {=_xlfn.BYROW(B55, _xlfn.LAMBDA(_xlpm.party, SUMIFS(ledger!J:J, ledger!B:B, _xlpm.party, ledger!E:E, "<>*RD*", ledger!D:D, "Slub", ledger!C:C, "<>November Closing CF") ))} -> 0 | J55: {=_xlfn.BYROW(B55, _xlfn.LAMBDA(_xlpm.party, SUMIFS(ledger!J:J, ledger!B:B, _xlpm.party, ledger!E:E, "<>*RD*", ledger!D:D, "Satin", ledger!C:C, "<>November Closing CF") ))} -> 0 | K55: {=_xlfn.BYROW(B55, _xlfn.LAMBDA(_xlpm.party, SUMIFS(ledger!J:J, ledger!B:B, _xlpm.party, ledger!E:E, "<>*RD*", ledger!D:D, "Black-chamki", ledger!C:C, "<>November Closing CF") ))} -> 0 | L55: {=_xlfn.BYROW(B55, _xlfn.LAMBDA(_xlpm.party, SUMIFS(ledger!J:J, ledger!B:B, _xlpm.party, ledger!E:E, "<>*RD*", ledger!D:D, "Kataan", ledger!C:C, "<>November Closing CF") ))} -> 0 | M55: {=_xlfn.BYROW(B55, _xlfn.LAMBDA(_xlpm.party, SUMIFS(ledger!J:J, ledger!B:B, _xlpm.party, ledger!E:E, "<>*RD*", ledger!D:D, "Munaar", ledger!C:C, "<>November Closing CF") ))} -> 0 | N55: =SUM(G55:M55) -> 232507.32 | O55: =(SUMIF(Table14[Party],B55,Table14[Credit])) -> 200000 | P55: =N55-O55 -> 32507.315 | Q55: 10 | R55: 12
B56: Azam | C56: 103717 | D56: 94839.978 | E56: 94839.978 | F56: 0 | G56: {=(_xlfn.BYROW(B56,_xlfn.LAMBDA(_xlpm.party, (SUMIFS(ledger!J:J,ledger!B:B,_xlpm.party,ledger!E:E,"<>*RD*",ledger!D:D,"Chamki",ledger!C:C,"<>November Closing CF")+ SUMIFS(ledger!J:J,ledger!B:B,_xlpm.party,ledger!E:E,"<>*RD*",ledger!D:D,"Crinkle",ledger!C:C,"<>November Closing CF") ))))} -> 948399.78 | H56: {=_xlfn.BYROW(B56, _xlfn.LAMBDA(_xlpm.party, SUMIFS(ledger!J:J, ledger!B:B, _xlpm.party, ledger!E:E, "<>*RD*", ledger!D:D, "Silky", ledger!C:C, "<>November Closing CF") ))} -> 0 | I56: {=_xlfn.BYROW(B56, _xlfn.LAMBDA(_xlpm.party, SUMIFS(ledger!J:J, ledger!B:B, _xlpm.party, ledger!E:E, "<>*RD*", ledger!D:D, "Slub", ledger!C:C, "<>November Closing CF") ))} -> 0 | J56: {=_xlfn.BYROW(B56, _xlfn.LAMBDA(_xlpm.party, SUMIFS(ledger!J:J, ledger!B:B, _xlpm.party, ledger!E:E, "<>*RD*", ledger!D:D, "Satin", ledger!C:C, "<>November Closing CF") ))} -> 0 | K56: {=_xlfn.BYROW(B56, _xlfn.LAMBDA(_xlpm.party, SUMIFS(ledger!J:J, ledger!B:B, _xlpm.party, ledger!E:E, "<>*RD*", ledger!D:D, "Black-chamki", ledger!C:C, "<>November Closing CF") ))} -> 0 | L56: {=_xlfn.BYROW(B56, _xlfn.LAMBDA(_xlpm.party, SUMIFS(ledger!J:J, ledger!B:B, _xlpm.party, ledger!E:E, "<>*RD*", ledger!D:D, "Kataan", ledger!C:C, "<>November Closing CF") ))} -> 0 | M56: {=_xlfn.BYROW(B56, _xlfn.LAMBDA(_xlpm.party, SUMIFS(ledger!J:J, ledger!B:B, _xlpm.party, ledger!E:E, "<>*RD*", ledger!D:D, "Munaar", ledger!C:C, "<>November Closing CF") ))} -> 0 | N56: =SUM(G56:M56) -> 948399.78 | O56: =(SUMIF(Table14[Party],B56,Table14[Credit])) -> 1007920 | P56: =N56-O56 -> -59520.219 | Q56: 10 | R56: 12
B57: Ubaidullah | C57: 0 | D57: 0 | E57: 0 | F57: 0 | G57: {=(_xlfn.BYROW(B57,_xlfn.LAMBDA(_xlpm.party, (SUMIFS(ledger!J:J,ledger!B:B,_xlpm.party,ledger!E:E,"<>*RD*",ledger!D:D,"Chamki",ledger!C:C,"<>November Closing CF")+ SUMIFS(ledger!J:J,ledger!B:B,_xlpm.party,ledger!E:E,"<>*RD*",ledger!D:D,"Crinkle",ledger!C:C,"<>November Closing CF") ))))} -> 0 | H57: {=_xlfn.BYROW(B57, _xlfn.LAMBDA(_xlpm.party, SUMIFS(ledger!J:J, ledger!B:B, _xlpm.party, ledger!E:E, "<>*RD*", ledger!D:D, "Silky", ledger!C:C, "<>November Closing CF") ))} -> 0 | I57: {=_xlfn.BYROW(B57, _xlfn.LAMBDA(_xlpm.party, SUMIFS(ledger!J:J, ledger!B:B, _xlpm.party, ledger!E:E, "<>*RD*", ledger!D:D, "Slub", ledger!C:C, "<>November Closing CF") ))} -> 0 | J57: {=_xlfn.BYROW(B57, _xlfn.LAMBDA(_xlpm.party, SUMIFS(ledger!J:J, ledger!B:B, _xlpm.party, ledger!E:E, "<>*RD*", ledger!D:D, "Satin", ledger!C:C, "<>November Closing CF") ))} -> 0 | K57: {=_xlfn.BYROW(B57, _xlfn.LAMBDA(_xlpm.party, SUMIFS(ledger!J:J, ledger!B:B, _xlpm.party, ledger!E:E, "<>*RD*", ledger!D:D, "Black-chamki", ledger!C:C, "<>November Closing CF") ))} -> 0 | L57: {=_xlfn.BYROW(B57, _xlfn.LAMBDA(_xlpm.party, SUMIFS(ledger!J:J, ledger!B:B, _xlpm.party, ledger!E:E, "<>*RD*", ledger!D:D, "Kataan", ledger!C:C, "<>November Closing CF") ))} -> 0 | M57: {=_xlfn.BYROW(B57, _xlfn.LAMBDA(_xlpm.party, SUMIFS(ledger!J:J, ledger!B:B, _xlpm.party, ledger!E:E, "<>*RD*", ledger!D:D, "Munaar", ledger!C:C, "<>November Closing CF") ))} -> 0 | N57: =SUM(G57:M57) -> 0 | O57: =SUMIF(Table14[Party], B57, Table14[Credit]) -> 0 | P57: =N57-O57 -> 0 | Q57: 10 | R57: 12 | U57: Row Labels | V57: Sum of Tiyaar | W57: Sum of Total
B58: Ashraf Zia | C58: 0 | D58: 0 | E58: 0 | F58: 0 | G58: {=(_xlfn.BYROW(B58,_xlfn.LAMBDA(_xlpm.party, (SUMIFS(ledger!J:J,ledger!B:B,_xlpm.party,ledger!E:E,"<>*RD*",ledger!D:D,"Chamki",ledger!C:C,"<>November Closing CF")+ SUMIFS(ledger!J:J,ledger!B:B,_xlpm.party,ledger!E:E,"<>*RD*",ledger!D:D,"Crinkle",ledger!C:C,"<>November Closing CF") ))))} -> 0 | H58: {=_xlfn.BYROW(B58, _xlfn.LAMBDA(_xlpm.party, SUMIFS(ledger!J:J, ledger!B:B, _xlpm.party, ledger!E:E, "<>*RD*", ledger!D:D, "Silky", ledger!C:C, "<>November Closing CF") ))} -> 0 | I58: {=_xlfn.BYROW(B58, _xlfn.LAMBDA(_xlpm.party, SUMIFS(ledger!J:J, ledger!B:B, _xlpm.party, ledger!E:E, "<>*RD*", ledger!D:D, "Slub", ledger!C:C, "<>November Closing CF") ))} -> 0 | J58: {=_xlfn.BYROW(B58, _xlfn.LAMBDA(_xlpm.party, SUMIFS(ledger!J:J, ledger!B:B, _xlpm.party, ledger!E:E, "<>*RD*", ledger!D:D, "Satin", ledger!C:C, "<>November Closing CF") ))} -> 0 | K58: {=_xlfn.BYROW(B58, _xlfn.LAMBDA(_xlpm.party, SUMIFS(ledger!J:J, ledger!B:B, _xlpm.party, ledger!E:E, "<>*RD*", ledger!D:D, "Black-chamki", ledger!C:C, "<>November Closing CF") ))} -> 0 | L58: {=_xlfn.BYROW(B58, _xlfn.LAMBDA(_xlpm.party, SUMIFS(ledger!J:J, ledger!B:B, _xlpm.party, ledger!E:E, "<>*RD*", ledger!D:D, "Kataan", ledger!C:C, "<>November Closing CF") ))} -> 0 | M58: {=_xlfn.BYROW(B58, _xlfn.LAMBDA(_xlpm.party, SUMIFS(ledger!J:J, ledger!B:B, _xlpm.party, ledger!E:E, "<>*RD*", ledger!D:D, "Munaar", ledger!C:C, "<>November Closing CF") ))} -> 0 | N58: =SUM(G58:M58) -> 0 | O58: =SUMIF(Table14[Party], B58, Table14[Credit]) -> 0 | P58: =N58-O58 -> 0 | Q58: 12 | R58: 12 | U58: BSC | V58: 200789.03 | W58: 1579608.6
B59: Hafiz Qureshi | C59: 84435 | D59: 77208.303 | E59: 77208.303 | F59: 0 | G59: {=(_xlfn.BYROW(B59,_xlfn.LAMBDA(_xlpm.party, (SUMIFS(ledger!J:J,ledger!B:B,_xlpm.party,ledger!E:E,"<>*RD*",ledger!D:D,"Chamki",ledger!C:C,"<>November Closing CF")+ SUMIFS(ledger!J:J,ledger!B:B,_xlpm.party,ledger!E:E,"<>*RD*",ledger!D:D,"Crinkle",ledger!C:C,"<>November Closing CF") ))))} -> 772083.03 | H59: {=_xlfn.BYROW(B59, _xlfn.LAMBDA(_xlpm.party, SUMIFS(ledger!J:J, ledger!B:B, _xlpm.party, ledger!E:E, "<>*RD*", ledger!D:D, "Silky", ledger!C:C, "<>November Closing CF") ))} -> 0 | I59: {=_xlfn.BYROW(B59, _xlfn.LAMBDA(_xlpm.party, SUMIFS(ledger!J:J, ledger!B:B, _xlpm.party, ledger!E:E, "<>*RD*", ledger!D:D, "Slub", ledger!C:C, "<>November Closing CF") ))} -> 0 | J59: {=_xlfn.BYROW(B59, _xlfn.LAMBDA(_xlpm.party, SUMIFS(ledger!J:J, ledger!B:B, _xlpm.party, ledger!E:E, "<>*RD*", ledger!D:D, "Satin", ledger!C:C, "<>November Closing CF") ))} -> 0 | K59: {=_xlfn.BYROW(B59, _xlfn.LAMBDA(_xlpm.party, SUMIFS(ledger!J:J, ledger!B:B, _xlpm.party, ledger!E:E, "<>*RD*", ledger!D:D, "Black-chamki", ledger!C:C, "<>November Closing CF") ))} -> 0 | L59: {=_xlfn.BYROW(B59, _xlfn.LAMBDA(_xlpm.party, SUMIFS(ledger!J:J, ledger!B:B, _xlpm.party, ledger!E:E, "<>*RD*", ledger!D:D, "Kataan", ledger!C:C, "<>November Closing CF") ))} -> 0 | M59: {=_xlfn.BYROW(B59, _xlfn.LAMBDA(_xlpm.party, SUMIFS(ledger!J:J, ledger!B:B, _xlpm.party, ledger!E:E, "<>*RD*", ledger!D:D, "Munaar", ledger!C:C, "<>November Closing CF") ))} -> 0 | N59: =SUM(G59:M59) -> 772083.03 | O59: =SUMIF(Table14[Party], B59, Table14[Credit]) -> 455400 | P59: =N59-O59 -> 316683.03 | Q59: 10 | R59: 12 | U59: Ejaz Sahab | V59: 34084.674 | W59: 409016.09
B60: Badshah Fabrics | C60: 118398 | D60: 108264.45 | E60: 108264.45 | F60: 0 | G60: {=(_xlfn.BYROW(B60,_xlfn.LAMBDA(_xlpm.party, (SUMIFS(ledger!J:J,ledger!B:B,_xlpm.party,ledger!E:E,"<>*RD*",ledger!D:D,"Chamki",ledger!C:C,"<>November Closing CF")+ SUMIFS(ledger!J:J,ledger!B:B,_xlpm.party,ledger!E:E,"<>*RD*",ledger!D:D,"Crinkle",ledger!C:C,"<>November Closing CF") ))))} -> 1082644.5 | H60: {=_xlfn.BYROW(B60, _xlfn.LAMBDA(_xlpm.party, SUMIFS(ledger!J:J, ledger!B:B, _xlpm.party, ledger!E:E, "<>*RD*", ledger!D:D, "Silky", ledger!C:C, "<>November Closing CF") ))} -> 0 | I60: {=_xlfn.BYROW(B60, _xlfn.LAMBDA(_xlpm.party, SUMIFS(ledger!J:J, ledger!B:B, _xlpm.party, ledger!E:E, "<>*RD*", ledger!D:D, "Slub", ledger!C:C, "<>November Closing CF") ))} -> 0 | J60: {=_xlfn.BYROW(B60, _xlfn.LAMBDA(_xlpm.party, SUMIFS(ledger!J:J, ledger!B:B, _xlpm.party, ledger!E:E, "<>*RD*", ledger!D:D, "Satin", ledger!C:C, "<>November Closing CF") ))} -> 0 | K60: {=_xlfn.BYROW(B60, _xlfn.LAMBDA(_xlpm.party, SUMIFS(ledger!J:J, ledger!B:B, _xlpm.party, ledger!E:E, "<>*RD*", ledger!D:D, "Black-chamki", ledger!C:C, "<>November Closing CF") ))} -> 0 | L60: {=_xlfn.BYROW(B60, _xlfn.LAMBDA(_xlpm.party, SUMIFS(ledger!J:J, ledger!B:B, _xlpm.party, ledger!E:E, "<>*RD*", ledger!D:D, "Kataan", ledger!C:C, "<>November Closing CF") ))} -> 0 | M60: {=_xlfn.BYROW(B60, _xlfn.LAMBDA(_xlpm.party, SUMIFS(ledger!J:J, ledger!B:B, _xlpm.party, ledger!E:E, "<>*RD*", ledger!D:D, "Munaar", ledger!C:C, "<>November Closing CF") ))} -> 0 | N60: =SUM(G60:M60) -> 1082644.5 | O60: =SUMIF(Table14[Party], B60, Table14[Credit]) -> 1090000 | P60: =N60-O60 -> -7355.523 | Q60: 10 | R60: 12 | U60: Arshad | V60: 66135.699 | W60: 687011.7
B61: Reject | C61: 0 | D61: 0 | E61: 0 | F61: 0 | G61: {=(_xlfn.BYROW(B61,_xlfn.LAMBDA(_xlpm.party, (SUMIFS(ledger!J:J,ledger!B:B,_xlpm.party,ledger!E:E,"<>*RD*",ledger!D:D,"Chamki",ledger!C:C,"<>November Closing CF")+ SUMIFS(ledger!J:J,ledger!B:B,_xlpm.party,ledger!E:E,"<>*RD*",ledger!D:D,"Crinkle",ledger!C:C,"<>November Closing CF") ))))} -> 0 | H61: {=_xlfn.BYROW(B61, _xlfn.LAMBDA(_xlpm.party, SUMIFS(ledger!J:J, ledger!B:B, _xlpm.party, ledger!E:E, "<>*RD*", ledger!D:D, "Silky", ledger!C:C, "<>November Closing CF") ))} -> 0 | I61: {=_xlfn.BYROW(B61, _xlfn.LAMBDA(_xlpm.party, SUMIFS(ledger!J:J, ledger!B:B, _xlpm.party, ledger!E:E, "<>*RD*", ledger!D:D, "Slub", ledger!C:C, "<>November Closing CF") ))} -> 0 | J61: {=_xlfn.BYROW(B61, _xlfn.LAMBDA(_xlpm.party, SUMIFS(ledger!J:J, ledger!B:B, _xlpm.party, ledger!E:E, "<>*RD*", ledger!D:D, "Satin", ledger!C:C, "<>November Closing CF") ))} -> 0 | K61: {=_xlfn.BYROW(B61, _xlfn.LAMBDA(_xlpm.party, SUMIFS(ledger!J:J, ledger!B:B, _xlpm.party, ledger!E:E, "<>*RD*", ledger!D:D, "Black-chamki", ledger!C:C, "<>November Closing CF") ))} -> 0 | L61: {=_xlfn.BYROW(B61, _xlfn.LAMBDA(_xlpm.party, SUMIFS(ledger!J:J, ledger!B:B, _xlpm.party, ledger!E:E, "<>*RD*", ledger!D:D, "Kataan", ledger!C:C, "<>November Closing CF") ))} -> 0 | M61: {=_xlfn.BYROW(B61, _xlfn.LAMBDA(_xlpm.party, SUMIFS(ledger!J:J, ledger!B:B, _xlpm.party, ledger!E:E, "<>*RD*", ledger!D:D, "Munaar", ledger!C:C, "<>November Closing CF") ))} -> 0 | N61: =SUM(G61:M61) -> 0 | O61: =SUMIF(Table14[Party], B61, Table14[Credit]) -> 0 | P61: =N61-O61 -> 0 | Q61: 10 | R61: 12 | U61: Shehzad Kamoki | V61: 8092.5384 | W61: 84971.653
B62: Amjad 7up | C62: 0 | D62: 0 | E62: 0 | F62: 0 | G62: {=(_xlfn.BYROW(B62,_xlfn.LAMBDA(_xlpm.party, (SUMIFS(ledger!J:J,ledger!B:B,_xlpm.party,ledger!E:E,"<>*RD*",ledger!D:D,"Chamki",ledger!C:C,"<>November Closing CF")+ SUMIFS(ledger!J:J,ledger!B:B,_xlpm.party,ledger!E:E,"<>*RD*",ledger!D:D,"Crinkle",ledger!C:C,"<>November Closing CF") ))))} -> 0 | H62: {=_xlfn.BYROW(B62, _xlfn.LAMBDA(_xlpm.party, SUMIFS(ledger!J:J, ledger!B:B, _xlpm.party, ledger!E:E, "<>*RD*", ledger!D:D, "Silky", ledger!C:C, "<>November Closing CF") ))} -> 0 | I62: {=_xlfn.BYROW(B62, _xlfn.LAMBDA(_xlpm.party, SUMIFS(ledger!J:J, ledger!B:B, _xlpm.party, ledger!E:E, "<>*RD*", ledger!D:D, "Slub", ledger!C:C, "<>November Closing CF") ))} -> 0 | J62: {=_xlfn.BYROW(B62, _xlfn.LAMBDA(_xlpm.party, SUMIFS(ledger!J:J, ledger!B:B, _xlpm.party, ledger!E:E, "<>*RD*", ledger!D:D, "Satin", ledger!C:C, "<>November Closing CF") ))} -> 0 | K62: {=_xlfn.BYROW(B62, _xlfn.LAMBDA(_xlpm.party, SUMIFS(ledger!J:J, ledger!B:B, _xlpm.party, ledger!E:E, "<>*RD*", ledger!D:D, "Black-chamki", ledger!C:C, "<>November Closing CF") ))} -> 0 | L62: {=_xlfn.BYROW(B62, _xlfn.LAMBDA(_xlpm.party, SUMIFS(ledger!J:J, ledger!B:B, _xlpm.party, ledger!E:E, "<>*RD*", ledger!D:D, "Kataan", ledger!C:C, "<>November Closing CF") ))} -> 0 | M62: {=_xlfn.BYROW(B62, _xlfn.LAMBDA(_xlpm.party, SUMIFS(ledger!J:J, ledger!B:B, _xlpm.party, ledger!E:E, "<>*RD*", ledger!D:D, "Munaar", ledger!C:C, "<>November Closing CF") ))} -> 0 | N62: =SUM(G62:M62) -> 0 | O62: =SUMIF(Table14[Party], B62, Table14[Credit]) -> 0 | P62: =N62-O62 -> 0 | Q62: 10 | R62: 12 | U62: Sufi Nawaz Sahab | V62: 23995.977 | W62: 0
B63: Hazrat Khan | C63: 0 | D63: 0 | E63: 0 | F63: 0 | G63: {=(_xlfn.BYROW(B63,_xlfn.LAMBDA(_xlpm.party, (SUMIFS(ledger!J:J,ledger!B:B,_xlpm.party,ledger!E:E,"<>*RD*",ledger!D:D,"Chamki",ledger!C:C,"<>November Closing CF")+ SUMIFS(ledger!J:J,ledger!B:B,_xlpm.party,ledger!E:E,"<>*RD*",ledger!D:D,"Crinkle",ledger!C:C,"<>November Closing CF") ))))} -> 0 | H63: {=_xlfn.BYROW(B63, _xlfn.LAMBDA(_xlpm.party, SUMIFS(ledger!J:J, ledger!B:B, _xlpm.party, ledger!E:E, "<>*RD*", ledger!D:D, "Silky", ledger!C:C, "<>November Closing CF") ))} -> 0 | I63: {=_xlfn.BYROW(B63, _xlfn.LAMBDA(_xlpm.party, SUMIFS(ledger!J:J, ledger!B:B, _xlpm.party, ledger!E:E, "<>*RD*", ledger!D:D, "Slub", ledger!C:C, "<>November Closing CF") ))} -> 0 | J63: {=_xlfn.BYROW(B63, _xlfn.LAMBDA(_xlpm.party, SUMIFS(ledger!J:J, ledger!B:B, _xlpm.party, ledger!E:E, "<>*RD*", ledger!D:D, "Satin", ledger!C:C, "<>November Closing CF") ))} -> 0 | K63: {=_xlfn.BYROW(B63, _xlfn.LAMBDA(_xlpm.party, SUMIFS(ledger!J:J, ledger!B:B, _xlpm.party, ledger!E:E, "<>*RD*", ledger!D:D, "Black-chamki", ledger!C:C, "<>November Closing CF") ))} -> 0 | L63: {=_xlfn.BYROW(B63, _xlfn.LAMBDA(_xlpm.party, SUMIFS(ledger!J:J, ledger!B:B, _xlpm.party, ledger!E:E, "<>*RD*", ledger!D:D, "Kataan", ledger!C:C, "<>November Closing CF") ))} -> 0 | M63: {=_xlfn.BYROW(B63, _xlfn.LAMBDA(_xlpm.party, SUMIFS(ledger!J:J, ledger!B:B, _xlpm.party, ledger!E:E, "<>*RD*", ledger!D:D, "Munaar", ledger!C:C, "<>November Closing CF") ))} -> 0 | N63: =SUM(G63:M63) -> 0 | O63: =SUMIF(Table14[Party], B63, Table14[Credit]) -> 0 | P63: =N63-O63 -> 0 | Q63: 10 | R63: 12 | U63: Sajad Khan | V63: 0 | W63: 0
B64: Haseeb Shamsi | C64: 0 | D64: 0 | E64: 0 | F64: 0 | G64: {=(_xlfn.BYROW(B64,_xlfn.LAMBDA(_xlpm.party, (SUMIFS(ledger!J:J,ledger!B:B,_xlpm.party,ledger!E:E,"<>*RD*",ledger!D:D,"Chamki",ledger!C:C,"<>November Closing CF")+ SUMIFS(ledger!J:J,ledger!B:B,_xlpm.party,ledger!E:E,"<>*RD*",ledger!D:D,"Crinkle",ledger!C:C,"<>November Closing CF") ))))} -> 0 | H64: {=_xlfn.BYROW(B64, _xlfn.LAMBDA(_xlpm.party, SUMIFS(ledger!J:J, ledger!B:B, _xlpm.party, ledger!E:E, "<>*RD*", ledger!D:D, "Silky", ledger!C:C, "<>November Closing CF") ))} -> 0 | I64: {=_xlfn.BYROW(B64, _xlfn.LAMBDA(_xlpm.party, SUMIFS(ledger!J:J, ledger!B:B, _xlpm.party, ledger!E:E, "<>*RD*", ledger!D:D, "Slub", ledger!C:C, "<>November Closing CF") ))} -> 0 | J64: {=_xlfn.BYROW(B64, _xlfn.LAMBDA(_xlpm.party, SUMIFS(ledger!J:J, ledger!B:B, _xlpm.party, ledger!E:E, "<>*RD*", ledger!D:D, "Satin", ledger!C:C, "<>November Closing CF") ))} -> 0 | K64: {=_xlfn.BYROW(B64, _xlfn.LAMBDA(_xlpm.party, SUMIFS(ledger!J:J, ledger!B:B, _xlpm.party, ledger!E:E, "<>*RD*", ledger!D:D, "Black-chamki", ledger!C:C, "<>November Closing CF") ))} -> 0 | L64: {=_xlfn.BYROW(B64, _xlfn.LAMBDA(_xlpm.party, SUMIFS(ledger!J:J, ledger!B:B, _xlpm.party, ledger!E:E, "<>*RD*", ledger!D:D, "Kataan", ledger!C:C, "<>November Closing CF") ))} -> 0 | M64: {=_xlfn.BYROW(B64, _xlfn.LAMBDA(_xlpm.party, SUMIFS(ledger!J:J, ledger!B:B, _xlpm.party, ledger!E:E, "<>*RD*", ledger!D:D, "Munaar", ledger!C:C, "<>November Closing CF") ))} -> 0 | N64: =SUM(G64:M64) -> 0 | O64: =SUMIF(Table14[Party], B81, Table14[Credit]) -> 0 | P64: =N64-O64 -> 0 | Q64: 10 | R64: 12 | U64: Raaz Fabrics | V64: 23250.732 | W64: 232507.32
B65: Faizan | C65: 0 | D65: 0 | E65: 0 | F65: 0 | G65: {=(_xlfn.BYROW(B65,_xlfn.LAMBDA(_xlpm.party, (SUMIFS(ledger!J:J,ledger!B:B,_xlpm.party,ledger!E:E,"<>*RD*",ledger!D:D,"Chamki",ledger!C:C,"<>November Closing CF")+ SUMIFS(ledger!J:J,ledger!B:B,_xlpm.party,ledger!E:E,"<>*RD*",ledger!D:D,"Crinkle",ledger!C:C,"<>November Closing CF") ))))} -> 0 | H65: {=_xlfn.BYROW(B65, _xlfn.LAMBDA(_xlpm.party, SUMIFS(ledger!J:J, ledger!B:B, _xlpm.party, ledger!E:E, "<>*RD*", ledger!D:D, "Silky", ledger!C:C, "<>November Closing CF") ))} -> 0 | I65: {=_xlfn.BYROW(B65, _xlfn.LAMBDA(_xlpm.party, SUMIFS(ledger!J:J, ledger!B:B, _xlpm.party, ledger!E:E, "<>*RD*", ledger!D:D, "Slub", ledger!C:C, "<>November Closing CF") ))} -> 0 | J65: {=_xlfn.BYROW(B65, _xlfn.LAMBDA(_xlpm.party, SUMIFS(ledger!J:J, ledger!B:B, _xlpm.party, ledger!E:E, "<>*RD*", ledger!D:D, "Satin", ledger!C:C, "<>November Closing CF") ))} -> 0 | K65: {=_xlfn.BYROW(B65, _xlfn.LAMBDA(_xlpm.party, SUMIFS(ledger!J:J, ledger!B:B, _xlpm.party, ledger!E:E, "<>*RD*", ledger!D:D, "Black-chamki", ledger!C:C, "<>November Closing CF") ))} -> 0 | L65: {=_xlfn.BYROW(B65, _xlfn.LAMBDA(_xlpm.party, SUMIFS(ledger!J:J, ledger!B:B, _xlpm.party, ledger!E:E, "<>*RD*", ledger!D:D, "Kataan", ledger!C:C, "<>November Closing CF") ))} -> 0 | M65: {=_xlfn.BYROW(B65, _xlfn.LAMBDA(_xlpm.party, SUMIFS(ledger!J:J, ledger!B:B, _xlpm.party, ledger!E:E, "<>*RD*", ledger!D:D, "Munaar", ledger!C:C, "<>November Closing CF") ))} -> 0 | N65: =SUM(G65:M65) -> 0 | O65: =SUMIF(Table14[Party], B65, Table14[Credit]) -> 0 | P65: =N65-O65 -> 0 | Q65: 10 | R65: 13 | U65: Azam | V65: 94839.978 | W65: 948399.78
B66: Shafique Ansari | C66: 0 | D66: 0 | E66: 0 | F66: 0 | G66: {=(_xlfn.BYROW(B66,_xlfn.LAMBDA(_xlpm.party, (SUMIFS(ledger!J:J,ledger!B:B,_xlpm.party,ledger!E:E,"<>*RD*",ledger!D:D,"Chamki",ledger!C:C,"<>November Closing CF")+ SUMIFS(ledger!J:J,ledger!B:B,_xlpm.party,ledger!E:E,"<>*RD*",ledger!D:D,"Crinkle",ledger!C:C,"<>November Closing CF") ))))} -> 0 | H66: {=_xlfn.BYROW(B66, _xlfn.LAMBDA(_xlpm.party, SUMIFS(ledger!J:J, ledger!B:B, _xlpm.party, ledger!E:E, "<>*RD*", ledger!D:D, "Silky", ledger!C:C, "<>November Closing CF") ))} -> 0 | I66: {=_xlfn.BYROW(B66, _xlfn.LAMBDA(_xlpm.party, SUMIFS(ledger!J:J, ledger!B:B, _xlpm.party, ledger!E:E, "<>*RD*", ledger!D:D, "Slub", ledger!C:C, "<>November Closing CF") ))} -> 0 | J66: {=_xlfn.BYROW(B66, _xlfn.LAMBDA(_xlpm.party, SUMIFS(ledger!J:J, ledger!B:B, _xlpm.party, ledger!E:E, "<>*RD*", ledger!D:D, "Satin", ledger!C:C, "<>November Closing CF") ))} -> 0 | K66: {=_xlfn.BYROW(B66, _xlfn.LAMBDA(_xlpm.party, SUMIFS(ledger!J:J, ledger!B:B, _xlpm.party, ledger!E:E, "<>*RD*", ledger!D:D, "Black-chamki", ledger!C:C, "<>November Closing CF") ))} -> 0 | L66: {=_xlfn.BYROW(B66, _xlfn.LAMBDA(_xlpm.party, SUMIFS(ledger!J:J, ledger!B:B, _xlpm.party, ledger!E:E, "<>*RD*", ledger!D:D, "Kataan", ledger!C:C, "<>November Closing CF") ))} -> 0 | M66: {=_xlfn.BYROW(B66, _xlfn.LAMBDA(_xlpm.party, SUMIFS(ledger!J:J, ledger!B:B, _xlpm.party, ledger!E:E, "<>*RD*", ledger!D:D, "Munaar", ledger!C:C, "<>November Closing CF") ))} -> 0 | N66: =SUM(G66:M66) -> 0 | O66: =SUMIF(Table14[Party], B66, Table14[Credit]) -> 0 | P66: =N66-O66 -> 0 | Q66: 10 | R66: 12 | U66: Ubaidullah | V66: 0 | W66: 0
B67: Amjad sohail | C67: 0 | D67: 0 | E67: 0 | F67: 0 | G67: {=(_xlfn.BYROW(B67,_xlfn.LAMBDA(_xlpm.party, (SUMIFS(ledger!J:J,ledger!B:B,_xlpm.party,ledger!E:E,"<>*RD*",ledger!D:D,"Chamki",ledger!C:C,"<>November Closing CF")+ SUMIFS(ledger!J:J,ledger!B:B,_xlpm.party,ledger!E:E,"<>*RD*",ledger!D:D,"Crinkle",ledger!C:C,"<>November Closing CF") ))))} -> 0 | H67: {=_xlfn.BYROW(B67, _xlfn.LAMBDA(_xlpm.party, SUMIFS(ledger!J:J, ledger!B:B, _xlpm.party, ledger!E:E, "<>*RD*", ledger!D:D, "Silky", ledger!C:C, "<>November Closing CF") ))} -> 0 | I67: {=_xlfn.BYROW(B67, _xlfn.LAMBDA(_xlpm.party, SUMIFS(ledger!J:J, ledger!B:B, _xlpm.party, ledger!E:E, "<>*RD*", ledger!D:D, "Slub", ledger!C:C, "<>November Closing CF") ))} -> 0 | J67: {=_xlfn.BYROW(B67, _xlfn.LAMBDA(_xlpm.party, SUMIFS(ledger!J:J, ledger!B:B, _xlpm.party, ledger!E:E, "<>*RD*", ledger!D:D, "Satin", ledger!C:C, "<>November Closing CF") ))} -> 0 | K67: {=_xlfn.BYROW(B67, _xlfn.LAMBDA(_xlpm.party, SUMIFS(ledger!J:J, ledger!B:B, _xlpm.party, ledger!E:E, "<>*RD*", ledger!D:D, "Black-chamki", ledger!C:C, "<>November Closing CF") ))} -> 0 | L67: {=_xlfn.BYROW(B67, _xlfn.LAMBDA(_xlpm.party, SUMIFS(ledger!J:J, ledger!B:B, _xlpm.party, ledger!E:E, "<>*RD*", ledger!D:D, "Kataan", ledger!C:C, "<>November Closing CF") ))} -> 0 | M67: {=_xlfn.BYROW(B67, _xlfn.LAMBDA(_xlpm.party, SUMIFS(ledger!J:J, ledger!B:B, _xlpm.party, ledger!E:E, "<>*RD*", ledger!D:D, "Munaar", ledger!C:C, "<>November Closing CF") ))} -> 0 | N67: =SUM(G67:M67) -> 0 | O67: =SUMIF(Table14[Party], B67, Table14[Credit]) -> 409310 | P67: =N67-O67 -> -409310 | Q67: 10 | R67: 12 | U67: Ashraf Zia | V67: 0 | W67: 0
B68: Salman Zaffar | C68: 28452 | D68: 26016.825 | E68: 26016.825 | F68: 0 | G68: {=(_xlfn.BYROW(B68,_xlfn.LAMBDA(_xlpm.party, (SUMIFS(ledger!J:J,ledger!B:B,_xlpm.party,ledger!E:E,"<>*RD*",ledger!D:D,"Chamki",ledger!C:C,"<>November Closing CF")+ SUMIFS(ledger!J:J,ledger!B:B,_xlpm.party,ledger!E:E,"<>*RD*",ledger!D:D,"Crinkle",ledger!C:C,"<>November Closing CF") ))))} -> 260168.25 | H68: {=_xlfn.BYROW(B68, _xlfn.LAMBDA(_xlpm.party, SUMIFS(ledger!J:J, ledger!B:B, _xlpm.party, ledger!E:E, "<>*RD*", ledger!D:D, "Silky", ledger!C:C, "<>November Closing CF") ))} -> 0 | I68: {=_xlfn.BYROW(B68, _xlfn.LAMBDA(_xlpm.party, SUMIFS(ledger!J:J, ledger!B:B, _xlpm.party, ledger!E:E, "<>*RD*", ledger!D:D, "Slub", ledger!C:C, "<>November Closing CF") ))} -> 0 | J68: {=_xlfn.BYROW(B68, _xlfn.LAMBDA(_xlpm.party, SUMIFS(ledger!J:J, ledger!B:B, _xlpm.party, ledger!E:E, "<>*RD*", ledger!D:D, "Satin", ledger!C:C, "<>November Closing CF") ))} -> 0 | K68: {=_xlfn.BYROW(B68, _xlfn.LAMBDA(_xlpm.party, SUMIFS(ledger!J:J, ledger!B:B, _xlpm.party, ledger!E:E, "<>*RD*", ledger!D:D, "Black-chamki", ledger!C:C, "<>November Closing CF") ))} -> 0 | L68: {=_xlfn.BYROW(B68, _xlfn.LAMBDA(_xlpm.party, SUMIFS(ledger!J:J, ledger!B:B, _xlpm.party, ledger!E:E, "<>*RD*", ledger!D:D, "Kataan", ledger!C:C, "<>November Closing CF") ))} -> 0 | M68: {=_xlfn.BYROW(B68, _xlfn.LAMBDA(_xlpm.party, SUMIFS(ledger!J:J, ledger!B:B, _xlpm.party, ledger!E:E, "<>*RD*", ledger!D:D, "Munaar", ledger!C:C, "<>November Closing CF") ))} -> 0 | N68: =SUM(G68:M68) -> 260168.25 | O68: =SUMIF(Table14[Party], B68, Table14[Credit]) -> 973525 | P68: =N68-O68 -> -713356.75 | Q68: 10 | R68: 12 | U68: Hafiz Qureshi | V68: 77208.303 | W68: 772083.03
B69: Shahid Qasayi | C69: 87689 | D69: 80183.797 | E69: 76222.568 | F69: 0 | G69: {=(_xlfn.BYROW(B69,_xlfn.LAMBDA(_xlpm.party, (SUMIFS(ledger!J:J,ledger!B:B,_xlpm.party,ledger!E:E,"<>*RD*",ledger!D:D,"Chamki",ledger!C:C,"<>November Closing CF")+ SUMIFS(ledger!J:J,ledger!B:B,_xlpm.party,ledger!E:E,"<>*RD*",ledger!D:D,"Crinkle",ledger!C:C,"<>November Closing CF") ))))} -> 762225.68 | H69: {=_xlfn.BYROW(B69, _xlfn.LAMBDA(_xlpm.party, SUMIFS(ledger!J:J, ledger!B:B, _xlpm.party, ledger!E:E, "<>*RD*", ledger!D:D, "Silky", ledger!C:C, "<>November Closing CF") ))} -> 0 | I69: {=_xlfn.BYROW(B69, _xlfn.LAMBDA(_xlpm.party, SUMIFS(ledger!J:J, ledger!B:B, _xlpm.party, ledger!E:E, "<>*RD*", ledger!D:D, "Slub", ledger!C:C, "<>November Closing CF") ))} -> 0 | J69: {=_xlfn.BYROW(B69, _xlfn.LAMBDA(_xlpm.party, SUMIFS(ledger!J:J, ledger!B:B, _xlpm.party, ledger!E:E, "<>*RD*", ledger!D:D, "Satin", ledger!C:C, "<>November Closing CF") ))} -> 0 | K69: {=_xlfn.BYROW(B69, _xlfn.LAMBDA(_xlpm.party, SUMIFS(ledger!J:J, ledger!B:B, _xlpm.party, ledger!E:E, "<>*RD*", ledger!D:D, "Black-chamki", ledger!C:C, "<>November Closing CF") ))} -> 47534.748 | L69: {=_xlfn.BYROW(B69, _xlfn.LAMBDA(_xlpm.party, SUMIFS(ledger!J:J, ledger!B:B, _xlpm.party, ledger!E:E, "<>*RD*", ledger!D:D, "Kataan", ledger!C:C, "<>November Closing CF") ))} -> 0 | M69: {=_xlfn.BYROW(B69, _xlfn.LAMBDA(_xlpm.party, SUMIFS(ledger!J:J, ledger!B:B, _xlpm.party, ledger!E:E, "<>*RD*", ledger!D:D, "Munaar", ledger!C:C, "<>November Closing CF") ))} -> 0 | N69: =SUM(G69:M69) -> 809760.42 | O69: =SUMIF(Table14[Party], B69, Table14[Credit]) -> 864770 | P69: =N69-O69 -> -55009.576 | Q69: 10 | R69: 12 | U69: Badshah Fabrics | V69: 108264.45 | W69: 618461.96
B70: Hameed corporation | C70: 0 | D70: 0 | E70: 0 | F70: 0 | G70: {=(_xlfn.BYROW(B70,_xlfn.LAMBDA(_xlpm.party, (SUMIFS(ledger!J:J,ledger!B:B,_xlpm.party,ledger!E:E,"<>*RD*",ledger!D:D,"Chamki",ledger!C:C,"<>November Closing CF")+ SUMIFS(ledger!J:J,ledger!B:B,_xlpm.party,ledger!E:E,"<>*RD*",ledger!D:D,"Crinkle",ledger!C:C,"<>November Closing CF") ))))} -> 0 | H70: {=_xlfn.BYROW(B70, _xlfn.LAMBDA(_xlpm.party, SUMIFS(ledger!J:J, ledger!B:B, _xlpm.party, ledger!E:E, "<>*RD*", ledger!D:D, "Silky", ledger!C:C, "<>November Closing CF") ))} -> 0 | I70: {=_xlfn.BYROW(B70, _xlfn.LAMBDA(_xlpm.party, SUMIFS(ledger!J:J, ledger!B:B, _xlpm.party, ledger!E:E, "<>*RD*", ledger!D:D, "Slub", ledger!C:C, "<>November Closing CF") ))} -> 0 | J70: {=_xlfn.BYROW(B70, _xlfn.LAMBDA(_xlpm.party, SUMIFS(ledger!J:J, ledger!B:B, _xlpm.party, ledger!E:E, "<>*RD*", ledger!D:D, "Satin", ledger!C:C, "<>November Closing CF") ))} -> 0 | K70: {=_xlfn.BYROW(B70, _xlfn.LAMBDA(_xlpm.party, SUMIFS(ledger!J:J, ledger!B:B, _xlpm.party, ledger!E:E, "<>*RD*", ledger!D:D, "Black-chamki", ledger!C:C, "<>November Closing CF") ))} -> 0 | L70: {=_xlfn.BYROW(B70, _xlfn.LAMBDA(_xlpm.party, SUMIFS(ledger!J:J, ledger!B:B, _xlpm.party, ledger!E:E, "<>*RD*", ledger!D:D, "Kataan", ledger!C:C, "<>November Closing CF") ))} -> 0 | M70: {=_xlfn.BYROW(B70, _xlfn.LAMBDA(_xlpm.party, SUMIFS(ledger!J:J, ledger!B:B, _xlpm.party, ledger!E:E, "<>*RD*", ledger!D:D, "Munaar", ledger!C:C, "<>November Closing CF") ))} -> 0 | N70: =SUM(G70:M70) -> 0 | O70: =SUMIF(Table14[Party], B70, Table14[Credit]) -> 0 | P70: =N70-O70 -> 0 | U70: Reject | V70: 0 | W70: 0
B71: ibraheem behraam | C71: 0 | D71: 0 | E71: 0 | F71: 0 | G71: {=(_xlfn.BYROW(B71,_xlfn.LAMBDA(_xlpm.party, (SUMIFS(ledger!J:J,ledger!B:B,_xlpm.party,ledger!E:E,"<>*RD*",ledger!D:D,"Chamki",ledger!C:C,"<>November Closing CF")+ SUMIFS(ledger!J:J,ledger!B:B,_xlpm.party,ledger!E:E,"<>*RD*",ledger!D:D,"Crinkle",ledger!C:C,"<>November Closing CF") ))))} -> 0 | H71: {=_xlfn.BYROW(B71, _xlfn.LAMBDA(_xlpm.party, SUMIFS(ledger!J:J, ledger!B:B, _xlpm.party, ledger!E:E, "<>*RD*", ledger!D:D, "Silky", ledger!C:C, "<>November Closing CF") ))} -> 0 | I71: {=_xlfn.BYROW(B71, _xlfn.LAMBDA(_xlpm.party, SUMIFS(ledger!J:J, ledger!B:B, _xlpm.party, ledger!E:E, "<>*RD*", ledger!D:D, "Slub", ledger!C:C, "<>November Closing CF") ))} -> 0 | J71: {=_xlfn.BYROW(B71, _xlfn.LAMBDA(_xlpm.party, SUMIFS(ledger!J:J, ledger!B:B, _xlpm.party, ledger!E:E, "<>*RD*", ledger!D:D, "Satin", ledger!C:C, "<>November Closing CF") ))} -> 0 | K71: {=_xlfn.BYROW(B71, _xlfn.LAMBDA(_xlpm.party, SUMIFS(ledger!J:J, ledger!B:B, _xlpm.party, ledger!E:E, "<>*RD*", ledger!D:D, "Black-chamki", ledger!C:C, "<>November Closing CF") ))} -> 0 | L71: {=_xlfn.BYROW(B71, _xlfn.LAMBDA(_xlpm.party, SUMIFS(ledger!J:J, ledger!B:B, _xlpm.party, ledger!E:E, "<>*RD*", ledger!D:D, "Kataan", ledger!C:C, "<>November Closing CF") ))} -> 0 | M71: {=_xlfn.BYROW(B71, _xlfn.LAMBDA(_xlpm.party, SUMIFS(ledger!J:J, ledger!B:B, _xlpm.party, ledger!E:E, "<>*RD*", ledger!D:D, "Munaar", ledger!C:C, "<>November Closing CF") ))} -> 0 | N71: =SUM(G71:M71) -> 0 | O71: =SUMIF(Table14[Party], B71, Table14[Credit]) -> 0 | P71: =N71-O71 -> 0 | U71: Amjad 7up | V71: 0 | W71: 0
B72: Zia-ullah karachi | C72: 0 | D72: 0 | E72: 0 | F72: 0 | G72: {=(_xlfn.BYROW(B72,_xlfn.LAMBDA(_xlpm.party, (SUMIFS(ledger!J:J,ledger!B:B,_xlpm.party,ledger!E:E,"<>*RD*",ledger!D:D,"Chamki",ledger!C:C,"<>November Closing CF")+ SUMIFS(ledger!J:J,ledger!B:B,_xlpm.party,ledger!E:E,"<>*RD*",ledger!D:D,"Crinkle",ledger!C:C,"<>November Closing CF") ))))} -> 0 | H72: {=_xlfn.BYROW(B72, _xlfn.LAMBDA(_xlpm.party, SUMIFS(ledger!J:J, ledger!B:B, _xlpm.party, ledger!E:E, "<>*RD*", ledger!D:D, "Silky", ledger!C:C, "<>November Closing CF") ))} -> 0 | I72: {=_xlfn.BYROW(B72, _xlfn.LAMBDA(_xlpm.party, SUMIFS(ledger!J:J, ledger!B:B, _xlpm.party, ledger!E:E, "<>*RD*", ledger!D:D, "Slub", ledger!C:C, "<>November Closing CF") ))} -> 0 | J72: {=_xlfn.BYROW(B72, _xlfn.LAMBDA(_xlpm.party, SUMIFS(ledger!J:J, ledger!B:B, _xlpm.party, ledger!E:E, "<>*RD*", ledger!D:D, "Satin", ledger!C:C, "<>November Closing CF") ))} -> 0 | K72: {=_xlfn.BYROW(B72, _xlfn.LAMBDA(_xlpm.party, SUMIFS(ledger!J:J, ledger!B:B, _xlpm.party, ledger!E:E, "<>*RD*", ledger!D:D, "Black-chamki", ledger!C:C, "<>November Closing CF") ))} -> 0 | L72: {=_xlfn.BYROW(B72, _xlfn.LAMBDA(_xlpm.party, SUMIFS(ledger!J:J, ledger!B:B, _xlpm.party, ledger!E:E, "<>*RD*", ledger!D:D, "Kataan", ledger!C:C, "<>November Closing CF") ))} -> 0 | M72: {=_xlfn.BYROW(B72, _xlfn.LAMBDA(_xlpm.party, SUMIFS(ledger!J:J, ledger!B:B, _xlpm.party, ledger!E:E, "<>*RD*", ledger!D:D, "Munaar", ledger!C:C, "<>November Closing CF") ))} -> 0 | N72: =SUM(G72:M72) -> 0 | O72: =SUMIF(Table14[Party], B72, Table14[Credit]) -> 0 | P72: =N72-O72 -> 0 | U72: Hazrat Khan | V72: 0 | W72: 0
B73: ZA | C73: 0 | D73: 0 | E73: 0 | F73: 0 | G73: {=(_xlfn.BYROW(B73,_xlfn.LAMBDA(_xlpm.party, (SUMIFS(ledger!J:J,ledger!B:B,_xlpm.party,ledger!E:E,"<>*RD*",ledger!D:D,"Chamki",ledger!C:C,"<>November Closing CF")+ SUMIFS(ledger!J:J,ledger!B:B,_xlpm.party,ledger!E:E,"<>*RD*",ledger!D:D,"Crinkle",ledger!C:C,"<>November Closing CF") ))))} -> 0 | H73: {=_xlfn.BYROW(B73, _xlfn.LAMBDA(_xlpm.party, SUMIFS(ledger!J:J, ledger!B:B, _xlpm.party, ledger!E:E, "<>*RD*", ledger!D:D, "Silky", ledger!C:C, "<>November Closing CF") ))} -> 0 | I73: {=_xlfn.BYROW(B73, _xlfn.LAMBDA(_xlpm.party, SUMIFS(ledger!J:J, ledger!B:B, _xlpm.party, ledger!E:E, "<>*RD*", ledger!D:D, "Slub", ledger!C:C, "<>November Closing CF") ))} -> 0 | J73: {=_xlfn.BYROW(B73, _xlfn.LAMBDA(_xlpm.party, SUMIFS(ledger!J:J, ledger!B:B, _xlpm.party, ledger!E:E, "<>*RD*", ledger!D:D, "Satin", ledger!C:C, "<>November Closing CF") ))} -> 0 | K73: {=_xlfn.BYROW(B73, _xlfn.LAMBDA(_xlpm.party, SUMIFS(ledger!J:J, ledger!B:B, _xlpm.party, ledger!E:E, "<>*RD*", ledger!D:D, "Black-chamki", ledger!C:C, "<>November Closing CF") ))} -> 0 | L73: {=_xlfn.BYROW(B73, _xlfn.LAMBDA(_xlpm.party, SUMIFS(ledger!J:J, ledger!B:B, _xlpm.party, ledger!E:E, "<>*RD*", ledger!D:D, "Kataan", ledger!C:C, "<>November Closing CF") ))} -> 0 | M73: {=_xlfn.BYROW(B73, _xlfn.LAMBDA(_xlpm.party, SUMIFS(ledger!J:J, ledger!B:B, _xlpm.party, ledger!E:E, "<>*RD*", ledger!D:D, "Munaar", ledger!C:C, "<>November Closing CF") ))} -> 0 | N73: =SUM(G73:M73) -> 0 | O73: =SUMIF(Table14[Party], B73, Table14[Credit]) -> 0 | P73: =N73-O73 -> 0 | U73: Haseeb Shamsi | V73: 0 | W73: 0
B74: Ahmad Javaid | C74: 8188 | D74: 7487.1982 | E74: 0 | F74: 0 | G74: {=(_xlfn.BYROW(B74,_xlfn.LAMBDA(_xlpm.party, (SUMIFS(ledger!J:J,ledger!B:B,_xlpm.party,ledger!E:E,"<>*RD*",ledger!D:D,"Chamki",ledger!C:C,"<>November Closing CF")+ SUMIFS(ledger!J:J,ledger!B:B,_xlpm.party,ledger!E:E,"<>*RD*",ledger!D:D,"Crinkle",ledger!C:C,"<>November Closing CF") ))))} -> 0 | H74: {=_xlfn.BYROW(B74, _xlfn.LAMBDA(_xlpm.party, SUMIFS(ledger!J:J, ledger!B:B, _xlpm.party, ledger!E:E, "<>*RD*", ledger!D:D, "Silky", ledger!C:C, "<>November Closing CF") ))} -> 0 | I74: {=_xlfn.BYROW(B74, _xlfn.LAMBDA(_xlpm.party, SUMIFS(ledger!J:J, ledger!B:B, _xlpm.party, ledger!E:E, "<>*RD*", ledger!D:D, "Slub", ledger!C:C, "<>November Closing CF") ))} -> 0 | J74: {=_xlfn.BYROW(B74, _xlfn.LAMBDA(_xlpm.party, SUMIFS(ledger!J:J, ledger!B:B, _xlpm.party, ledger!E:E, "<>*RD*", ledger!D:D, "Satin", ledger!C:C, "<>November Closing CF") ))} -> 0 | K74: {=_xlfn.BYROW(B74, _xlfn.LAMBDA(_xlpm.party, SUMIFS(ledger!J:J, ledger!B:B, _xlpm.party, ledger!E:E, "<>*RD*", ledger!D:D, "Black-chamki", ledger!C:C, "<>November Closing CF") ))} -> 0 | L74: {=_xlfn.BYROW(B74, _xlfn.LAMBDA(_xlpm.party, SUMIFS(ledger!J:J, ledger!B:B, _xlpm.party, ledger!E:E, "<>*RD*", ledger!D:D, "Kataan", ledger!C:C, "<>November Closing CF") ))} -> 0 | M74: {=_xlfn.BYROW(B74, _xlfn.LAMBDA(_xlpm.party, SUMIFS(ledger!J:J, ledger!B:B, _xlpm.party, ledger!E:E, "<>*RD*", ledger!D:D, "Munaar", ledger!C:C, "<>November Closing CF") ))} -> 97333.577 | N74: =SUM(G74:M74) -> 97333.577 | O74: =SUMIF(Table14[Party], B74, Table14[Credit]) -> 0 | P74: =N74-O74 -> 97333.577 | U74: Faizan | V74: 0 | W74: 0
G75: {=(_xlfn.BYROW(B75,_xlfn.LAMBDA(_xlpm.party, (SUMIFS(ledger!J:J,ledger!B:B,_xlpm.party,ledger!E:E,"<>*RD*",ledger!D:D,"Chamki",ledger!C:C,"<>November Closing CF")+ SUMIFS(ledger!J:J,ledger!B:B,_xlpm.party,ledger!E:E,"<>*RD*",ledger!D:D,"Crinkle",ledger!C:C,"<>November Closing CF") ))))} -> 0 | H75: {=_xlfn.BYROW(B75, _xlfn.LAMBDA(_xlpm.party, SUMIFS(ledger!J:J, ledger!B:B, _xlpm.party, ledger!E:E, "<>*RD*", ledger!D:D, "Silky", ledger!C:C, "<>November Closing CF") ))} -> 0 | I75: {=_xlfn.BYROW(B75, _xlfn.LAMBDA(_xlpm.party, SUMIFS(ledger!J:J, ledger!B:B, _xlpm.party, ledger!E:E, "<>*RD*", ledger!D:D, "Slub", ledger!C:C, "<>November Closing CF") ))} -> 0 | J75: {=_xlfn.BYROW(B75, _xlfn.LAMBDA(_xlpm.party, SUMIFS(ledger!J:J, ledger!B:B, _xlpm.party, ledger!E:E, "<>*RD*", ledger!D:D, "Satin", ledger!C:C, "<>November Closing CF") ))} -> 0 | K75: {=_xlfn.BYROW(B75, _xlfn.LAMBDA(_xlpm.party, SUMIFS(ledger!J:J, ledger!B:B, _xlpm.party, ledger!E:E, "<>*RD*", ledger!D:D, "Black-chamki", ledger!C:C, "<>November Closing CF") ))} -> 0 | L75: {=_xlfn.BYROW(B75, _xlfn.LAMBDA(_xlpm.party, SUMIFS(ledger!J:J, ledger!B:B, _xlpm.party, ledger!E:E, "<>*RD*", ledger!D:D, "Kataan", ledger!C:C, "<>November Closing CF") ))} -> 0 | M75: {=_xlfn.BYROW(B75, _xlfn.LAMBDA(_xlpm.party, SUMIFS(ledger!J:J, ledger!B:B, _xlpm.party, ledger!E:E, "<>*RD*", ledger!D:D, "Munaar", ledger!C:C, "<>November Closing CF") ))} -> 0 | N75: =SUM(G75:M75) -> 0 | O75: =SUMIF(Table14[Party], B75, Table14[Credit]) -> 0 | P75: =N75-O75 -> 0 | U75: Grand Total | V75: 636661.38 | W75: 5332060.2
G76: {=(_xlfn.BYROW(B76,_xlfn.LAMBDA(_xlpm.party, (SUMIFS(ledger!J:J,ledger!B:B,_xlpm.party,ledger!E:E,"<>*RD*",ledger!D:D,"Chamki",ledger!C:C,"<>November Closing CF")+ SUMIFS(ledger!J:J,ledger!B:B,_xlpm.party,ledger!E:E,"<>*RD*",ledger!D:D,"Crinkle",ledger!C:C,"<>November Closing CF") ))))} -> 0 | H76: {=_xlfn.BYROW(B76, _xlfn.LAMBDA(_xlpm.party, SUMIFS(ledger!J:J, ledger!B:B, _xlpm.party, ledger!E:E, "<>*RD*", ledger!D:D, "Silky", ledger!C:C, "<>November Closing CF") ))} -> 0 | I76: {=_xlfn.BYROW(B76, _xlfn.LAMBDA(_xlpm.party, SUMIFS(ledger!J:J, ledger!B:B, _xlpm.party, ledger!E:E, "<>*RD*", ledger!D:D, "Slub", ledger!C:C, "<>November Closing CF") ))} -> 0 | J76: {=_xlfn.BYROW(B76, _xlfn.LAMBDA(_xlpm.party, SUMIFS(ledger!J:J, ledger!B:B, _xlpm.party, ledger!E:E, "<>*RD*", ledger!D:D, "Satin", ledger!C:C, "<>November Closing CF") ))} -> 0 | K76: {=_xlfn.BYROW(B76, _xlfn.LAMBDA(_xlpm.party, SUMIFS(ledger!J:J, ledger!B:B, _xlpm.party, ledger!E:E, "<>*RD*", ledger!D:D, "Black-chamki", ledger!C:C, "<>November Closing CF") ))} -> 0 | L76: {=_xlfn.BYROW(B76, _xlfn.LAMBDA(_xlpm.party, SUMIFS(ledger!J:J, ledger!B:B, _xlpm.party, ledger!E:E, "<>*RD*", ledger!D:D, "Kataan", ledger!C:C, "<>November Closing CF") ))} -> 0 | M76: {=_xlfn.BYROW(B76, _xlfn.LAMBDA(_xlpm.party, SUMIFS(ledger!J:J, ledger!B:B, _xlpm.party, ledger!E:E, "<>*RD*", ledger!D:D, "Munaar", ledger!C:C, "<>November Closing CF") ))} -> 0 | N76: =SUM(G76:M76) -> 0 | O76: =SUMIF(Table14[Party], B76, Table14[Credit]) -> 0 | P76: =N76-O76 -> 0
G77: {=(_xlfn.BYROW(B77,_xlfn.LAMBDA(_xlpm.party, (SUMIFS(ledger!J:J,ledger!B:B,_xlpm.party,ledger!E:E,"<>*RD*",ledger!D:D,"Chamki",ledger!C:C,"<>November Closing CF")+ SUMIFS(ledger!J:J,ledger!B:B,_xlpm.party,ledger!E:E,"<>*RD*",ledger!D:D,"Crinkle",ledger!C:C,"<>November Closing CF") ))))} -> 0 | H77: {=_xlfn.BYROW(B77, _xlfn.LAMBDA(_xlpm.party, SUMIFS(ledger!J:J, ledger!B:B, _xlpm.party, ledger!E:E, "<>*RD*", ledger!D:D, "Silky", ledger!C:C, "<>November Closing CF") ))} -> 0 | I77: {=_xlfn.BYROW(B77, _xlfn.LAMBDA(_xlpm.party, SUMIFS(ledger!J:J, ledger!B:B, _xlpm.party, ledger!E:E, "<>*RD*", ledger!D:D, "Slub", ledger!C:C, "<>November Closing CF") ))} -> 0 | J77: {=_xlfn.BYROW(B77, _xlfn.LAMBDA(_xlpm.party, SUMIFS(ledger!J:J, ledger!B:B, _xlpm.party, ledger!E:E, "<>*RD*", ledger!D:D, "Satin", ledger!C:C, "<>November Closing CF") ))} -> 0 | K77: {=_xlfn.BYROW(B77, _xlfn.LAMBDA(_xlpm.party, SUMIFS(ledger!J:J, ledger!B:B, _xlpm.party, ledger!E:E, "<>*RD*", ledger!D:D, "Black-chamki", ledger!C:C, "<>November Closing CF") ))} -> 0 | L77: {=_xlfn.BYROW(B77, _xlfn.LAMBDA(_xlpm.party, SUMIFS(ledger!J:J, ledger!B:B, _xlpm.party, ledger!E:E, "<>*RD*", ledger!D:D, "Kataan", ledger!C:C, "<>November Closing CF") ))} -> 0 | M77: {=_xlfn.BYROW(B77, _xlfn.LAMBDA(_xlpm.party, SUMIFS(ledger!J:J, ledger!B:B, _xlpm.party, ledger!E:E, "<>*RD*", ledger!D:D, "Munaar", ledger!C:C, "<>November Closing CF") ))} -> 0 | N77: =SUM(G77:M77) -> 0 | O77: =SUMIF(Table14[Party], B77, Table14[Credit]) -> 0 | P77: =N77-O77 -> 0
G78: {=(_xlfn.BYROW(B78,_xlfn.LAMBDA(_xlpm.party, (SUMIFS(ledger!J:J,ledger!B:B,_xlpm.party,ledger!E:E,"<>*RD*",ledger!D:D,"Chamki",ledger!C:C,"<>November Closing CF")+ SUMIFS(ledger!J:J,ledger!B:B,_xlpm.party,ledger!E:E,"<>*RD*",ledger!D:D,"Crinkle",ledger!C:C,"<>November Closing CF") ))))} -> 0 | H78: {=_xlfn.BYROW(B78, _xlfn.LAMBDA(_xlpm.party, SUMIFS(ledger!J:J, ledger!B:B, _xlpm.party, ledger!E:E, "<>*RD*", ledger!D:D, "Silky", ledger!C:C, "<>November Closing CF") ))} -> 0 | I78: {=_xlfn.BYROW(B78, _xlfn.LAMBDA(_xlpm.party, SUMIFS(ledger!J:J, ledger!B:B, _xlpm.party, ledger!E:E, "<>*RD*", ledger!D:D, "Slub", ledger!C:C, "<>November Closing CF") ))} -> 0 | J78: {=_xlfn.BYROW(B78, _xlfn.LAMBDA(_xlpm.party, SUMIFS(ledger!J:J, ledger!B:B, _xlpm.party, ledger!E:E, "<>*RD*", ledger!D:D, "Satin", ledger!C:C, "<>November Closing CF") ))} -> 0 | K78: {=_xlfn.BYROW(B78, _xlfn.LAMBDA(_xlpm.party, SUMIFS(ledger!J:J, ledger!B:B, _xlpm.party, ledger!E:E, "<>*RD*", ledger!D:D, "Black-chamki", ledger!C:C, "<>November Closing CF") ))} -> 0 | L78: {=_xlfn.BYROW(B78, _xlfn.LAMBDA(_xlpm.party, SUMIFS(ledger!J:J, ledger!B:B, _xlpm.party, ledger!E:E, "<>*RD*", ledger!D:D, "Kataan", ledger!C:C, "<>November Closing CF") ))} -> 0 | M78: {=_xlfn.BYROW(B78, _xlfn.LAMBDA(_xlpm.party, SUMIFS(ledger!J:J, ledger!B:B, _xlpm.party, ledger!E:E, "<>*RD*", ledger!D:D, "Munaar", ledger!C:C, "<>November Closing CF") ))} -> 0 | N78: =SUM(G78:M78) -> 0 | O78: =SUMIF(Table14[Party], B78, Table14[Credit]) -> 0 | P78: =N78-O78 -> 0
G79: {=(_xlfn.BYROW(B79,_xlfn.LAMBDA(_xlpm.party, (SUMIFS(ledger!J:J,ledger!B:B,_xlpm.party,ledger!E:E,"<>*RD*",ledger!D:D,"Chamki",ledger!C:C,"<>November Closing CF")+ SUMIFS(ledger!J:J,ledger!B:B,_xlpm.party,ledger!E:E,"<>*RD*",ledger!D:D,"Crinkle",ledger!C:C,"<>November Closing CF") ))))} -> 0 | H79: {=_xlfn.BYROW(B79, _xlfn.LAMBDA(_xlpm.party, SUMIFS(ledger!J:J, ledger!B:B, _xlpm.party, ledger!E:E, "<>*RD*", ledger!D:D, "Silky", ledger!C:C, "<>November Closing CF") ))} -> 0 | I79: {=_xlfn.BYROW(B79, _xlfn.LAMBDA(_xlpm.party, SUMIFS(ledger!J:J, ledger!B:B, _xlpm.party, ledger!E:E, "<>*RD*", ledger!D:D, "Slub", ledger!C:C, "<>November Closing CF") ))} -> 0 | J79: {=_xlfn.BYROW(B79, _xlfn.LAMBDA(_xlpm.party, SUMIFS(ledger!J:J, ledger!B:B, _xlpm.party, ledger!E:E, "<>*RD*", ledger!D:D, "Satin", ledger!C:C, "<>November Closing CF") ))} -> 0 | K79: {=_xlfn.BYROW(B79, _xlfn.LAMBDA(_xlpm.party, SUMIFS(ledger!J:J, ledger!B:B, _xlpm.party, ledger!E:E, "<>*RD*", ledger!D:D, "Black-chamki", ledger!C:C, "<>November Closing CF") ))} -> 0 | L79: {=_xlfn.BYROW(B79, _xlfn.LAMBDA(_xlpm.party, SUMIFS(ledger!J:J, ledger!B:B, _xlpm.party, ledger!E:E, "<>*RD*", ledger!D:D, "Kataan", ledger!C:C, "<>November Closing CF") ))} -> 0 | M79: {=_xlfn.BYROW(B79, _xlfn.LAMBDA(_xlpm.party, SUMIFS(ledger!J:J, ledger!B:B, _xlpm.party, ledger!E:E, "<>*RD*", ledger!D:D, "Munaar", ledger!C:C, "<>November Closing CF") ))} -> 0 | N79: =SUM(G79:M79) -> 0
B81: Billing (Previous)
B83: Parties: | C83: Gaz | D83: Total Metres | E83: Total Chamki | F83: Total Super Silky | G83: Billing (Chamki/Crinkle) | H83: Billing (Super Chamki) | I83: billing (Slub) | J83: Billing (Satin) | K83: Billing (Black-Chamki) | L83: Billing (kataan | M83: Billing (Munaar) | N83: Adjusted Bill | O83: Amount Paid | P83: Balance | Q83: Rate (Chamki) | R83: Rate (Super Silky)
B84: {=_xlfn.UNIQUE(Table1[Party Name])} -> BSC | C84: =_xlfn.XLOOKUP($B49,[1]Billing!$Q$5:$Q$40,[1]Billing!$R$5:$R$40) -> 2534939 | D84: =_xlfn.XLOOKUP($B49,[1]Billing!$Q$5:$Q$40,[1]Billing!$S$5:$S$40) -> 2317976.4 | E84: =_xlfn.XLOOKUP($B49,[1]Billing!$Q$5:$Q$40,[1]Billing!$T$5:$T$40) -> 2035507.5 | F84: =_xlfn.XLOOKUP($B49,[1]Billing!$Q$5:$Q$40,[1]Billing!$U$5:$U$40) -> 282468.91 | G84: =_xlfn.XLOOKUP($B49,[1]Billing!$Q$5:$Q$40,[1]Billing!$V$5:$V$40) -> 20355075 | H84: =_xlfn.XLOOKUP($B49,[1]Billing!$Q$5:$Q$40,[1]Billing!$W$5:$W$40) -> 3583739.9 | I84: =_xlfn.XLOOKUP($B49,[1]Billing!$Q$5:$Q$40,[1]Billing!$X$5:$X$40) -> 0 | J84: =_xlfn.XLOOKUP($B49,[1]Billing!$Q$5:$Q$40,[1]Billing!$Y$5:$Y$40) -> 0 | K84: =_xlfn.XLOOKUP($B49,[1]Billing!$Q$5:$Q$40,[1]Billing!$Z$5:$Z$40) -> 0 | L84: =_xlfn.XLOOKUP($B49,[1]Billing!$Q$5:$Q$40,[1]Billing!$AA$5:$AA$40) -> 0 | M84: =_xlfn.XLOOKUP($B49,[1]Billing!$Q$5:$Q$40,[1]Billing!$AB$5:$AB$40) -> 0 | N84: =G84+H84+I84+J84+K84+L84+M84 -> 23938815 | O84: =_xlfn.XLOOKUP($B49,[1]Billing!$Q$5:$Q$40,[1]Billing!$AD$5:$AD$40) -> 19750734 | P84: =N84-O84 -> 4188080.9 | Q84: 10 | R84: 13
B85: Ejaz Sahab | C85: =_xlfn.XLOOKUP($B50,[1]Billing!$Q$5:$Q$40,[1]Billing!$R$5:$R$40) -> 393394 | D85: =_xlfn.XLOOKUP($B50,[1]Billing!$Q$5:$Q$40,[1]Billing!$S$5:$S$40) -> 359723.85 | E85: =_xlfn.XLOOKUP($B50,[1]Billing!$Q$5:$Q$40,[1]Billing!$T$5:$T$40) -> 148145.57 | F85: =_xlfn.XLOOKUP($B50,[1]Billing!$Q$5:$Q$40,[1]Billing!$U$5:$U$40) -> 211578.27 | G85: =_xlfn.XLOOKUP($B50,[1]Billing!$Q$5:$Q$40,[1]Billing!$V$5:$V$40) -> 1481455.7 | H85: =_xlfn.XLOOKUP($B50,[1]Billing!$Q$5:$Q$40,[1]Billing!$W$5:$W$40) -> 2691373.4 | I85: =_xlfn.XLOOKUP($B50,[1]Billing!$Q$5:$Q$40,[1]Billing!$X$5:$X$40) -> 0 | J85: =_xlfn.XLOOKUP($B50,[1]Billing!$Q$5:$Q$40,[1]Billing!$Y$5:$Y$40) -> 0 | K85: =_xlfn.XLOOKUP($B50,[1]Billing!$Q$5:$Q$40,[1]Billing!$Z$5:$Z$40) -> 0 | L85: =_xlfn.XLOOKUP($B50,[1]Billing!$Q$5:$Q$40,[1]Billing!$AA$5:$AA$40) -> 0 | M85: =_xlfn.XLOOKUP($B50,[1]Billing!$Q$5:$Q$40,[1]Billing!$AB$5:$AB$40) -> 0 | N85: =G85+H85+I85+J85+K85+L85+M85 -> 4172829.2 | O85: =_xlfn.XLOOKUP($B50,[1]Billing!$Q$5:$Q$40,[1]Billing!$AD$5:$AD$40) -> 3963904 | P85: =N85-O85 -> 208925.19 | Q85: 10 | R85: 13
B86: Arshad | C86: =_xlfn.XLOOKUP($B51,[1]Billing!$Q$5:$Q$40,[1]Billing!$R$5:$R$40) -> 657148 | D86: =_xlfn.XLOOKUP($B51,[1]Billing!$Q$5:$Q$40,[1]Billing!$S$5:$S$40) -> 600903.44 | E86: =_xlfn.XLOOKUP($B51,[1]Billing!$Q$5:$Q$40,[1]Billing!$T$5:$T$40) -> 522790.78 | F86: =_xlfn.XLOOKUP($B51,[1]Billing!$Q$5:$Q$40,[1]Billing!$U$5:$U$40) -> 78112.655 | G86: =_xlfn.XLOOKUP($B51,[1]Billing!$Q$5:$Q$40,[1]Billing!$V$5:$V$40) -> 5227907.8 | H86: =_xlfn.XLOOKUP($B51,[1]Billing!$Q$5:$Q$40,[1]Billing!$W$5:$W$40) -> 1000670.3 | I86: =_xlfn.XLOOKUP($B51,[1]Billing!$Q$5:$Q$40,[1]Billing!$X$5:$X$40) -> 0 | J86: =_xlfn.XLOOKUP($B51,[1]Billing!$Q$5:$Q$40,[1]Billing!$Y$5:$Y$40) -> 0 | K86: =_xlfn.XLOOKUP($B51,[1]Billing!$Q$5:$Q$40,[1]Billing!$Z$5:$Z$40) -> 0 | L86: =_xlfn.XLOOKUP($B51,[1]Billing!$Q$5:$Q$40,[1]Billing!$AA$5:$AA$40) -> 0 | M86: =_xlfn.XLOOKUP($B51,[1]Billing!$Q$5:$Q$40,[1]Billing!$AB$5:$AB$40) -> 0 | N86: =G86+H86+I86+J86+K86+L86+M86 -> 6228578.1 | O86: =_xlfn.XLOOKUP($B51,[1]Billing!$Q$5:$Q$40,[1]Billing!$AD$5:$AD$40) -> 6002935 | P86: =N86-O86 -> 225643.09 | Q86: 10 | R86: 13
B87: Shehzad Kamoki | C87: =_xlfn.XLOOKUP($B52,[1]Billing!$Q$5:$Q$40,[1]Billing!$R$5:$R$40) -> 134607 | D87: =_xlfn.XLOOKUP($B52,[1]Billing!$Q$5:$Q$40,[1]Billing!$S$5:$S$40) -> 123086.14 | E87: =_xlfn.XLOOKUP($B52,[1]Billing!$Q$5:$Q$40,[1]Billing!$T$5:$T$40) -> 123086.14 | F87: =_xlfn.XLOOKUP($B52,[1]Billing!$Q$5:$Q$40,[1]Billing!$U$5:$U$40) -> 0 | G87: =_xlfn.XLOOKUP($B52,[1]Billing!$Q$5:$Q$40,[1]Billing!$V$5:$V$40) -> 1269270.3 | H87: =_xlfn.XLOOKUP($B52,[1]Billing!$Q$5:$Q$40,[1]Billing!$W$5:$W$40) -> 0 | I87: =_xlfn.XLOOKUP($B52,[1]Billing!$Q$5:$Q$40,[1]Billing!$X$5:$X$40) -> 0 | J87: =_xlfn.XLOOKUP($B52,[1]Billing!$Q$5:$Q$40,[1]Billing!$Y$5:$Y$40) -> 0 | K87: =_xlfn.XLOOKUP($B52,[1]Billing!$Q$5:$Q$40,[1]Billing!$Z$5:$Z$40) -> 0 | L87: =_xlfn.XLOOKUP($B52,[1]Billing!$Q$5:$Q$40,[1]Billing!$AA$5:$AA$40) -> 0 | M87: =_xlfn.XLOOKUP($B52,[1]Billing!$Q$5:$Q$40,[1]Billing!$AB$5:$AB$40) -> 0 | N87: =G87+H87+I87+J87+K87+L87+M87 -> 1269270.3 | O87: =_xlfn.XLOOKUP($B52,[1]Billing!$Q$5:$Q$40,[1]Billing!$AD$5:$AD$40) -> 1268740 | P87: =N87-O87 -> 530.34404 | Q87: 10.5 | R87: 13
B88: Sufi Nawaz Sahab | C88: =_xlfn.XLOOKUP($B53,[1]Billing!$Q$5:$Q$40,[1]Billing!$R$5:$R$40) -> 1186725 | D88: =_xlfn.XLOOKUP($B53,[1]Billing!$Q$5:$Q$40,[1]Billing!$S$5:$S$40) -> 1085154.5 | E88: =_xlfn.XLOOKUP($B53,[1]Billing!$Q$5:$Q$40,[1]Billing!$T$5:$T$40) -> 599330.65 | F88: =_xlfn.XLOOKUP($B53,[1]Billing!$Q$5:$Q$40,[1]Billing!$U$5:$U$40) -> 485823.88 | G88: =_xlfn.XLOOKUP($B53,[1]Billing!$Q$5:$Q$40,[1]Billing!$V$5:$V$40) -> 5408917.9 | H88: =_xlfn.XLOOKUP($B53,[1]Billing!$Q$5:$Q$40,[1]Billing!$W$5:$W$40) -> 5829886.6 | I88: =_xlfn.XLOOKUP($B53,[1]Billing!$Q$5:$Q$40,[1]Billing!$X$5:$X$40) -> 0 | J88: =_xlfn.XLOOKUP($B53,[1]Billing!$Q$5:$Q$40,[1]Billing!$Y$5:$Y$40) -> 0 | K88: =_xlfn.XLOOKUP($B53,[1]Billing!$Q$5:$Q$40,[1]Billing!$Z$5:$Z$40) -> 0 | L88: =_xlfn.XLOOKUP($B53,[1]Billing!$Q$5:$Q$40,[1]Billing!$AA$5:$AA$40) -> 0 | M88: =_xlfn.XLOOKUP($B53,[1]Billing!$Q$5:$Q$40,[1]Billing!$AB$5:$AB$40) -> 0 | N88: =G88+H88+I88+J88+K88+L88+M88 -> 11238804 | O88: =_xlfn.XLOOKUP($B53,[1]Billing!$Q$5:$Q$40,[1]Billing!$AD$5:$AD$40) -> 10629100 | P88: =N88-O88 -> 609704.47 | Q88: 10 | R88: 13
B89: Sajad Khan | C89: =_xlfn.XLOOKUP($B54,[1]Billing!$Q$5:$Q$40,[1]Billing!$R$5:$R$40) -> 865551 | D89: =_xlfn.XLOOKUP($B54,[1]Billing!$Q$5:$Q$40,[1]Billing!$S$5:$S$40) -> 791469.46 | E89: =_xlfn.XLOOKUP($B54,[1]Billing!$Q$5:$Q$40,[1]Billing!$T$5:$T$40) -> 785980.25 | F89: =_xlfn.XLOOKUP($B54,[1]Billing!$Q$5:$Q$40,[1]Billing!$U$5:$U$40) -> 0 | G89: =_xlfn.XLOOKUP($B54,[1]Billing!$Q$5:$Q$40,[1]Billing!$V$5:$V$40) -> 7859802.5 | H89: =_xlfn.XLOOKUP($B54,[1]Billing!$Q$5:$Q$40,[1]Billing!$W$5:$W$40) -> 0 | I89: =_xlfn.XLOOKUP($B54,[1]Billing!$Q$5:$Q$40,[1]Billing!$X$5:$X$40) -> 71359.729 | J89: =_xlfn.XLOOKUP($B54,[1]Billing!$Q$5:$Q$40,[1]Billing!$Y$5:$Y$40) -> 0 | K89: =_xlfn.XLOOKUP($B54,[1]Billing!$Q$5:$Q$40,[1]Billing!$Z$5:$Z$40) -> 0 | L89: =_xlfn.XLOOKUP($B54,[1]Billing!$Q$5:$Q$40,[1]Billing!$AA$5:$AA$40) -> 0 | M89: =_xlfn.XLOOKUP($B54,[1]Billing!$Q$5:$Q$40,[1]Billing!$AB$5:$AB$40) -> 0 | N89: =G89+H89+I89+J89+K89+L89+M89 -> 7931162.2 | O89: =_xlfn.XLOOKUP($B54,[1]Billing!$Q$5:$Q$40,[1]Billing!$AD$5:$AD$40) -> 7397871 | P89: =N89-O89 -> 533291.22 | Q89: 10 | R89: 13
B90: Raaz Fabrics | C90: =_xlfn.XLOOKUP($B55,[1]Billing!$Q$5:$Q$40,[1]Billing!$R$5:$R$40) -> 152434 | D90: =_xlfn.XLOOKUP($B55,[1]Billing!$Q$5:$Q$40,[1]Billing!$S$5:$S$40) -> 139387.34 | E90: =_xlfn.XLOOKUP($B55,[1]Billing!$Q$5:$Q$40,[1]Billing!$T$5:$T$40) -> 139387.34 | F90: =_xlfn.XLOOKUP($B55,[1]Billing!$Q$5:$Q$40,[1]Billing!$U$5:$U$40) -> 0 | G90: =_xlfn.XLOOKUP($B55,[1]Billing!$Q$5:$Q$40,[1]Billing!$V$5:$V$40) -> 1393873.4 | H90: =_xlfn.XLOOKUP($B55,[1]Billing!$Q$5:$Q$40,[1]Billing!$W$5:$W$40) -> 0 | I90: =_xlfn.XLOOKUP($B55,[1]Billing!$Q$5:$Q$40,[1]Billing!$X$5:$X$40) -> 0 | J90: =_xlfn.XLOOKUP($B55,[1]Billing!$Q$5:$Q$40,[1]Billing!$Y$5:$Y$40) -> 0 | K90: =_xlfn.XLOOKUP($B55,[1]Billing!$Q$5:$Q$40,[1]Billing!$Z$5:$Z$40) -> 0 | L90: =_xlfn.XLOOKUP($B55,[1]Billing!$Q$5:$Q$40,[1]Billing!$AA$5:$AA$40) -> 0 | M90: =_xlfn.XLOOKUP($B55,[1]Billing!$Q$5:$Q$40,[1]Billing!$AB$5:$AB$40) -> 0 | N90: =G90+H90+I90+J90+K90+L90+M90 -> 1393873.4 | O90: =_xlfn.XLOOKUP($B55,[1]Billing!$Q$5:$Q$40,[1]Billing!$AD$5:$AD$40) -> 1100000 | P90: =N90-O90 -> 293873.45 | Q90: 10 | R90: 13
B91: Azam | C91: =_xlfn.XLOOKUP($B56,[1]Billing!$Q$5:$Q$40,[1]Billing!$R$5:$R$40) -> 361607 | D91: =_xlfn.XLOOKUP($B56,[1]Billing!$Q$5:$Q$40,[1]Billing!$S$5:$S$40) -> 330657.46 | E91: =_xlfn.XLOOKUP($B56,[1]Billing!$Q$5:$Q$40,[1]Billing!$T$5:$T$40) -> 305469.09 | F91: =_xlfn.XLOOKUP($B56,[1]Billing!$Q$5:$Q$40,[1]Billing!$U$5:$U$40) -> 25188.369 | G91: =_xlfn.XLOOKUP($B56,[1]Billing!$Q$5:$Q$40,[1]Billing!$V$5:$V$40) -> 3054690.9 | H91: =_xlfn.XLOOKUP($B56,[1]Billing!$Q$5:$Q$40,[1]Billing!$W$5:$W$40) -> 327448.79 | I91: =_xlfn.XLOOKUP($B56,[1]Billing!$Q$5:$Q$40,[1]Billing!$X$5:$X$40) -> 0 | J91: =_xlfn.XLOOKUP($B56,[1]Billing!$Q$5:$Q$40,[1]Billing!$Y$5:$Y$40) -> 0 | K91: =_xlfn.XLOOKUP($B56,[1]Billing!$Q$5:$Q$40,[1]Billing!$Z$5:$Z$40) -> 0 | L91: =_xlfn.XLOOKUP($B56,[1]Billing!$Q$5:$Q$40,[1]Billing!$AA$5:$AA$40) -> 0 | M91: =_xlfn.XLOOKUP($B56,[1]Billing!$Q$5:$Q$40,[1]Billing!$AB$5:$AB$40) -> 0 | N91: =G91+H91+I91+J91+K91+L91+M91 -> 3382139.7 | O91: =_xlfn.XLOOKUP($B56,[1]Billing!$Q$5:$Q$40,[1]Billing!$AD$5:$AD$40) -> 3322620 | P91: =N91-O91 -> 59519.722 | Q91: 10 | R91: 13
B92: Ubaidullah | C92: =_xlfn.XLOOKUP($B57,[1]Billing!$Q$5:$Q$40,[1]Billing!$R$5:$R$40) -> 66850 | D92: =_xlfn.XLOOKUP($B57,[1]Billing!$Q$5:$Q$40,[1]Billing!$S$5:$S$40) -> 61128.383 | E92: =_xlfn.XLOOKUP($B57,[1]Billing!$Q$5:$Q$40,[1]Billing!$T$5:$T$40) -> 46132.955 | F92: =_xlfn.XLOOKUP($B57,[1]Billing!$Q$5:$Q$40,[1]Billing!$U$5:$U$40) -> 14995.428 | G92: =_xlfn.XLOOKUP($B57,[1]Billing!$Q$5:$Q$40,[1]Billing!$V$5:$V$40) -> 461329.55 | H92: =_xlfn.XLOOKUP($B57,[1]Billing!$Q$5:$Q$40,[1]Billing!$W$5:$W$40) -> 179945.14 | I92: =_xlfn.XLOOKUP($B57,[1]Billing!$Q$5:$Q$40,[1]Billing!$X$5:$X$40) -> 0 | J92: =_xlfn.XLOOKUP($B57,[1]Billing!$Q$5:$Q$40,[1]Billing!$Y$5:$Y$40) -> 0 | K92: =_xlfn.XLOOKUP($B57,[1]Billing!$Q$5:$Q$40,[1]Billing!$Z$5:$Z$40) -> 0 | L92: =_xlfn.XLOOKUP($B57,[1]Billing!$Q$5:$Q$40,[1]Billing!$AA$5:$AA$40) -> 0 | M92: =_xlfn.XLOOKUP($B57,[1]Billing!$Q$5:$Q$40,[1]Billing!$AB$5:$AB$40) -> 0 | N92: =G92+H92+I92+J92+K92+L92+M92 -> 641274.69 | O92: =_xlfn.XLOOKUP($B57,[1]Billing!$Q$5:$Q$40,[1]Billing!$AD$5:$AD$40) -> 640190 | P92: =N92-O92 -> 1084.6891 | Q92: 10 | R92: 13
B93: Ashraf Zia | C93: =_xlfn.XLOOKUP($B58,[1]Billing!$Q$5:$Q$40,[1]Billing!$R$5:$R$40) -> 23305 | D93: =_xlfn.XLOOKUP($B58,[1]Billing!$Q$5:$Q$40,[1]Billing!$S$5:$S$40) -> 21310.351 | E93: =_xlfn.XLOOKUP($B58,[1]Billing!$Q$5:$Q$40,[1]Billing!$T$5:$T$40) -> 21310.351 | F93: =_xlfn.XLOOKUP($B58,[1]Billing!$Q$5:$Q$40,[1]Billing!$U$5:$U$40) -> 0 | G93: =_xlfn.XLOOKUP($B58,[1]Billing!$Q$5:$Q$40,[1]Billing!$V$5:$V$40) -> 255724.21 | H93: =_xlfn.XLOOKUP($B58,[1]Billing!$Q$5:$Q$40,[1]Billing!$W$5:$W$40) -> 0 | I93: =_xlfn.XLOOKUP($B58,[1]Billing!$Q$5:$Q$40,[1]Billing!$X$5:$X$40) -> 0 | J93: =_xlfn.XLOOKUP($B58,[1]Billing!$Q$5:$Q$40,[1]Billing!$Y$5:$Y$40) -> 0 | K93: =_xlfn.XLOOKUP($B58,[1]Billing!$Q$5:$Q$40,[1]Billing!$Z$5:$Z$40) -> 0 | L93: =_xlfn.XLOOKUP($B58,[1]Billing!$Q$5:$Q$40,[1]Billing!$AA$5:$AA$40) -> 0 | M93: =_xlfn.XLOOKUP($B58,[1]Billing!$Q$5:$Q$40,[1]Billing!$AB$5:$AB$40) -> 0 | N93: =G93+H93+I93+J93+K93+L93+M93 -> 255724.21 | O93: =_xlfn.XLOOKUP($B58,[1]Billing!$Q$5:$Q$40,[1]Billing!$AD$5:$AD$40) -> 130000 | P93: =N93-O93 -> 125724.21 | Q93: 12 | R93: 13
B94: Hafiz Qureshi | C94: =_xlfn.XLOOKUP($B59,[1]Billing!$Q$5:$Q$40,[1]Billing!$R$5:$R$40) -> 202815 | D94: =_xlfn.XLOOKUP($B59,[1]Billing!$Q$5:$Q$40,[1]Billing!$S$5:$S$40) -> 185456.29 | E94: =_xlfn.XLOOKUP($B59,[1]Billing!$Q$5:$Q$40,[1]Billing!$T$5:$T$40) -> 185456.29 | F94: =_xlfn.XLOOKUP($B59,[1]Billing!$Q$5:$Q$40,[1]Billing!$U$5:$U$40) -> 0 | G94: =_xlfn.XLOOKUP($B59,[1]Billing!$Q$5:$Q$40,[1]Billing!$V$5:$V$40) -> 1854562.9 | H94: =_xlfn.XLOOKUP($B59,[1]Billing!$Q$5:$Q$40,[1]Billing!$W$5:$W$40) -> 0 | I94: =_xlfn.XLOOKUP($B59,[1]Billing!$Q$5:$Q$40,[1]Billing!$X$5:$X$40) -> 0 | J94: =_xlfn.XLOOKUP($B59,[1]Billing!$Q$5:$Q$40,[1]Billing!$Y$5:$Y$40) -> 0 | K94: =_xlfn.XLOOKUP($B59,[1]Billing!$Q$5:$Q$40,[1]Billing!$Z$5:$Z$40) -> 0 | L94: =_xlfn.XLOOKUP($B59,[1]Billing!$Q$5:$Q$40,[1]Billing!$AA$5:$AA$40) -> 0 | M94: =_xlfn.XLOOKUP($B59,[1]Billing!$Q$5:$Q$40,[1]Billing!$AB$5:$AB$40) -> 0 | N94: =G94+H94+I94+J94+K94+L94+M94 -> 1854562.9 | O94: =_xlfn.XLOOKUP($B59,[1]Billing!$Q$5:$Q$40,[1]Billing!$AD$5:$AD$40) -> 1805980 | P94: =N94-O94 -> 48582.911 | Q94: 10 | R94: 13
B95: Badshah Fabrics | C95: =_xlfn.XLOOKUP($B60,[1]Billing!$Q$5:$Q$40,[1]Billing!$R$5:$R$40) -> 517408 | D95: =_xlfn.XLOOKUP($B60,[1]Billing!$Q$5:$Q$40,[1]Billing!$S$5:$S$40) -> 473123.63 | E95: =_xlfn.XLOOKUP($B60,[1]Billing!$Q$5:$Q$40,[1]Billing!$T$5:$T$40) -> 355909.84 | F95: =_xlfn.XLOOKUP($B60,[1]Billing!$Q$5:$Q$40,[1]Billing!$U$5:$U$40) -> 117213.79 | G95: =_xlfn.XLOOKUP($B60,[1]Billing!$Q$5:$Q$40,[1]Billing!$V$5:$V$40) -> 3559098.4 | H95: =_xlfn.XLOOKUP($B60,[1]Billing!$Q$5:$Q$40,[1]Billing!$W$5:$W$40) -> 1460624.5 | I95: =_xlfn.XLOOKUP($B60,[1]Billing!$Q$5:$Q$40,[1]Billing!$X$5:$X$40) -> 0 | J95: =_xlfn.XLOOKUP($B60,[1]Billing!$Q$5:$Q$40,[1]Billing!$Y$5:$Y$40) -> 0 | K95: =_xlfn.XLOOKUP($B60,[1]Billing!$Q$5:$Q$40,[1]Billing!$Z$5:$Z$40) -> 0 | L95: =_xlfn.XLOOKUP($B60,[1]Billing!$Q$5:$Q$40,[1]Billing!$AA$5:$AA$40) -> 0 | M95: =_xlfn.XLOOKUP($B60,[1]Billing!$Q$5:$Q$40,[1]Billing!$AB$5:$AB$40) -> 0 | N95: =G95+H95+I95+J95+K95+L95+M95 -> 5019722.9 | O95: =_xlfn.XLOOKUP($B60,[1]Billing!$Q$5:$Q$40,[1]Billing!$AD$5:$AD$40) -> 4925761 | P95: =N95-O95 -> 93961.933 | Q95: 10 | R95: 13
B96: Reject | C96: =_xlfn.XLOOKUP($B61,[1]Billing!$Q$5:$Q$40,[1]Billing!$R$5:$R$40) -> 0 | D96: =_xlfn.XLOOKUP($B61,[1]Billing!$Q$5:$Q$40,[1]Billing!$S$5:$S$40) -> 0 | E96: =_xlfn.XLOOKUP($B61,[1]Billing!$Q$5:$Q$40,[1]Billing!$T$5:$T$40) -> 0 | F96: =_xlfn.XLOOKUP($B61,[1]Billing!$Q$5:$Q$40,[1]Billing!$U$5:$U$40) -> 0 | G96: =_xlfn.XLOOKUP($B61,[1]Billing!$Q$5:$Q$40,[1]Billing!$V$5:$V$40) -> 0 | H96: =_xlfn.XLOOKUP($B61,[1]Billing!$Q$5:$Q$40,[1]Billing!$W$5:$W$40) -> 0 | I96: =_xlfn.XLOOKUP($B61,[1]Billing!$Q$5:$Q$40,[1]Billing!$X$5:$X$40) -> 0 | J96: =_xlfn.XLOOKUP($B61,[1]Billing!$Q$5:$Q$40,[1]Billing!$Y$5:$Y$40) -> 0 | K96: =_xlfn.XLOOKUP($B61,[1]Billing!$Q$5:$Q$40,[1]Billing!$Z$5:$Z$40) -> 0 | L96: =_xlfn.XLOOKUP($B61,[1]Billing!$Q$5:$Q$40,[1]Billing!$AA$5:$AA$40) -> 0 | M96: =_xlfn.XLOOKUP($B61,[1]Billing!$Q$5:$Q$40,[1]Billing!$AB$5:$AB$40) -> 0 | N96: =G96+H96+I96+J96+K96+L96+M96 -> 0 | O96: =_xlfn.XLOOKUP($B61,[1]Billing!$Q$5:$Q$40,[1]Billing!$AD$5:$AD$40) -> 0 | P96: =N96-O96 -> 0 | Q96: 10 | R96: 13
... B103: Salman Zaffar | C103: =_xlfn.XLOOKUP($B68,[1]Billing!$Q$5:$Q$40,[1]Billing!$R$5:$R$40) -> 64780 | D103: =_xlfn.XLOOKUP($B68,[1]Billing!$Q$5:$Q$40,[1]Billing!$S$5:$S$40) -> 59235.552 | E103: =_xlfn.XLOOKUP($B68,[1]Billing!$Q$5:$Q$40,[1]Billing!$T$5:$T$40) -> 14355.34 | F103: =_xlfn.XLOOKUP($B68,[1]Billing!$Q$5:$Q$40,[1]Billing!$U$5:$U$40) -> 31409.108 | G103: =_xlfn.XLOOKUP($B68,[1]Billing!$Q$5:$Q$40,[1]Billing!$V$5:$V$40) -> 143553.4 | H103: =_xlfn.XLOOKUP($B68,[1]Billing!$Q$5:$Q$40,[1]Billing!$W$5:$W$40) -> 408318.4 | I103: =_xlfn.XLOOKUP($B68,[1]Billing!$Q$5:$Q$40,[1]Billing!$X$5:$X$40) -> 0 | J103: =_xlfn.XLOOKUP($B68,[1]Billing!$Q$5:$Q$40,[1]Billing!$Y$5:$Y$40) -> 0 | K103: =_xlfn.XLOOKUP($B68,[1]Billing!$Q$5:$Q$40,[1]Billing!$Z$5:$Z$40) -> 161653.26 | L103: =_xlfn.XLOOKUP($B68,[1]Billing!$Q$5:$Q$40,[1]Billing!$AA$5:$AA$40) -> 0 | M103: =_xlfn.XLOOKUP($B68,[1]Billing!$Q$5:$Q$40,[1]Billing!$AB$5:$AB$40) -> 0 | N103: =G103+H103+I103+J103+K103+L103+M103 -> 713525.05 | O103: =_xlfn.XLOOKUP($B68,[1]Billing!$Q$5:$Q$40,[1]Billing!$AD$5:$AD$40) -> 0 | P103: =N103-O103 -> 713525.05 | Q103: 10 | R103: 13
B104: Shahid Qasayi | C104: =_xlfn.XLOOKUP($B69,[1]Billing!$Q$5:$Q$40,[1]Billing!$R$5:$R$40) -> 176129 | D104: =_xlfn.XLOOKUP($B69,[1]Billing!$Q$5:$Q$40,[1]Billing!$S$5:$S$40) -> 161054.32 | E104: =_xlfn.XLOOKUP($B69,[1]Billing!$Q$5:$Q$40,[1]Billing!$T$5:$T$40) -> 113495.79 | F104: =_xlfn.XLOOKUP($B69,[1]Billing!$Q$5:$Q$40,[1]Billing!$U$5:$U$40) -> 0 | G104: =_xlfn.XLOOKUP($B69,[1]Billing!$Q$5:$Q$40,[1]Billing!$V$5:$V$40) -> 1134957.9 | H104: =_xlfn.XLOOKUP($B69,[1]Billing!$Q$5:$Q$40,[1]Billing!$W$5:$W$40) -> 0 | I104: =_xlfn.XLOOKUP($B69,[1]Billing!$Q$5:$Q$40,[1]Billing!$X$5:$X$40) -> 0 | J104: =_xlfn.XLOOKUP($B69,[1]Billing!$Q$5:$Q$40,[1]Billing!$Y$5:$Y$40) -> 0 | K104: =_xlfn.XLOOKUP($B69,[1]Billing!$Q$5:$Q$40,[1]Billing!$Z$5:$Z$40) -> 0 | L104: =_xlfn.XLOOKUP($B69,[1]Billing!$Q$5:$Q$40,[1]Billing!$AA$5:$AA$40) -> 523143.75 | M104: =_xlfn.XLOOKUP($B69,[1]Billing!$Q$5:$Q$40,[1]Billing!$AB$5:$AB$40) -> 0 | N104: =G104+H104+I104+J104+K104+L104+M104 -> 1658101.7 | O104: =_xlfn.XLOOKUP($B69,[1]Billing!$Q$5:$Q$40,[1]Billing!$AD$5:$AD$40) -> 1468325 | P104: =N104-O104 -> 189776.68
B105: Hameed corporation | C105: =_xlfn.XLOOKUP($B70,[1]Billing!$Q$5:$Q$40,[1]Billing!$R$5:$R$40) -> 46404 | D105: =_xlfn.XLOOKUP($B70,[1]Billing!$Q$5:$Q$40,[1]Billing!$S$5:$S$40) -> 42432.334 | E105: =_xlfn.XLOOKUP($B70,[1]Billing!$Q$5:$Q$40,[1]Billing!$T$5:$T$40) -> 42432.334 | F105: =_xlfn.XLOOKUP($B70,[1]Billing!$Q$5:$Q$40,[1]Billing!$U$5:$U$40) -> 0 | G105: =_xlfn.XLOOKUP($B70,[1]Billing!$Q$5:$Q$40,[1]Billing!$V$5:$V$40) -> 424323.34 | H105: =_xlfn.XLOOKUP($B70,[1]Billing!$Q$5:$Q$40,[1]Billing!$W$5:$W$40) -> 0 | I105: =_xlfn.XLOOKUP($B70,[1]Billing!$Q$5:$Q$40,[1]Billing!$X$5:$X$40) -> 0 | J105: =_xlfn.XLOOKUP($B70,[1]Billing!$Q$5:$Q$40,[1]Billing!$Y$5:$Y$40) -> 0 | K105: =_xlfn.XLOOKUP($B70,[1]Billing!$Q$5:$Q$40,[1]Billing!$Z$5:$Z$40) -> 0 | L105: =_xlfn.XLOOKUP($B70,[1]Billing!$Q$5:$Q$40,[1]Billing!$AA$5:$AA$40) -> 0 | M105: =_xlfn.XLOOKUP($B70,[1]Billing!$Q$5:$Q$40,[1]Billing!$AB$5:$AB$40) -> 0 | N105: =G105+H105+I105+J105+K105+L105+M105 -> 424323.34 | O105: =_xlfn.XLOOKUP($B70,[1]Billing!$Q$5:$Q$40,[1]Billing!$AD$5:$AD$40) -> 424323 | P105: =N105-O105 -> 0.33577176
B106: ibraheem behraam | C106: =_xlfn.XLOOKUP($B71,[1]Billing!$Q$5:$Q$40,[1]Billing!$R$5:$R$40) -> 66705 | D106: =_xlfn.XLOOKUP($B71,[1]Billing!$Q$5:$Q$40,[1]Billing!$S$5:$S$40) -> 60995.794 | E106: =_xlfn.XLOOKUP($B71,[1]Billing!$Q$5:$Q$40,[1]Billing!$T$5:$T$40) -> 0 | F106: =_xlfn.XLOOKUP($B71,[1]Billing!$Q$5:$Q$40,[1]Billing!$U$5:$U$40) -> 60995.794 | G106: =_xlfn.XLOOKUP($B71,[1]Billing!$Q$5:$Q$40,[1]Billing!$V$5:$V$40) -> 0 | H106: =_xlfn.XLOOKUP($B71,[1]Billing!$Q$5:$Q$40,[1]Billing!$W$5:$W$40) -> 792945.32 | I106: =_xlfn.XLOOKUP($B71,[1]Billing!$Q$5:$Q$40,[1]Billing!$X$5:$X$40) -> 0 | J106: =_xlfn.XLOOKUP($B71,[1]Billing!$Q$5:$Q$40,[1]Billing!$Y$5:$Y$40) -> 0 | K106: =_xlfn.XLOOKUP($B71,[1]Billing!$Q$5:$Q$40,[1]Billing!$Z$5:$Z$40) -> 0 | L106: =_xlfn.XLOOKUP($B71,[1]Billing!$Q$5:$Q$40,[1]Billing!$AA$5:$AA$40) -> 0 | M106: =_xlfn.XLOOKUP($B71,[1]Billing!$Q$5:$Q$40,[1]Billing!$AB$5:$AB$40) -> 0 | N106: =G106+H106+I106+J106+K106+L106+M106 -> 792945.32 | O106: =_xlfn.XLOOKUP($B71,[1]Billing!$Q$5:$Q$40,[1]Billing!$AD$5:$AD$40) -> 790500 | P106: =N106-O106 -> 2445.3182
B107: Zia-ullah karachi | C107: =_xlfn.XLOOKUP($B72,[1]Billing!$Q$5:$Q$40,[1]Billing!$R$5:$R$40) -> 13622 | D107: =_xlfn.XLOOKUP($B72,[1]Billing!$Q$5:$Q$40,[1]Billing!$S$5:$S$40) -> 12456.108 | E107: =_xlfn.XLOOKUP($B72,[1]Billing!$Q$5:$Q$40,[1]Billing!$T$5:$T$40) -> 12456.108 | F107: =_xlfn.XLOOKUP($B72,[1]Billing!$Q$5:$Q$40,[1]Billing!$U$5:$U$40) -> 0 | G107: =_xlfn.XLOOKUP($B72,[1]Billing!$Q$5:$Q$40,[1]Billing!$V$5:$V$40) -> 124561.08 | H107: =_xlfn.XLOOKUP($B72,[1]Billing!$Q$5:$Q$40,[1]Billing!$W$5:$W$40) -> 0 | I107: =_xlfn.XLOOKUP($B72,[1]Billing!$Q$5:$Q$40,[1]Billing!$X$5:$X$40) -> 0 | J107: =_xlfn.XLOOKUP($B72,[1]Billing!$Q$5:$Q$40,[1]Billing!$Y$5:$Y$40) -> 0 | K107: =_xlfn.XLOOKUP($B72,[1]Billing!$Q$5:$Q$40,[1]Billing!$Z$5:$Z$40) -> 0 | L107: =_xlfn.XLOOKUP($B72,[1]Billing!$Q$5:$Q$40,[1]Billing!$AA$5:$AA$40) -> 0 | M107: =_xlfn.XLOOKUP($B72,[1]Billing!$Q$5:$Q$40,[1]Billing!$AB$5:$AB$40) -> 0 | N107: =G107+H107+I107+J107+K107+L107+M107 -> 124561.08 | O107: =_xlfn.XLOOKUP($B72,[1]Billing!$Q$5:$Q$40,[1]Billing!$AD$5:$AD$40) -> 124560 | P107: =N107-O107 -> 1.0826628
B108: ZA | C108: =_xlfn.XLOOKUP($B73,[1]Billing!$Q$5:$Q$40,[1]Billing!$R$5:$R$40) -> 32399 | D108: =_xlfn.XLOOKUP($B73,[1]Billing!$Q$5:$Q$40,[1]Billing!$S$5:$S$40) -> 29626.006 | E108: =_xlfn.XLOOKUP($B73,[1]Billing!$Q$5:$Q$40,[1]Billing!$T$5:$T$40) -> 0 | F108: =_xlfn.XLOOKUP($B73,[1]Billing!$Q$5:$Q$40,[1]Billing!$U$5:$U$40) -> 29626.006 | G108: =_xlfn.XLOOKUP($B73,[1]Billing!$Q$5:$Q$40,[1]Billing!$V$5:$V$40) -> 0 | H108: =_xlfn.XLOOKUP($B73,[1]Billing!$Q$5:$Q$40,[1]Billing!$W$5:$W$40) -> 385138.08 | I108: =_xlfn.XLOOKUP($B73,[1]Billing!$Q$5:$Q$40,[1]Billing!$X$5:$X$40) -> 0 | J108: =_xlfn.XLOOKUP($B73,[1]Billing!$Q$5:$Q$40,[1]Billing!$Y$5:$Y$40) -> 0 | K108: =_xlfn.XLOOKUP($B73,[1]Billing!$Q$5:$Q$40,[1]Billing!$Z$5:$Z$40) -> 0 | L108: =_xlfn.XLOOKUP($B73,[1]Billing!$Q$5:$Q$40,[1]Billing!$AA$5:$AA$40) -> 0 | M108: =_xlfn.XLOOKUP($B73,[1]Billing!$Q$5:$Q$40,[1]Billing!$AB$5:$AB$40) -> 0 | N108: =G108+H108+I108+J108+K108+L108+M108 -> 385138.08 | O108: =_xlfn.XLOOKUP($B73,[1]Billing!$Q$5:$Q$40,[1]Billing!$AD$5:$AD$40) -> 250000 | P108: =N108-O108 -> 135138.08
B109: Ahmad Javaid | C109: =_xlfn.XLOOKUP($B74,[1]Billing!$Q$5:$Q$40,[1]Billing!$R$5:$R$40) -> 4557 | D109: =_xlfn.XLOOKUP($B74,[1]Billing!$Q$5:$Q$40,[1]Billing!$S$5:$S$40) -> 4166.9715 | E109: =_xlfn.XLOOKUP($B74,[1]Billing!$Q$5:$Q$40,[1]Billing!$T$5:$T$40) -> 0 | F109: =_xlfn.XLOOKUP($B74,[1]Billing!$Q$5:$Q$40,[1]Billing!$U$5:$U$40) -> 0 | G109: =_xlfn.XLOOKUP($B74,[1]Billing!$Q$5:$Q$40,[1]Billing!$V$5:$V$40) -> 0 | H109: =_xlfn.XLOOKUP($B74,[1]Billing!$Q$5:$Q$40,[1]Billing!$W$5:$W$40) -> 0 | I109: =_xlfn.XLOOKUP($B74,[1]Billing!$Q$5:$Q$40,[1]Billing!$X$5:$X$40) -> 0 | J109: =_xlfn.XLOOKUP($B74,[1]Billing!$Q$5:$Q$40,[1]Billing!$Y$5:$Y$40) -> 0 | K109: =_xlfn.XLOOKUP($B74,[1]Billing!$Q$5:$Q$40,[1]Billing!$Z$5:$Z$40) -> 0 | L109: =_xlfn.XLOOKUP($B74,[1]Billing!$Q$5:$Q$40,[1]Billing!$AA$5:$AA$40) -> 0 | M109: =_xlfn.XLOOKUP($B74,[1]Billing!$Q$5:$Q$40,[1]Billing!$AB$5:$AB$40) -> 54170.629 | N109: =G109+H109+I109+J109+K109+L109+M109 -> 54170.629 | O109: =_xlfn.XLOOKUP($B74,[1]Billing!$Q$5:$Q$40,[1]Billing!$AD$5:$AD$40) -> 0 | P109: =N109-O109 -> 54170.629
C110: =_xlfn.XLOOKUP($B75,[1]Billing!$Q$5:$Q$40,[1]Billing!$R$5:$R$40) -> 0 | D110: =_xlfn.XLOOKUP($B75,[1]Billing!$Q$5:$Q$40,[1]Billing!$S$5:$S$40) -> 0 | E110: =_xlfn.XLOOKUP($B75,[1]Billing!$Q$5:$Q$40,[1]Billing!$T$5:$T$40) -> 0 | F110: =_xlfn.XLOOKUP($B75,[1]Billing!$Q$5:$Q$40,[1]Billing!$U$5:$U$40) -> 0 | G110: =_xlfn.XLOOKUP($B75,[1]Billing!$Q$5:$Q$40,[1]Billing!$V$5:$V$40) -> 0 | H110: =_xlfn.XLOOKUP($B75,[1]Billing!$Q$5:$Q$40,[1]Billing!$W$5:$W$40) -> 0 | I110: =_xlfn.XLOOKUP($B75,[1]Billing!$Q$5:$Q$40,[1]Billing!$X$5:$X$40) -> 0 | J110: =_xlfn.XLOOKUP($B75,[1]Billing!$Q$5:$Q$40,[1]Billing!$Y$5:$Y$40) -> 0 | K110: =_xlfn.XLOOKUP($B75,[1]Billing!$Q$5:$Q$40,[1]Billing!$Z$5:$Z$40) -> 0 | L110: =_xlfn.XLOOKUP($B75,[1]Billing!$Q$5:$Q$40,[1]Billing!$AA$5:$AA$40) -> 0 | M110: =_xlfn.XLOOKUP($B75,[1]Billing!$Q$5:$Q$40,[1]Billing!$AB$5:$AB$40) -> 0 | N110: =G110+H110+I110+J110+K110+L110+M110 -> 0 | O110: =_xlfn.XLOOKUP($B75,[1]Billing!$Q$5:$Q$40,[1]Billing!$AD$5:$AD$40) -> 0 | P110: =N110-O110 -> 0
C111: =_xlfn.XLOOKUP($B76,[1]Billing!$Q$5:$Q$40,[1]Billing!$R$5:$R$40) -> 0 | D111: =_xlfn.XLOOKUP($B76,[1]Billing!$Q$5:$Q$40,[1]Billing!$S$5:$S$40) -> 0 | E111: =_xlfn.XLOOKUP($B76,[1]Billing!$Q$5:$Q$40,[1]Billing!$T$5:$T$40) -> 0 | F111: =_xlfn.XLOOKUP($B76,[1]Billing!$Q$5:$Q$40,[1]Billing!$U$5:$U$40) -> 0 | G111: =_xlfn.XLOOKUP($B76,[1]Billing!$Q$5:$Q$40,[1]Billing!$V$5:$V$40) -> 0 | H111: =_xlfn.XLOOKUP($B76,[1]Billing!$Q$5:$Q$40,[1]Billing!$W$5:$W$40) -> 0 | I111: =_xlfn.XLOOKUP($B76,[1]Billing!$Q$5:$Q$40,[1]Billing!$X$5:$X$40) -> 0 | J111: =_xlfn.XLOOKUP($B76,[1]Billing!$Q$5:$Q$40,[1]Billing!$Y$5:$Y$40) -> 0 | K111: =_xlfn.XLOOKUP($B76,[1]Billing!$Q$5:$Q$40,[1]Billing!$Z$5:$Z$40) -> 0 | L111: =_xlfn.XLOOKUP($B76,[1]Billing!$Q$5:$Q$40,[1]Billing!$AA$5:$AA$40) -> 0 | M111: =_xlfn.XLOOKUP($B76,[1]Billing!$Q$5:$Q$40,[1]Billing!$AB$5:$AB$40) -> 0 | N111: =G111+H111+I111+J111+K111+L111+M111 -> 0 | O111: =_xlfn.XLOOKUP($B76,[1]Billing!$Q$5:$Q$40,[1]Billing!$AD$5:$AD$40) -> 0 | P111: =N111-O111 -> 0
C112: =_xlfn.XLOOKUP($B77,[1]Billing!$Q$5:$Q$40,[1]Billing!$R$5:$R$40) -> 0 | D112: =_xlfn.XLOOKUP($B77,[1]Billing!$Q$5:$Q$40,[1]Billing!$S$5:$S$40) -> 0 | E112: =_xlfn.XLOOKUP($B77,[1]Billing!$Q$5:$Q$40,[1]Billing!$T$5:$T$40) -> 0 | F112: =_xlfn.XLOOKUP($B77,[1]Billing!$Q$5:$Q$40,[1]Billing!$U$5:$U$40) -> 0 | G112: =_xlfn.XLOOKUP($B77,[1]Billing!$Q$5:$Q$40,[1]Billing!$V$5:$V$40) -> 0 | H112: =_xlfn.XLOOKUP($B77,[1]Billing!$Q$5:$Q$40,[1]Billing!$W$5:$W$40) -> 0 | I112: =_xlfn.XLOOKUP($B77,[1]Billing!$Q$5:$Q$40,[1]Billing!$X$5:$X$40) -> 0 | J112: =_xlfn.XLOOKUP($B77,[1]Billing!$Q$5:$Q$40,[1]Billing!$Y$5:$Y$40) -> 0 | K112: =_xlfn.XLOOKUP($B77,[1]Billing!$Q$5:$Q$40,[1]Billing!$Z$5:$Z$40) -> 0 | L112: =_xlfn.XLOOKUP($B77,[1]Billing!$Q$5:$Q$40,[1]Billing!$AA$5:$AA$40) -> 0 | M112: =_xlfn.XLOOKUP($B77,[1]Billing!$Q$5:$Q$40,[1]Billing!$AB$5:$AB$40) -> 0 | N112: =G112+H112+I112+J112+K112+L112+M112 -> 0 | O112: =_xlfn.XLOOKUP($B77,[1]Billing!$Q$5:$Q$40,[1]Billing!$AD$5:$AD$40) -> 0 | P112: =N112-O112 -> 0
C113: =_xlfn.XLOOKUP($B78,[1]Billing!$Q$5:$Q$40,[1]Billing!$R$5:$R$40) -> 0 | D113: =_xlfn.XLOOKUP($B78,[1]Billing!$Q$5:$Q$40,[1]Billing!$S$5:$S$40) -> 0 | E113: =_xlfn.XLOOKUP($B78,[1]Billing!$Q$5:$Q$40,[1]Billing!$T$5:$T$40) -> 0 | F113: =_xlfn.XLOOKUP($B78,[1]Billing!$Q$5:$Q$40,[1]Billing!$U$5:$U$40) -> 0 | G113: =_xlfn.XLOOKUP($B78,[1]Billing!$Q$5:$Q$40,[1]Billing!$V$5:$V$40) -> 0 | H113: =_xlfn.XLOOKUP($B78,[1]Billing!$Q$5:$Q$40,[1]Billing!$W$5:$W$40) -> 0 | I113: =_xlfn.XLOOKUP($B78,[1]Billing!$Q$5:$Q$40,[1]Billing!$X$5:$X$40) -> 0 | J113: =_xlfn.XLOOKUP($B78,[1]Billing!$Q$5:$Q$40,[1]Billing!$Y$5:$Y$40) -> 0 | K113: =_xlfn.XLOOKUP($B78,[1]Billing!$Q$5:$Q$40,[1]Billing!$Z$5:$Z$40) -> 0 | L113: =_xlfn.XLOOKUP($B78,[1]Billing!$Q$5:$Q$40,[1]Billing!$AA$5:$AA$40) -> 0 | M113: =_xlfn.XLOOKUP($B78,[1]Billing!$Q$5:$Q$40,[1]Billing!$AB$5:$AB$40) -> 0 | N113: =G113+H113+I113+J113+K113+L113+M113 -> 0 | O113: =_xlfn.XLOOKUP($B78,[1]Billing!$Q$5:$Q$40,[1]Billing!$AD$5:$AD$40) -> 0 | P113: =N113-O113 -> 0
C114: =_xlfn.XLOOKUP($B79,[1]Billing!$Q$5:$Q$40,[1]Billing!$R$5:$R$40) -> 0 | D114: =_xlfn.XLOOKUP($B79,[1]Billing!$Q$5:$Q$40,[1]Billing!$S$5:$S$40) -> 0 | E114: =_xlfn.XLOOKUP($B79,[1]Billing!$Q$5:$Q$40,[1]Billing!$T$5:$T$40) -> 0 | F114: =_xlfn.XLOOKUP($B79,[1]Billing!$Q$5:$Q$40,[1]Billing!$U$5:$U$40) -> 0 | G114: =_xlfn.XLOOKUP($B79,[1]Billing!$Q$5:$Q$40,[1]Billing!$V$5:$V$40) -> 0 | H114: =_xlfn.XLOOKUP($B79,[1]Billing!$Q$5:$Q$40,[1]Billing!$W$5:$W$40) -> 0 | I114: =_xlfn.XLOOKUP($B79,[1]Billing!$Q$5:$Q$40,[1]Billing!$X$5:$X$40) -> 0 | J114: =_xlfn.XLOOKUP($B79,[1]Billing!$Q$5:$Q$40,[1]Billing!$Y$5:$Y$40) -> 0 | K114: =_xlfn.XLOOKUP($B79,[1]Billing!$Q$5:$Q$40,[1]Billing!$Z$5:$Z$40) -> 0 | L114: =_xlfn.XLOOKUP($B79,[1]Billing!$Q$5:$Q$40,[1]Billing!$AA$5:$AA$40) -> 0 | M114: =_xlfn.XLOOKUP($B79,[1]Billing!$Q$5:$Q$40,[1]Billing!$AB$5:$AB$40) -> 0 | N114: =G114+H114+I114+J114+K114+L114+M114 -> 0 | O114: =_xlfn.XLOOKUP($B79,[1]Billing!$Q$5:$Q$40,[1]Billing!$AD$5:$AD$40) -> 0 | P114: =N114-O114 -> 0
C115: =_xlfn.XLOOKUP($B80,[1]Billing!$Q$5:$Q$40,[1]Billing!$R$5:$R$40) -> 0 | D115: =_xlfn.XLOOKUP($B80,[1]Billing!$Q$5:$Q$40,[1]Billing!$S$5:$S$40) -> 0 | E115: =_xlfn.XLOOKUP($B80,[1]Billing!$Q$5:$Q$40,[1]Billing!$T$5:$T$40) -> 0 | F115: =_xlfn.XLOOKUP($B80,[1]Billing!$Q$5:$Q$40,[1]Billing!$U$5:$U$40) -> 0 | G115: =_xlfn.XLOOKUP($B80,[1]Billing!$Q$5:$Q$40,[1]Billing!$V$5:$V$40) -> 0 | H115: =_xlfn.XLOOKUP($B80,[1]Billing!$Q$5:$Q$40,[1]Billing!$W$5:$W$40) -> 0 | I115: =_xlfn.XLOOKUP($B80,[1]Billing!$Q$5:$Q$40,[1]Billing!$X$5:$X$40) -> 0 | J115: =_xlfn.XLOOKUP($B80,[1]Billing!$Q$5:$Q$40,[1]Billing!$Y$5:$Y$40) -> 0 | K115: =_xlfn.XLOOKUP($B80,[1]Billing!$Q$5:$Q$40,[1]Billing!$Z$5:$Z$40) -> 0 | L115: =_xlfn.XLOOKUP($B80,[1]Billing!$Q$5:$Q$40,[1]Billing!$AA$5:$AA$40) -> 0 | M115: =_xlfn.XLOOKUP($B80,[1]Billing!$Q$5:$Q$40,[1]Billing!$AB$5:$AB$40) -> 0 | N115: =G115+H115+I115+J115+K115+L115+M115 -> 0 | O115: =_xlfn.XLOOKUP($B80,[1]Billing!$Q$5:$Q$40,[1]Billing!$AD$5:$AD$40) -> 0 | P115: =N115-O115 -> 0

Sheet Bill Print
I4: Party Names: | J4: {=_xlfn.UNIQUE(Table1[Party Name])} -> BSC
J5: Ejaz Sahab
B6: shahid Qasayi | J6: Arshad
B7: Description | C7: Rate | D7: gazana | E7: sum | J7: Shehzad Kamoki
B8: Total Gazana/gaz | D8: {=_xlfn.XLOOKUP($B$6,_xlfn.ANCHORARRAY( Billing!Q5), INDEX(Billing!R5:R25, _xlfn.SEQUENCE(ROWS(_xlfn.ANCHORARRAY(Billing!$Q$5)))), "Not Found")} -> 263818 | J8: Sufi Nawaz Sahab
J9: Sajad Khan
B10: Gazana/meters | D10: {=_xlfn.XLOOKUP($B$6,_xlfn.ANCHORARRAY( Billing!$Q$5), INDEX(Billing!S5:S25, _xlfn.SEQUENCE(ROWS(_xlfn.ANCHORARRAY(Billing!$Q$5)))), "Not Found")} -> 241238.11 | J10: Raaz Fabrics
J11: Azam
B12: Total Chamki-crinkle/meters | C12: {=_xlfn.XLOOKUP($B$6,_xlfn.ANCHORARRAY( Billing!$B$49), OFFSET(Billing!Q49, 0, 0, ROWS(_xlfn.ANCHORARRAY(Billing!$B$49))), "Not Found")} -> 10 | D12: {=_xlfn.XLOOKUP($B$6,_xlfn.ANCHORARRAY( Billing!$Q$5), INDEX(Billing!T5:T25, _xlfn.SEQUENCE(ROWS(_xlfn.ANCHORARRAY(Billing!$Q$5)))), "Not Found")} -> 189718.36 | E12: =Table21[[#This Row],[gazana]]*Table21[[#This Row],[Rate]] -> 1897183.6 | J12: Ubaidullah
J13: Ashraf Zia
B14: Total Super Silky/meters | C14: {=_xlfn.XLOOKUP($B$6,_xlfn.ANCHORARRAY( Billing!$B$49), OFFSET(Billing!R49, 0, 0, ROWS(_xlfn.ANCHORARRAY(Billing!$B$49))), "Not Found")} -> 12 | D14: {=_xlfn.XLOOKUP($B$6,_xlfn.ANCHORARRAY( Billing!$Q$5), INDEX(Billing!U5:U25, _xlfn.SEQUENCE(ROWS(_xlfn.ANCHORARRAY(Billing!$Q$5)))), "Not Found")} -> 0 | E14: =Table21[[#This Row],[gazana]]*Table21[[#This Row],[Rate]] -> 0 | J14: Hafiz Qureshi
J15: Badshah Fabrics
B16: Total Billing | E16: =E12+E14 -> 1897183.6 | J16: Reject
J17: Amjad 7up
B18: Total Paid | E18: {=_xlfn.XLOOKUP($B$6,_xlfn.ANCHORARRAY( Billing!Q5), OFFSET(Billing!AD5, 0, 0, ROWS(_xlfn.ANCHORARRAY(Billing!Q5))), "Not Found")} -> 2333095 | J18: Hazrat Khan
J19: Haseeb Shamsi
B20: Total Balance | E20: {=_xlfn.XLOOKUP($B$6,_xlfn.ANCHORARRAY( Billing!Q5), OFFSET(Billing!AE5, 0, 0, ROWS(_xlfn.ANCHORARRAY(Billing!Q5))), "Not Found")} -> 134767.11 | J20: Faizan
J21: Shafique Ansari
J22: Amjad sohail
J23: Salman Zaffar
J24: Shahid Qasayi
J25: Hameed corporation
J26: ibraheem behraam
J27: Zia-ullah karachi
J28: ZA
J29: Ahmad Javaid

Sheet Expenses
B1: Expenses
B3: Type | C3: Amount | D3: Description | E3: cost per meter
B4: Wood | C4: =Wood!K6+((363*810)+(830*233)+(146*580)) -> 3209860 | D4: 700*810 | E4: =Table12[[#This Row],[Amount]]/Table1[[#Totals],[tiyar/meters]] -> 4.2778216
B5: Dyes/Chemical | C5: =SUM(Table8[Price])+Dyes!P56 -> 1077660 | E5: =Table12[[#This Row],[Amount]]/Table1[[#Totals],[tiyar/meters]] -> 1.4362113
B6: Finish | C6: =SUM(Table2[Price])+Finish!K30 -> 457600 | D6: 60 bags starch 3 bp26 | E6: =Table12[[#This Row],[Amount]]/Table1[[#Totals],[tiyar/meters]] -> 0.60984939
B7: Misc | C7: =SUMIFS(Table14[Debit], Table14[Party],Table12[[#This Row],[Type]]) -> 11275 | E7: =Table12[[#This Row],[Amount]]/Table1[[#Totals],[tiyar/meters]] -> 0.015026337
B8: Electricity | C8: =Electricity!E3 -> 0 | E8: =Table12[[#This Row],[Amount]]/Table1[[#Totals],[tiyar/meters]] -> 0
B9: Salary | C9: =SUMIFS(Table14[Debit], Table14[Party],Table12[[#This Row],[Type]])+SUMIFS(Table14[Debit], Table14[Party],"Advance Salary") -> 140300 | E9: =Table12[[#This Row],[Amount]]/Table1[[#Totals],[tiyar/meters]] -> 0.18697961
B10: Running Acc | C10: =Table5[[#Totals],[Amount]] -> 54460 | E10: =Table12[[#This Row],[Amount]]/Table1[[#Totals],[tiyar/meters]] -> 0.072579541
B11: Transport | C11: =Table13[[#Totals],[Debit]] -> 74805 | E11: =Table12[[#This Row],[Amount]]/Table1[[#Totals],[tiyar/meters]] -> 0.099693583
B12: Parts | C12: =Table15[[#Totals],[Amount]] -> 69995 | E12: =Table12[[#This Row],[Amount]]/Table1[[#Totals],[tiyar/meters]] -> 0.093283234
E13: =Table12[[#This Row],[Amount]]/Table1[[#Totals],[tiyar/meters]] -> 0
C14: =SUM(Table12[Amount]) -> 5095955
B17: Stock (for next 15th)
B18: Stock | C18: quantity | D18: Column3
B19: Wood | C19: =388+236+100+288 -> 1012 | D19: mann
B20: Starch | C20: 100 | D20: Kg
B21: Pva | C21: 75 | D21: Kg
B22: Dyes | C22: Nil

Sheet Profit
B2: Column1 | C2: Column2
B3: Billing | C3: =Billing!C23 + SUMIFS(Table14[Credit], Table14[Party], "Transport") -> 7678658.4
B4: Expenses | C4: =Table12[[#Totals],[Amount]] -> 5095955
B5: Profit | C5: =C3-C4 -> 2582703.4
B10: Column1 | C10: Column2
B11: Billing | C11: =C3 -> 7678658.4
B12: Credit | C12: =SUM(Table14[Credit]) -> 20676731
B13: balance | C13: =(C11-C12) -> -12998073
B15: Expenses | C15: =C4 -> 5095955
B16: Debit | C16: =SUM(Table14[Debit]) -> 20589837
B17: Exp Balance | C17: =C15-C16 -> -15493882
B19: Cash in hand | C19: =Table18[[#Totals],[amount]] -> 86894
B21: Difference | C21: =(C13-C17)+C19 -> 2582703.4 | E21: My share: | F21: =C5*0.05 -> 129135.17

Sheet Transport
B2: Date | C2: Type | D2: Debit | E2: Credit | F2: Diff
B3: 46006 | D3: =SUMIFS(Table14[Debit], Table14[Date], Table13[[#This Row],[Date]], Table14[Party], "Transport") -> 0 | E3: =SUMIFS(Table14[Credit], Table14[Date], Table13[[#This Row],[Date]], Table14[Party], "Transport") -> 0
B4: 46007 | D4: =SUMIFS(Table14[Debit], Table14[Date], Table13[[#This Row],[Date]], Table14[Party], "Transport") -> 0 | E4: =SUMIFS(Table14[Credit], Table14[Date], Table13[[#This Row],[Date]], Table14[Party], "Transport") -> 0
B5: 46008 | D5: =SUMIFS(Table14[Debit], Table14[Date], Table13[[#This Row],[Date]], Table14[Party], "Transport") -> 0 | E5: =SUMIFS(Table14[Credit], Table14[Date], Table13[[#This Row],[Date]], Table14[Party], "Transport") -> 0
B6: 46009 | D6: =SUMIFS(Table14[Debit], Table14[Date], Table13[[#This Row],[Date]], Table14[Party], "Transport") -> 0 | E6: =SUMIFS(Table14[Credit], Table14[Date], Table13[[#This Row],[Date]], Table14[Party], "Transport") -> 0
B7: 46010 | D7: =SUMIFS(Table14[Debit], Table14[Date], Table13[[#This Row],[Date]], Table14[Party], "Transport") -> 16000 | E7: =SUMIFS(Table14[Credit], Table14[Date], Table13[[#This Row],[Date]], Table14[Party], "Transport") -> 0
B8: 46011 | D8: =SUMIFS(Table14[Debit], Table14[Date], Table13[[#This Row],[Date]], Table14[Party], "Transport") -> 11836 | E8: =SUMIFS(Table14[Credit], Table14[Date], Table13[[#This Row],[Date]], Table14[Party], "Transport") -> 0
B9: 46012 | D9: =SUMIFS(Table14[Debit], Table14[Date], Table13[[#This Row],[Date]], Table14[Party], "Transport") -> 0 | E9: =SUMIFS(Table14[Credit], Table14[Date], Table13[[#This Row],[Date]], Table14[Party], "Transport") -> 0
B10: 46013 | D10: =SUMIFS(Table14[Debit], Table14[Date], Table13[[#This Row],[Date]], Table14[Party], "Transport") -> 0 | E10: =SUMIFS(Table14[Credit], Table14[Date], Table13[[#This Row],[Date]], Table14[Party], "Transport") -> 0
B11: 46014 | D11: =SUMIFS(Table14[Debit], Table14[Date], Table13[[#This Row],[Date]], Table14[Party], "Transport") -> 5306 | E11: =SUMIFS(Table14[Credit], Table14[Date], Table13[[#This Row],[Date]], Table14[Party], "Transport") -> 0
B12: 46015 | D12: =SUMIFS(Table14[Debit], Table14[Date], Table13[[#This Row],[Date]], Table14[Party], "Transport") -> 14900 | E12: =SUMIFS(Table14[Credit], Table14[Date], Table13[[#This Row],[Date]], Table14[Party], "Transport") -> 0
B13: 46016 | D13: =SUMIFS(Table14[Debit], Table14[Date], Table13[[#This Row],[Date]], Table14[Party], "Transport") -> 5313 | E13: =SUMIFS(Table14[Credit], Table14[Date], Table13[[#This Row],[Date]], Table14[Party], "Transport") -> 0
B14: 46017 | D14: =SUMIFS(Table14[Debit], Table14[Date], Table13[[#This Row],[Date]], Table14[Party], "Transport") -> 0 | E14: =SUMIFS(Table14[Credit], Table14[Date], Table13[[#This Row],[Date]], Table14[Party], "Transport") -> 0
... B37: 46040 | D37: =SUMIFS(Table14[Debit], Table14[Date], Table13[[#This Row],[Date]], Table14[Party], "Transport") -> 0 | E37: =SUMIFS(Table14[Credit], Table14[Date], Table13[[#This Row],[Date]], Table14[Party], "Transport") -> 0
D38: =SUBTOTAL(109,Table13[Debit]) -> 74805 | E38: =SUBTOTAL(109,Table13[Credit]) -> 0 | F38: =Table13[[#Totals],[Debit]]-Table13[[#Totals],[Credit]] -> 74805

Sheet ledger
A1: Date | B1: Party Name | C1: Bill Number | D1: Quality | E1: Shipment Number | F1: Kora/metre | G1: Tiyaar/gaz | H1: shortage % | I1: tiyar/meters | J1: billing | K1: Total Billing
A2: 45979 | B2: BSC | C2: November Closing CF | D2: Chamki | H2: =_xlfn.XLOOKUP(Table1[[#This Row],[Shipment Number]], 'pivot '!A:A,'pivot '!G:G, "NF") -> #DIV/0! | I2: =_xlfn.XLOOKUP(Table1[[#This Row],[Party Name]], [1]Billing!$Q$5:$Q$40, [1]Billing!$T$5:$T$40) -> 2035507.5 | J2: =_xlfn.XLOOKUP(Table1[[#This Row],[Party Name]], [1]Billing!$Q$5:$Q$40, [1]Billing!$V$5:$V$40) -> 20355075
A3: 45979 | B3: Ejaz Sahab | C3: November Closing CF | D3: Chamki | H3: =_xlfn.XLOOKUP(Table1[[#This Row],[Shipment Number]], 'pivot '!A:A,'pivot '!G:G, "NF") -> #DIV/0! | I3: =_xlfn.XLOOKUP(Table1[[#This Row],[Party Name]], [1]Billing!$Q$5:$Q$40, [1]Billing!$T$5:$T$40) -> 148145.57 | J3: =_xlfn.XLOOKUP(Table1[[#This Row],[Party Name]], [1]Billing!$Q$5:$Q$40, [1]Billing!$V$5:$V$40) -> 1481455.7
A4: 45979 | B4: Arshad | C4: November Closing CF | D4: Chamki | H4: =_xlfn.XLOOKUP(Table1[[#This Row],[Shipment Number]], 'pivot '!A:A,'pivot '!G:G, "NF") -> #DIV/0! | I4: =_xlfn.XLOOKUP(Table1[[#This Row],[Party Name]], [1]Billing!$Q$5:$Q$40, [1]Billing!$T$5:$T$40) -> 522790.78 | J4: =_xlfn.XLOOKUP(Table1[[#This Row],[Party Name]], [1]Billing!$Q$5:$Q$40, [1]Billing!$V$5:$V$40) -> 5227907.8
A5: 45979 | B5: Shehzad Kamoki | C5: November Closing CF | D5: Chamki | H5: =_xlfn.XLOOKUP(Table1[[#This Row],[Shipment Number]], 'pivot '!A:A,'pivot '!G:G, "NF") -> #DIV/0! | I5: =_xlfn.XLOOKUP(Table1[[#This Row],[Party Name]], [1]Billing!$Q$5:$Q$40, [1]Billing!$T$5:$T$40) -> 123086.14 | J5: =_xlfn.XLOOKUP(Table1[[#This Row],[Party Name]], [1]Billing!$Q$5:$Q$40, [1]Billing!$V$5:$V$40) -> 1269270.3
A6: 45979 | B6: Sufi Nawaz Sahab | C6: November Closing CF | D6: Chamki | H6: =_xlfn.XLOOKUP(Table1[[#This Row],[Shipment Number]], 'pivot '!A:A,'pivot '!G:G, "NF") -> #DIV/0! | I6: =_xlfn.XLOOKUP(Table1[[#This Row],[Party Name]], [1]Billing!$Q$5:$Q$40, [1]Billing!$T$5:$T$40) -> 599330.65 | J6: =_xlfn.XLOOKUP(Table1[[#This Row],[Party Name]], [1]Billing!$Q$5:$Q$40, [1]Billing!$V$5:$V$40) -> 5408917.9
A7: 45979 | B7: Sajad Khan | C7: November Closing CF | D7: Chamki | H7: =_xlfn.XLOOKUP(Table1[[#This Row],[Shipment Number]], 'pivot '!A:A,'pivot '!G:G, "NF") -> #DIV/0! | I7: =_xlfn.XLOOKUP(Table1[[#This Row],[Party Name]], [1]Billing!$Q$5:$Q$40, [1]Billing!$T$5:$T$40) -> 785980.25 | J7: =_xlfn.XLOOKUP(Table1[[#This Row],[Party Name]], [1]Billing!$Q$5:$Q$40, [1]Billing!$V$5:$V$40) -> 7859802.5
A8: 45979 | B8: Raaz Fabrics | C8: November Closing CF | D8: Chamki | H8: =_xlfn.XLOOKUP(Table1[[#This Row],[Shipment Number]], 'pivot '!A:A,'pivot '!G:G, "NF") -> #DIV/0! | I8: =_xlfn.XLOOKUP(Table1[[#This Row],[Party Name]], [1]Billing!$Q$5:$Q$40, [1]Billing!$T$5:$T$40) -> 139387.34 | J8: =_xlfn.XLOOKUP(Table1[[#This Row],[Party Name]], [1]Billing!$Q$5:$Q$40, [1]Billing!$V$5:$V$40) -> 1393873.4
A9: 45979 | B9: Azam | C9: November Closing CF | D9: Chamki | H9: =_xlfn.XLOOKUP(Table1[[#This Row],[Shipment Number]], 'pivot '!A:A,'pivot '!G:G, "NF") -> #DIV/0! | I9: =_xlfn.XLOOKUP(Table1[[#This Row],[Party Name]], [1]Billing!$Q$5:$Q$40, [1]Billing!$T$5:$T$40) -> 305469.09 | J9: =_xlfn.XLOOKUP(Table1[[#This Row],[Party Name]], [1]Billing!$Q$5:$Q$40, [1]Billing!$V$5:$V$40) -> 3054690.9
A10: 45979 | B10: Ubaidullah | C10: November Closing CF | D10: Chamki | H10: =_xlfn.XLOOKUP(Table1[[#This Row],[Shipment Number]], 'pivot '!A:A,'pivot '!G:G, "NF") -> #DIV/0! | I10: =_xlfn.XLOOKUP(Table1[[#This Row],[Party Name]], [1]Billing!$Q$5:$Q$40, [1]Billing!$T$5:$T$40) -> 46132.955 | J10: =_xlfn.XLOOKUP(Table1[[#This Row],[Party Name]], [1]Billing!$Q$5:$Q$40, [1]Billing!$V$5:$V$40) -> 461329.55
A11: 45979 | B11: Ashraf Zia | C11: November Closing CF | D11: Chamki | H11: =_xlfn.XLOOKUP(Table1[[#This Row],[Shipment Number]], 'pivot '!A:A,'pivot '!G:G, "NF") -> #DIV/0! | I11: =_xlfn.XLOOKUP(Table1[[#This Row],[Party Name]], [1]Billing!$Q$5:$Q$40, [1]Billing!$T$5:$T$40) -> 21310.351 | J11: =_xlfn.XLOOKUP(Table1[[#This Row],[Party Name]], [1]Billing!$Q$5:$Q$40, [1]Billing!$V$5:$V$40) -> 255724.21
A12: 45979 | B12: Hafiz Qureshi | C12: November Closing CF | D12: Chamki | H12: =_xlfn.XLOOKUP(Table1[[#This Row],[Shipment Number]], 'pivot '!A:A,'pivot '!G:G, "NF") -> #DIV/0! | I12: =_xlfn.XLOOKUP(Table1[[#This Row],[Party Name]], [1]Billing!$Q$5:$Q$40, [1]Billing!$T$5:$T$40) -> 185456.29 | J12: =_xlfn.XLOOKUP(Table1[[#This Row],[Party Name]], [1]Billing!$Q$5:$Q$40, [1]Billing!$V$5:$V$40) -> 1854562.9
A13: 45979 | B13: Badshah Fabrics | C13: November Closing CF | D13: Chamki | H13: =_xlfn.XLOOKUP(Table1[[#This Row],[Shipment Number]], 'pivot '!A:A,'pivot '!G:G, "NF") -> #DIV/0! | I13: =_xlfn.XLOOKUP(Table1[[#This Row],[Party Name]], [1]Billing!$Q$5:$Q$40, [1]Billing!$T$5:$T$40) -> 355909.84 | J13: =_xlfn.XLOOKUP(Table1[[#This Row],[Party Name]], [1]Billing!$Q$5:$Q$40, [1]Billing!$V$5:$V$40) -> 3559098.4
... A27: 45979 | B27: Ahmad Javaid | C27: November Closing CF | D27: Chamki | H27: =_xlfn.XLOOKUP(Table1[[#This Row],[Shipment Number]], 'pivot '!A:A,'pivot '!G:G, "NF") -> #DIV/0! | I27: =_xlfn.XLOOKUP(Table1[[#This Row],[Party Name]], [1]Billing!$Q$5:$Q$40, [1]Billing!$T$5:$T$40) -> 0 | J27: =_xlfn.XLOOKUP(Table1[[#This Row],[Party Name]], [1]Billing!$Q$5:$Q$40, [1]Billing!$V$5:$V$40) -> 0
A28: 45979 | B28: BSC | C28: November Closing CF | D28: Silky | H28: =_xlfn.XLOOKUP(Table1[[#This Row],[Shipment Number]], 'pivot '!A:A,'pivot '!G:G, "NF") -> #DIV/0! | I28: =_xlfn.XLOOKUP(Table1[[#This Row],[Party Name]], [1]Billing!$Q$5:$Q$40, [1]Billing!$U$5:$U$40) -> 282468.91 | J28: =_xlfn.XLOOKUP(Table1[[#This Row],[Party Name]], [1]Billing!$Q$5:$Q$40, [1]Billing!$W$5:$W$40) -> 3583739.9
A29: 45979 | B29: Ejaz Sahab | C29: November Closing CF | D29: Silky | H29: =_xlfn.XLOOKUP(Table1[[#This Row],[Shipment Number]], 'pivot '!A:A,'pivot '!G:G, "NF") -> #DIV/0! | I29: =_xlfn.XLOOKUP(Table1[[#This Row],[Party Name]], [1]Billing!$Q$5:$Q$40, [1]Billing!$U$5:$U$40) -> 211578.27 | J29: =_xlfn.XLOOKUP(Table1[[#This Row],[Party Name]], [1]Billing!$Q$5:$Q$40, [1]Billing!$W$5:$W$40) -> 2691373.4
A30: 45979 | B30: Arshad | C30: November Closing CF | D30: Silky | H30: =_xlfn.XLOOKUP(Table1[[#This Row],[Shipment Number]], 'pivot '!A:A,'pivot '!G:G, "NF") -> #DIV/0! | I30: =_xlfn.XLOOKUP(Table1[[#This Row],[Party Name]], [1]Billing!$Q$5:$Q$40, [1]Billing!$U$5:$U$40) -> 78112.655 | J30: =_xlfn.XLOOKUP(Table1[[#This Row],[Party Name]], [1]Billing!$Q$5:$Q$40, [1]Billing!$W$5:$W$40) -> 1000670.3
A31: 45979 | B31: Shehzad Kamoki | C31: November Closing CF | D31: Silky | H31: =_xlfn.XLOOKUP(Table1[[#This Row],[Shipment Number]], 'pivot '!A:A,'pivot '!G:G, "NF") -> #DIV/0! | I31: =_xlfn.XLOOKUP(Table1[[#This Row],[Party Name]], [1]Billing!$Q$5:$Q$40, [1]Billing!$U$5:$U$40) -> 0 | J31: =_xlfn.XLOOKUP(Table1[[#This Row],[Party Name]], [1]Billing!$Q$5:$Q$40, [1]Billing!$W$5:$W$40) -> 0
A32: 45979 | B32: Sufi Nawaz Sahab | C32: November Closing CF | D32: Silky | H32: =_xlfn.XLOOKUP(Table1[[#This Row],[Shipment Number]], 'pivot '!A:A,'pivot '!G:G, "NF") -> #DIV/0! | I32: =_xlfn.XLOOKUP(Table1[[#This Row],[Party Name]], [1]Billing!$Q$5:$Q$40, [1]Billing!$U$5:$U$40) -> 485823.88 | J32: =_xlfn.XLOOKUP(Table1[[#This Row],[Party Name]], [1]Billing!$Q$5:$Q$40, [1]Billing!$W$5:$W$40) -> 5829886.6
A33: 45979 | B33: Sajad Khan | C33: November Closing CF | D33: Silky | H33: =_xlfn.XLOOKUP(Table1[[#This Row],[Shipment Number]], 'pivot '!A:A,'pivot '!G:G, "NF") -> #DIV/0! | I33: =_xlfn.XLOOKUP(Table1[[#This Row],[Party Name]], [1]Billing!$Q$5:$Q$40, [1]Billing!$U$5:$U$40) -> 0 | J33: =_xlfn.XLOOKUP(Table1[[#This Row],[Party Name]], [1]Billing!$Q$5:$Q$40, [1]Billing!$W$5:$W$40) -> 0
A34: 45979 | B34: Raaz Fabrics | C34: November Closing CF | D34: Silky | H34: =_xlfn.XLOOKUP(Table1[[#This Row],[Shipment Number]], 'pivot '!A:A,'pivot '!G:G, "NF") -> #DIV/0! | I34: =_xlfn.XLOOKUP(Table1[[#This Row],[Party Name]], [1]Billing!$Q$5:$Q$40, [1]Billing!$U$5:$U$40) -> 0 | J34: =_xlfn.XLOOKUP(Table1[[#This Row],[Party Name]], [1]Billing!$Q$5:$Q$40, [1]Billing!$W$5:$W$40) -> 0
A35: 45979 | B35: Azam | C35: November Closing CF | D35: Silky | H35: =_xlfn.XLOOKUP(Table1[[#This Row],[Shipment Number]], 'pivot '!A:A,'pivot '!G:G, "NF") -> #DIV/0! | I35: =_xlfn.XLOOKUP(Table1[[#This Row],[Party Name]], [1]Billing!$Q$5:$Q$40, [1]Billing!$U$5:$U$40) -> 25188.369 | J35: =_xlfn.XLOOKUP(Table1[[#This Row],[Party Name]], [1]Billing!$Q$5:$Q$40, [1]Billing!$W$5:$W$40) -> 327448.79
A36: 45979 | B36: Ubaidullah | C36: November Closing CF | D36: Silky | H36: =_xlfn.XLOOKUP(Table1[[#This Row],[Shipment Number]], 'pivot '!A:A,'pivot '!G:G, "NF") -> #DIV/0! | I36: =_xlfn.XLOOKUP(Table1[[#This Row],[Party Name]], [1]Billing!$Q$5:$Q$40, [1]Billing!$U$5:$U$40) -> 14995.428 | J36: =_xlfn.XLOOKUP(Table1[[#This Row],[Party Name]], [1]Billing!$Q$5:$Q$40, [1]Billing!$W$5:$W$40) -> 179945.14
A37: 45979 | B37: Ashraf Zia | C37: November Closing CF | D37: Silky | H37: =_xlfn.XLOOKUP(Table1[[#This Row],[Shipment Number]], 'pivot '!A:A,'pivot '!G:G, "NF") -> #DIV/0! | I37: =_xlfn.XLOOKUP(Table1[[#This Row],[Party Name]], [1]Billing!$Q$5:$Q$40, [1]Billing!$U$5:$U$40) -> 0 | J37: =_xlfn.XLOOKUP(Table1[[#This Row],[Party Name]], [1]Billing!$Q$5:$Q$40, [1]Billing!$W$5:$W$40) -> 0
A38: 45979 | B38: Hafiz Qureshi | C38: November Closing CF | D38: Silky | H38: =_xlfn.XLOOKUP(Table1[[#This Row],[Shipment Number]], 'pivot '!A:A,'pivot '!G:G, "NF") -> #DIV/0! | I38: =_xlfn.XLOOKUP(Table1[[#This Row],[Party Name]], [1]Billing!$Q$5:$Q$40, [1]Billing!$U$5:$U$40) -> 0 | J38: =_xlfn.XLOOKUP(Table1[[#This Row],[Party Name]], [1]Billing!$Q$5:$Q$40, [1]Billing!$W$5:$W$40) -> 0
A39: 45979 | B39: Badshah Fabrics | C39: November Closing CF | D39: Silky | H39: =_xlfn.XLOOKUP(Table1[[#This Row],[Shipment Number]], 'pivot '!A:A,'pivot '!G:G, "NF") -> #DIV/0! | I39: =_xlfn.XLOOKUP(Table1[[#This Row],[Party Name]], [1]Billing!$Q$5:$Q$40, [1]Billing!$U$5:$U$40) -> 117213.79 | J39: =_xlfn.XLOOKUP(Table1[[#This Row],[Party Name]], [1]Billing!$Q$5:$Q$40, [1]Billing!$W$5:$W$40) -> 1460624.5
... A53: 45979 | B53: Ahmad Javaid | C53: November Closing CF | D53: Silky | H53: =_xlfn.XLOOKUP(Table1[[#This Row],[Shipment Number]], 'pivot '!A:A,'pivot '!G:G, "NF") -> #DIV/0! | I53: =_xlfn.XLOOKUP(Table1[[#This Row],[Party Name]], [1]Billing!$Q$5:$Q$40, [1]Billing!$U$5:$U$40) -> 0 | J53: =_xlfn.XLOOKUP(Table1[[#This Row],[Party Name]], [1]Billing!$Q$5:$Q$40, [1]Billing!$W$5:$W$40) -> 0
A54: 45979 | B54: Sajad Khan | C54: November Closing CF | D54: Slub | H54: =_xlfn.XLOOKUP(Table1[[#This Row],[Shipment Number]], 'pivot '!A:A,'pivot '!G:G, "NF") -> #DIV/0! | J54: =_xlfn.XLOOKUP(Table1[[#This Row],[Party Name]], [1]Billing!$Q$5:$Q$40, [1]Billing!$X$5:$X$40) -> 71359.729
A55: 45979 | B55: Faizan | C55: November Closing CF | D55: Slub | H55: =_xlfn.XLOOKUP(Table1[[#This Row],[Shipment Number]], 'pivot '!A:A,'pivot '!G:G, "NF") -> #DIV/0! | J55: =_xlfn.XLOOKUP(Table1[[#This Row],[Party Name]], [1]Billing!$Q$5:$Q$40, [1]Billing!$X$5:$X$40) -> 44550.11
A56: 45979 | B56: Shafique Ansari | C56: November Closing CF | D56: Satin | H56: =_xlfn.XLOOKUP(Table1[[#This Row],[Shipment Number]], 'pivot '!A:A,'pivot '!G:G, "NF") -> #DIV/0! | J56: =_xlfn.XLOOKUP(Table1[[#This Row],[Party Name]], [1]Billing!$Q$5:$Q$40, [1]Billing!$Y$5:$Y$40) -> 94656.181
A57: 45979 | B57: Salman Zaffar | C57: November Closing CF | D57: Black-Chamki | H57: =_xlfn.XLOOKUP(Table1[[#This Row],[Shipment Number]], 'pivot '!A:A,'pivot '!G:G, "NF") -> #DIV/0! | J57: =_xlfn.XLOOKUP(Table1[[#This Row],[Party Name]], [1]Billing!$Q$5:$Q$40, [1]Billing!$Z$5:$Z$40) -> 161653.26
A58: 45979 | B58: Shahid Qasayi | C58: November Closing CF | D58: Kataan | H58: =_xlfn.XLOOKUP(Table1[[#This Row],[Shipment Number]], 'pivot '!A:A,'pivot '!G:G, "NF") -> #DIV/0! | J58: =_xlfn.XLOOKUP(Table1[[#This Row],[Party Name]], [1]Billing!$Q$5:$Q$40, [1]Billing!$AA$5:$AA$40) -> 523143.75
A59: 45979 | B59: Ahmad Javaid | C59: November Closing CF | D59: Munaar | H59: =_xlfn.XLOOKUP(Table1[[#This Row],[Shipment Number]], 'pivot '!A:A,'pivot '!G:G, "NF") -> #DIV/0! | J59: =_xlfn.XLOOKUP(Table1[[#This Row],[Party Name]], [1]Billing!$Q$5:$Q$40, [1]Billing!$AB$5:$AB$40) -> 54170.629
A60: 46009 | B60: Azam | C60: 1256 | D60: Chamki | E60: 1971 | F60: 50697 | G60: 49746 | H60: =_xlfn.XLOOKUP(Table1[[#This Row],[Shipment Number]], 'pivot '!A:A,'pivot '!G:G, "NF") -> 10.274187 | I60: =Table1[[#This Row],[Tiyaar/gaz]]/1.0936 -> 45488.296 | J60: {=_xlfn.IFS( AND(Table1[[#This Row],[Party Name]]="Faizan",Table1[[#This Row],[Quality]]="Silky"),Table1[[#This Row],[tiyar/meters]]*13, AND(Table1[[#This Row],[Party Name]]="Sajad Khan",Table1[[#This Row],[Quality]]="Slub"),Table1[[#This Row],[tiyar/meters]]*13, AND(Table1[[#This Row],[Party Name]]="Faizan",Table1[[#This Row],[Quality]]="Slub"),Table1[[#This Row],[tiyar/meters]]*15, AND(Table1[[#This Row],[Party Name]]="Shafique Ansari",Table1[[#This Row],[Quality]]="Satin"),Table1[[#This Row],[tiyar/meters]]*28, Table1[[#This Row],[Quality]]="Chamki",Table1[[#This Row],[tiyar/meters]]*10, Table1[[#This Row],[Quality]]="Black-Chamki",Table1[[#This Row],[tiyar/meters]]*12, Table1[[#This Row],[Quality]]="Silky",Table1[[#This Row],[tiyar/meters]]*13, Table1[[#This Row],[Quality]]="Crinkle",Table1[[#This Row],[tiyar/meters]]*10,Table1[[#This Row],[Quality]]="Kataan",Table1[[#This Row],[tiyar/meters]]*11,Table1[[#This Row],[Quality]]="Munaar",Table1[[#This Row],[tiyar/meters]]*13 )} -> 454882.96
A61: 46009 | B61: Arshad | C61: 1257 | D61: Chamki | E61: 1951 | F61: 54197 | G61: 28916 | H61: =_xlfn.XLOOKUP(Table1[[#This Row],[Shipment Number]], 'pivot '!A:A,'pivot '!G:G, "NF") -> 1.6396859 | I61: =Table1[[#This Row],[Tiyaar/gaz]]/1.0936 -> 26441.112 | J61: {=_xlfn.IFS( AND(Table1[[#This Row],[Party Name]]="Faizan",Table1[[#This Row],[Quality]]="Silky"),Table1[[#This Row],[tiyar/meters]]*13, AND(Table1[[#This Row],[Party Name]]="Sajad Khan",Table1[[#This Row],[Quality]]="Slub"),Table1[[#This Row],[tiyar/meters]]*13, AND(Table1[[#This Row],[Party Name]]="Faizan",Table1[[#This Row],[Quality]]="Slub"),Table1[[#This Row],[tiyar/meters]]*15, AND(Table1[[#This Row],[Party Name]]="Shafique Ansari",Table1[[#This Row],[Quality]]="Satin"),Table1[[#This Row],[tiyar/meters]]*28, Table1[[#This Row],[Quality]]="Chamki",Table1[[#This Row],[tiyar/meters]]*10, Table1[[#This Row],[Quality]]="Black-Chamki",Table1[[#This Row],[tiyar/meters]]*12, Table1[[#This Row],[Quality]]="Silky",Table1[[#This Row],[tiyar/meters]]*13, Table1[[#This Row],[Quality]]="Crinkle",Table1[[#This Row],[tiyar/meters]]*10,Table1[[#This Row],[Quality]]="Kataan",Table1[[#This Row],[tiyar/meters]]*11,Table1[[#This Row],[Quality]]="Munaar",Table1[[#This Row],[tiyar/meters]]*13 )} -> 264411.12
A62: 46009 | B62: Badshah Fabrics | C62: 1258 | D62: Chamki | E62: 1934 | F62: 38741 | G62: 12375 | H62: =_xlfn.XLOOKUP(Table1[[#This Row],[Shipment Number]], 'pivot '!A:A,'pivot '!G:G, "NF") -> 2.6934958 | I62: =Table1[[#This Row],[Tiyaar/gaz]]/1.0936 -> 11315.838 | J62: {=_xlfn.IFS( AND(Table1[[#This Row],[Party Name]]="Faizan",Table1[[#This Row],[Quality]]="Silky"),Table1[[#This Row],[tiyar/meters]]*13, AND(Table1[[#This Row],[Party Name]]="Sajad Khan",Table1[[#This Row],[Quality]]="Slub"),Table1[[#This Row],[tiyar/meters]]*13, AND(Table1[[#This Row],[Party Name]]="Faizan",Table1[[#This Row],[Quality]]="Slub"),Table1[[#This Row],[tiyar/meters]]*15, AND(Table1[[#This Row],[Party Name]]="Shafique Ansari",Table1[[#This Row],[Quality]]="Satin"),Table1[[#This Row],[tiyar/meters]]*28, Table1[[#This Row],[Quality]]="Chamki",Table1[[#This Row],[tiyar/meters]]*10, Table1[[#This Row],[Quality]]="Black-Chamki",Table1[[#This Row],[tiyar/meters]]*12, Table1[[#This Row],[Quality]]="Silky",Table1[[#This Row],[tiyar/meters]]*13, Table1[[#This Row],[Quality]]="Crinkle",Table1[[#This Row],[tiyar/meters]]*10,Table1[[#This Row],[Quality]]="Kataan",Table1[[#This Row],[tiyar/meters]]*11,Table1[[#This Row],[Quality]]="Munaar",Table1[[#This Row],[tiyar/meters]]*13 )} -> 113158.38
A63: 46010 | B63: Badshah Fabrics | C63: 1259 | D63: Chamki | E63: 1934 | F63: 38741 | G63: 28851 | H63: =_xlfn.XLOOKUP(Table1[[#This Row],[Shipment Number]], 'pivot '!A:A,'pivot '!G:G, "NF") -> 2.6934958 | I63: =Table1[[#This Row],[Tiyaar/gaz]]/1.0936 -> 26381.675 | J63: {=_xlfn.IFS( AND(Table1[[#This Row],[Party Name]]="Faizan",Table1[[#This Row],[Quality]]="Silky"),Table1[[#This Row],[tiyar/meters]]*13, AND(Table1[[#This Row],[Party Name]]="Sajad Khan",Table1[[#This Row],[Quality]]="Slub"),Table1[[#This Row],[tiyar/meters]]*13, AND(Table1[[#This Row],[Party Name]]="Faizan",Table1[[#This Row],[Quality]]="Slub"),Table1[[#This Row],[tiyar/meters]]*15, AND(Table1[[#This Row],[Party Name]]="Shafique Ansari",Table1[[#This Row],[Quality]]="Satin"),Table1[[#This Row],[tiyar/meters]]*28, Table1[[#This Row],[Quality]]="Chamki",Table1[[#This Row],[tiyar/meters]]*10, Table1[[#This Row],[Quality]]="Black-Chamki",Table1[[#This Row],[tiyar/meters]]*12, Table1[[#This Row],[Quality]]="Silky",Table1[[#This Row],[tiyar/meters]]*13, Table1[[#This Row],[Quality]]="Crinkle",Table1[[#This Row],[tiyar/meters]]*10,Table1[[#This Row],[Quality]]="Kataan",Table1[[#This Row],[tiyar/meters]]*11,Table1[[#This Row],[Quality]]="Munaar",Table1[[#This Row],[tiyar/meters]]*13 )} -> 263816.75
A64: 46010 | B64: Badshah Fabrics | C64: 1260 | D64: Chamki | E64: 1924 | F64: 24876 | G64: 16411 | H64: =_xlfn.XLOOKUP(Table1[[#This Row],[Shipment Number]], 'pivot '!A:A,'pivot '!G:G, "NF") -> 2.9237689 | I64: =Table1[[#This Row],[Tiyaar/gaz]]/1.0936 -> 15006.401 | J64: {=_xlfn.IFS( AND(Table1[[#This Row],[Party Name]]="Faizan",Table1[[#This Row],[Quality]]="Silky"),Table1[[#This Row],[tiyar/meters]]*13, AND(Table1[[#This Row],[Party Name]]="Sajad Khan",Table1[[#This Row],[Quality]]="Slub"),Table1[[#This Row],[tiyar/meters]]*13, AND(Table1[[#This Row],[Party Name]]="Faizan",Table1[[#This Row],[Quality]]="Slub"),Table1[[#This Row],[tiyar/meters]]*15, AND(Table1[[#This Row],[Party Name]]="Shafique Ansari",Table1[[#This Row],[Quality]]="Satin"),Table1[[#This Row],[tiyar/meters]]*28, Table1[[#This Row],[Quality]]="Chamki",Table1[[#This Row],[tiyar/meters]]*10, Table1[[#This Row],[Quality]]="Black-Chamki",Table1[[#This Row],[tiyar/meters]]*12, Table1[[#This Row],[Quality]]="Silky",Table1[[#This Row],[tiyar/meters]]*13, Table1[[#This Row],[Quality]]="Crinkle",Table1[[#This Row],[tiyar/meters]]*10,Table1[[#This Row],[Quality]]="Kataan",Table1[[#This Row],[tiyar/meters]]*11,Table1[[#This Row],[Quality]]="Munaar",Table1[[#This Row],[tiyar/meters]]*13 )} -> 150064.01
A65: 46011 | B65: Arshad | C65: 1261 | D65: Chamki | E65: 1951 | F65: 54197 | G65: 10108 | H65: =_xlfn.XLOOKUP(Table1[[#This Row],[Shipment Number]], 'pivot '!A:A,'pivot '!G:G, "NF") -> 1.6396859 | I65: =Table1[[#This Row],[Tiyaar/gaz]]/1.0936 -> 9242.8676 | J65: {=_xlfn.IFS( AND(Table1[[#This Row],[Party Name]]="Faizan",Table1[[#This Row],[Quality]]="Silky"),Table1[[#This Row],[tiyar/meters]]*13, AND(Table1[[#This Row],[Party Name]]="Sajad Khan",Table1[[#This Row],[Quality]]="Slub"),Table1[[#This Row],[tiyar/meters]]*13, AND(Table1[[#This Row],[Party Name]]="Faizan",Table1[[#This Row],[Quality]]="Slub"),Table1[[#This Row],[tiyar/meters]]*15, AND(Table1[[#This Row],[Party Name]]="Shafique Ansari",Table1[[#This Row],[Quality]]="Satin"),Table1[[#This Row],[tiyar/meters]]*28, Table1[[#This Row],[Quality]]="Chamki",Table1[[#This Row],[tiyar/meters]]*10, Table1[[#This Row],[Quality]]="Black-Chamki",Table1[[#This Row],[tiyar/meters]]*12, Table1[[#This Row],[Quality]]="Silky",Table1[[#This Row],[tiyar/meters]]*13, Table1[[#This Row],[Quality]]="Crinkle",Table1[[#This Row],[tiyar/meters]]*10,Table1[[#This Row],[Quality]]="Kataan",Table1[[#This Row],[tiyar/meters]]*11,Table1[[#This Row],[Quality]]="Munaar",Table1[[#This Row],[tiyar/meters]]*13 )} -> 92428.676
A66: 46011 | B66: Badshah Fabrics | C66: 1262 | D66: Chamki | E66: 1924 | F66: 24876 | G66: 7846 | H66: =_xlfn.XLOOKUP(Table1[[#This Row],[Shipment Number]], 'pivot '!A:A,'pivot '!G:G, "NF") -> 2.9237689 | I66: =Table1[[#This Row],[Tiyaar/gaz]]/1.0936 -> 7174.4696 | J66: {=_xlfn.IFS( AND(Table1[[#This Row],[Party Name]]="Faizan",Table1[[#This Row],[Quality]]="Silky"),Table1[[#This Row],[tiyar/meters]]*13, AND(Table1[[#This Row],[Party Name]]="Sajad Khan",Table1[[#This Row],[Quality]]="Slub"),Table1[[#This Row],[tiyar/meters]]*13, AND(Table1[[#This Row],[Party Name]]="Faizan",Table1[[#This Row],[Quality]]="Slub"),Table1[[#This Row],[tiyar/meters]]*15, AND(Table1[[#This Row],[Party Name]]="Shafique Ansari",Table1[[#This Row],[Quality]]="Satin"),Table1[[#This Row],[tiyar/meters]]*28, Table1[[#This Row],[Quality]]="Chamki",Table1[[#This Row],[tiyar/meters]]*10, Table1[[#This Row],[Quality]]="Black-Chamki",Table1[[#This Row],[tiyar/meters]]*12, Table1[[#This Row],[Quality]]="Silky",Table1[[#This Row],[tiyar/meters]]*13, Table1[[#This Row],[Quality]]="Crinkle",Table1[[#This Row],[tiyar/meters]]*10,Table1[[#This Row],[Quality]]="Kataan",Table1[[#This Row],[tiyar/meters]]*11,Table1[[#This Row],[Quality]]="Munaar",Table1[[#This Row],[tiyar/meters]]*13 )} -> 71744.696
A67: 46011 | B67: Badshah Fabrics | C67: 1263 | D67: crinkle | E67: 1835 | F67: 50010 | G67: 25414 | H67: =_xlfn.XLOOKUP(Table1[[#This Row],[Shipment Number]], 'pivot '!A:A,'pivot '!G:G, "NF") -> 7.1820603 | I67: =Table1[[#This Row],[Tiyaar/gaz]]/1.0936 -> 23238.844 | J67: {=_xlfn.IFS( AND(Table1[[#This Row],[Party Name]]="Faizan",Table1[[#This Row],[Quality]]="Silky"),Table1[[#This Row],[tiyar/meters]]*13, AND(Table1[[#This Row],[Party Name]]="Sajad Khan",Table1[[#This Row],[Quality]]="Slub"),Table1[[#This Row],[tiyar/meters]]*13, AND(Table1[[#This Row],[Party Name]]="Faizan",Table1[[#This Row],[Quality]]="Slub"),Table1[[#This Row],[tiyar/meters]]*15, AND(Table1[[#This Row],[Party Name]]="Shafique Ansari",Table1[[#This Row],[Quality]]="Satin"),Table1[[#This Row],[tiyar/meters]]*28, Table1[[#This Row],[Quality]]="Chamki",Table1[[#This Row],[tiyar/meters]]*10, Table1[[#This Row],[Quality]]="Black-Chamki",Table1[[#This Row],[tiyar/meters]]*12, Table1[[#This Row],[Quality]]="Silky",Table1[[#This Row],[tiyar/meters]]*13, Table1[[#This Row],[Quality]]="Crinkle",Table1[[#This Row],[tiyar/meters]]*10,Table1[[#This Row],[Quality]]="Kataan",Table1[[#This Row],[tiyar/meters]]*11,Table1[[#This Row],[Quality]]="Munaar",Table1[[#This Row],[tiyar/meters]]*13 )} -> 232388.44
A68: 46013 | B68: BSC | C68: 1264 | D68: crinkle | E68: 1628 | F68: 48198 | G68: 10049 | H68: =_xlfn.XLOOKUP(Table1[[#This Row],[Shipment Number]], 'pivot '!A:A,'pivot '!G:G, "NF") -> 20.998452 | I68: =Table1[[#This Row],[Tiyaar/gaz]]/1.0936 -> 9188.9173 | J68: {=_xlfn.IFS( AND(Table1[[#This Row],[Party Name]]="Faizan",Table1[[#This Row],[Quality]]="Silky"),Table1[[#This Row],[tiyar/meters]]*13, AND(Table1[[#This Row],[Party Name]]="Sajad Khan",Table1[[#This Row],[Quality]]="Slub"),Table1[[#This Row],[tiyar/meters]]*13, AND(Table1[[#This Row],[Party Name]]="Faizan",Table1[[#This Row],[Quality]]="Slub"),Table1[[#This Row],[tiyar/meters]]*15, AND(Table1[[#This Row],[Party Name]]="Shafique Ansari",Table1[[#This Row],[Quality]]="Satin"),Table1[[#This Row],[tiyar/meters]]*28, Table1[[#This Row],[Quality]]="Chamki",Table1[[#This Row],[tiyar/meters]]*10, Table1[[#This Row],[Quality]]="Black-Chamki",Table1[[#This Row],[tiyar/meters]]*12, Table1[[#This Row],[Quality]]="Silky",Table1[[#This Row],[tiyar/meters]]*13, Table1[[#This Row],[Quality]]="Crinkle",Table1[[#This Row],[tiyar/meters]]*10,Table1[[#This Row],[Quality]]="Kataan",Table1[[#This Row],[tiyar/meters]]*11,Table1[[#This Row],[Quality]]="Munaar",Table1[[#This Row],[tiyar/meters]]*13 )} -> 91889.173
A69: 46013 | B69: Badshah Fabrics | C69: 1265 | D69: crinkle | E69: 1835 | F69: 50010 | G69: 25349 | H69: =_xlfn.XLOOKUP(Table1[[#This Row],[Shipment Number]], 'pivot '!A:A,'pivot '!G:G, "NF") -> 7.1820603 | I69: =Table1[[#This Row],[Tiyaar/gaz]]/1.0936 -> 23179.407 | J69: {=_xlfn.IFS( AND(Table1[[#This Row],[Party Name]]="Faizan",Table1[[#This Row],[Quality]]="Silky"),Table1[[#This Row],[tiyar/meters]]*13, AND(Table1[[#This Row],[Party Name]]="Sajad Khan",Table1[[#This Row],[Quality]]="Slub"),Table1[[#This Row],[tiyar/meters]]*13, AND(Table1[[#This Row],[Party Name]]="Faizan",Table1[[#This Row],[Quality]]="Slub"),Table1[[#This Row],[tiyar/meters]]*15, AND(Table1[[#This Row],[Party Name]]="Shafique Ansari",Table1[[#This Row],[Quality]]="Satin"),Table1[[#This Row],[tiyar/meters]]*28, Table1[[#This Row],[Quality]]="Chamki",Table1[[#This Row],[tiyar/meters]]*10, Table1[[#This Row],[Quality]]="Black-Chamki",Table1[[#This Row],[tiyar/meters]]*12, Table1[[#This Row],[Quality]]="Silky",Table1[[#This Row],[tiyar/meters]]*13, Table1[[#This Row],[Quality]]="Crinkle",Table1[[#This Row],[tiyar/meters]]*10,Table1[[#This Row],[Quality]]="Kataan",Table1[[#This Row],[tiyar/meters]]*11,Table1[[#This Row],[Quality]]="Munaar",Table1[[#This Row],[tiyar/meters]]*13 )} -> 231794.07
